Workbook

Sheet README
A1: Item | B1: Value
A2: Annotator Agreement Manual Review Workbook
A3: Annotator A | B3: 1
A4: Annotator B | B4: (2, 3)
A5: Paired completed documents | B5: 140
A6: Document-feature comparisons | B6: 560
A7: Rows in Review Queue | B7: 63
A9: How to review | B9: Open Review Queue and inspect only the rows where the annotators differ.
A10: TP | B10: Same underlying entity/value annotated by both annotators.
A11: FP | B11: Value annotated only by Annotator 1.
A12: FN | B12: Value annotated only by Annotator (2, 3).
A13: Manual override | B13: Fill ALL THREE manual_TP/manual_FP/manual_FN cells. Partial overrides are flagged INCOMPLETE.
A14: Reviewed text | B14: Edit the two *_reviewed columns when differently worded annotations should be treated as the same value. These reviewed strings are used for the reviewed Cohen's kappa after rerunning the notebook.
A15: Exclude | B15: Set exclude = Yes only when the comparison should not be part of agreement analysis.
... A18: Span differences | B18: Same value at a different occurrence/span is already treated as value-level agreement and does not enter the Review Queue.

Sheet Scores
A1: Feature | B1: Comparisons | C1: Full agreements | D1: Agreement | E1: TP | F1: FP | G1: FN | H1: Precision (A1) | I1: Recall (A1) | J1: F1 | K1: Needs review | L1: Incomplete overrides
A2: Ontvanger | B2: =COUNTIFS('All Comparisons'!$D$2:$D$561,$A2)-COUNTIFS('Review Queue'!$D$2:$D$64,$A2,'Review Queue'!$X$2:$X$64,"Yes") -> 140 | C2: =SUMIFS('All Comparisons'!$R$2:$R$561,'All Comparisons'!$D$2:$D$561,$A2)+SUMIFS('Review Queue'!$AE$2:$AE$64,'Review Queue'!$D$2:$D$64,$A2)-SUMIFS('Review Queue'!$R$2:$R$64,'Review Queue'!$D$2:$D$64,$A2) -> 119 | D2: =IFERROR(C2/B2,0) -> 0.85 | E2: =SUMIFS('All Comparisons'!$O$2:$O$561,'All Comparisons'!$D$2:$D$561,$A2)+SUMIFS('Review Queue'!$AB$2:$AB$64,'Review Queue'!$D$2:$D$64,$A2)-SUMIFS('Review Queue'!$O$2:$O$64,'Review Queue'!$D$2:$D$64,$A2) -> 115 | F2: =SUMIFS('All Comparisons'!$P$2:$P$561,'All Comparisons'!$D$2:$D$561,$A2)+SUMIFS('Review Queue'!$AC$2:$AC$64,'Review Queue'!$D$2:$D$64,$A2)-SUMIFS('Review Queue'!$P$2:$P$64,'Review Queue'!$D$2:$D$64,$A2) -> 6 | G2: =SUMIFS('All Comparisons'!$Q$2:$Q$561,'All Comparisons'!$D$2:$D$561,$A2)+SUMIFS('Review Queue'!$AD$2:$AD$64,'Review Queue'!$D$2:$D$64,$A2)-SUMIFS('Review Queue'!$Q$2:$Q$64,'Review Queue'!$D$2:$D$64,$A2) -> 21 | H2: =IFERROR(E2/(E2+F2),0) -> 0.95041322 | I2: =IFERROR(E2/(E2+G2),0) -> 0.84558824 | J2: =IFERROR(2*H2*I2/(H2+I2),0) -> 0.89494163 | K2: =COUNTIFS('Review Queue'!$D$2:$D$64,$A2,'Review Queue'!$Y$2:$Y$64,"<>Reviewed",'Review Queue'!$X$2:$X$64,"<>Yes") -> 40 | L2: =COUNTIFS('Review Queue'!$D$2:$D$64,$A2,'Review Queue'!$AA$2:$AA$64,"INCOMPLETE") -> 0
A3: Besluitvormend Orgaan | B3: =COUNTIFS('All Comparisons'!$D$2:$D$561,$A3)-COUNTIFS('Review Queue'!$D$2:$D$64,$A3,'Review Queue'!$X$2:$X$64,"Yes") -> 140 | C3: =SUMIFS('All Comparisons'!$R$2:$R$561,'All Comparisons'!$D$2:$D$561,$A3)+SUMIFS('Review Queue'!$AE$2:$AE$64,'Review Queue'!$D$2:$D$64,$A3)-SUMIFS('Review Queue'!$R$2:$R$64,'Review Queue'!$D$2:$D$64,$A3) -> 136 | D3: =IFERROR(C3/B3,0) -> 0.97142857 | E3: =SUMIFS('All Comparisons'!$O$2:$O$561,'All Comparisons'!$D$2:$D$561,$A3)+SUMIFS('Review Queue'!$AB$2:$AB$64,'Review Queue'!$D$2:$D$64,$A3)-SUMIFS('Review Queue'!$O$2:$O$64,'Review Queue'!$D$2:$D$64,$A3) -> 136 | F3: =SUMIFS('All Comparisons'!$P$2:$P$561,'All Comparisons'!$D$2:$D$561,$A3)+SUMIFS('Review Queue'!$AC$2:$AC$64,'Review Queue'!$D$2:$D$64,$A3)-SUMIFS('Review Queue'!$P$2:$P$64,'Review Queue'!$D$2:$D$64,$A3) -> 2 | G3: =SUMIFS('All Comparisons'!$Q$2:$Q$561,'All Comparisons'!$D$2:$D$561,$A3)+SUMIFS('Review Queue'!$AD$2:$AD$64,'Review Queue'!$D$2:$D$64,$A3)-SUMIFS('Review Queue'!$Q$2:$Q$64,'Review Queue'!$D$2:$D$64,$A3) -> 4 | H3: =IFERROR(E3/(E3+F3),0) -> 0.98550725 | I3: =IFERROR(E3/(E3+G3),0) -> 0.97142857 | J3: =IFERROR(2*H3*I3/(H3+I3),0) -> 0.97841727 | K3: =COUNTIFS('Review Queue'!$D$2:$D$64,$A3,'Review Queue'!$Y$2:$Y$64,"<>Reviewed",'Review Queue'!$X$2:$X$64,"<>Yes") -> 8 | L3: =COUNTIFS('Review Queue'!$D$2:$D$64,$A3,'Review Queue'!$AA$2:$AA$64,"INCOMPLETE") -> 0
A4: Rechtshandeling | B4: =COUNTIFS('All Comparisons'!$D$2:$D$561,$A4)-COUNTIFS('Review Queue'!$D$2:$D$64,$A4,'Review Queue'!$X$2:$X$64,"Yes") -> 140 | C4: =SUMIFS('All Comparisons'!$R$2:$R$561,'All Comparisons'!$D$2:$D$561,$A4)+SUMIFS('Review Queue'!$AE$2:$AE$64,'Review Queue'!$D$2:$D$64,$A4)-SUMIFS('Review Queue'!$R$2:$R$64,'Review Queue'!$D$2:$D$64,$A4) -> 138 | D4: =IFERROR(C4/B4,0) -> 0.98571429 | E4: =SUMIFS('All Comparisons'!$O$2:$O$561,'All Comparisons'!$D$2:$D$561,$A4)+SUMIFS('Review Queue'!$AB$2:$AB$64,'Review Queue'!$D$2:$D$64,$A4)-SUMIFS('Review Queue'!$O$2:$O$64,'Review Queue'!$D$2:$D$64,$A4) -> 139 | F4: =SUMIFS('All Comparisons'!$P$2:$P$561,'All Comparisons'!$D$2:$D$561,$A4)+SUMIFS('Review Queue'!$AC$2:$AC$64,'Review Queue'!$D$2:$D$64,$A4)-SUMIFS('Review Queue'!$P$2:$P$64,'Review Queue'!$D$2:$D$64,$A4) -> 2 | G4: =SUMIFS('All Comparisons'!$Q$2:$Q$561,'All Comparisons'!$D$2:$D$561,$A4)+SUMIFS('Review Queue'!$AD$2:$AD$64,'Review Queue'!$D$2:$D$64,$A4)-SUMIFS('Review Queue'!$Q$2:$Q$64,'Review Queue'!$D$2:$D$64,$A4) -> 2 | H4: =IFERROR(E4/(E4+F4),0) -> 0.9858156 | I4: =IFERROR(E4/(E4+G4),0) -> 0.9858156 | J4: =IFERROR(2*H4*I4/(H4+I4),0) -> 0.9858156 | K4: =COUNTIFS('Review Queue'!$D$2:$D$64,$A4,'Review Queue'!$Y$2:$Y$64,"<>Reviewed",'Review Queue'!$X$2:$X$64,"<>Yes") -> 9 | L4: =COUNTIFS('Review Queue'!$D$2:$D$64,$A4,'Review Queue'!$AA$2:$AA$64,"INCOMPLETE") -> 0
A5: Rechtsobject | B5: =COUNTIFS('All Comparisons'!$D$2:$D$561,$A5)-COUNTIFS('Review Queue'!$D$2:$D$64,$A5,'Review Queue'!$X$2:$X$64,"Yes") -> 140 | C5: =SUMIFS('All Comparisons'!$R$2:$R$561,'All Comparisons'!$D$2:$D$561,$A5)+SUMIFS('Review Queue'!$AE$2:$AE$64,'Review Queue'!$D$2:$D$64,$A5)-SUMIFS('Review Queue'!$R$2:$R$64,'Review Queue'!$D$2:$D$64,$A5) -> 139 | D5: =IFERROR(C5/B5,0) -> 0.99285714 | E5: =SUMIFS('All Comparisons'!$O$2:$O$561,'All Comparisons'!$D$2:$D$561,$A5)+SUMIFS('Review Queue'!$AB$2:$AB$64,'Review Queue'!$D$2:$D$64,$A5)-SUMIFS('Review Queue'!$O$2:$O$64,'Review Queue'!$D$2:$D$64,$A5) -> 140 | F5: =SUMIFS('All Comparisons'!$P$2:$P$561,'All Comparisons'!$D$2:$D$561,$A5)+SUMIFS('Review Queue'!$AC$2:$AC$64,'Review Queue'!$D$2:$D$64,$A5)-SUMIFS('Review Queue'!$P$2:$P$64,'Review Queue'!$D$2:$D$64,$A5) -> 1 | G5: =SUMIFS('All Comparisons'!$Q$2:$Q$561,'All Comparisons'!$D$2:$D$561,$A5)+SUMIFS('Review Queue'!$AD$2:$AD$64,'Review Queue'!$D$2:$D$64,$A5)-SUMIFS('Review Queue'!$Q$2:$Q$64,'Review Queue'!$D$2:$D$64,$A5) -> 0 | H5: =IFERROR(E5/(E5+F5),0) -> 0.9929078 | I5: =IFERROR(E5/(E5+G5),0) -> 1 | J5: =IFERROR(2*H5*I5/(H5+I5),0) -> 0.99644128 | K5: =COUNTIFS('Review Queue'!$D$2:$D$64,$A5,'Review Queue'!$Y$2:$Y$64,"<>Reviewed",'Review Queue'!$X$2:$X$64,"<>Yes") -> 6 | L5: =COUNTIFS('Review Queue'!$D$2:$D$64,$A5,'Review Queue'!$AA$2:$AA$64,"INCOMPLETE") -> 0
A6: Overall | B6: =560-COUNTIFS('Review Queue'!$X$2:$X$64,"Yes") -> 560 | C6: =SUM('All Comparisons'!$R$2:$R$561)+SUM('Review Queue'!$AE$2:$AE$64)-SUM('Review Queue'!$R$2:$R$64) -> 532 | D6: =IFERROR(C6/B6,0) -> 0.95 | E6: =SUM('All Comparisons'!$O$2:$O$561)+SUM('Review Queue'!$AB$2:$AB$64)-SUM('Review Queue'!$O$2:$O$64) -> 530 | F6: =SUM('All Comparisons'!$P$2:$P$561)+SUM('Review Queue'!$AC$2:$AC$64)-SUM('Review Queue'!$P$2:$P$64) -> 11 | G6: =SUM('All Comparisons'!$Q$2:$Q$561)+SUM('Review Queue'!$AD$2:$AD$64)-SUM('Review Queue'!$Q$2:$Q$64) -> 27 | H6: =IFERROR(E6/(E6+F6),0) -> 0.97966728 | I6: =IFERROR(E6/(E6+G6),0) -> 0.95152603 | J6: =IFERROR(2*H6*I6/(H6+I6),0) -> 0.96539162 | K6: =COUNTIFS('Review Queue'!$Y$2:$Y$64,"<>Reviewed",'Review Queue'!$X$2:$X$64,"<>Yes") -> 63 | L6: =COUNTIFS('Review Queue'!$AA$2:$AA$64,"INCOMPLETE") -> 0

Sheet Scores by Authority
A1: Authority | B1: Feature | C1: Comparisons | D1: Full agreements | E1: Agreement | F1: TP | G1: FP | H1: FN | I1: Precision (A1) | J1: Recall (A1) | K1: F1 | L1: Needs review | M1: Incomplete overrides
A2: ACM | B2: Ontvanger | C2: =COUNTIFS('All Comparisons'!$C$2:$C$561,$A2,'All Comparisons'!$D$2:$D$561,$B2)-COUNTIFS('Review Queue'!$C$2:$C$64,$A2,'Review Queue'!$D$2:$D$64,$B2,'Review Queue'!$X$2:$X$64,"Yes") -> 20 | D2: =SUMIFS('All Comparisons'!$R$2:$R$561,'All Comparisons'!$C$2:$C$561,$A2,'All Comparisons'!$D$2:$D$561,$B2)+SUMIFS('Review Queue'!$AE$2:$AE$64,'Review Queue'!$C$2:$C$64,$A2,'Review Queue'!$D$2:$D$64,$B2)-SUMIFS('Review Queue'!$R$2:$R$64,'Review Queue'!$C$2:$C$64,$A2,'Review Queue'!$D$2:$D$64,$B2) -> 20 | E2: =IFERROR(D2/C2,0) -> 1 | F2: =SUMIFS('All Comparisons'!$O$2:$O$561,'All Comparisons'!$C$2:$C$561,$A2,'All Comparisons'!$D$2:$D$561,$B2)+SUMIFS('Review Queue'!$AB$2:$AB$64,'Review Queue'!$C$2:$C$64,$A2,'Review Queue'!$D$2:$D$64,$B2)-SUMIFS('Review Queue'!$O$2:$O$64,'Review Queue'!$C$2:$C$64,$A2,'Review Queue'!$D$2:$D$64,$B2) -> 22 | G2: =SUMIFS('All Comparisons'!$P$2:$P$561,'All Comparisons'!$C$2:$C$561,$A2,'All Comparisons'!$D$2:$D$561,$B2)+SUMIFS('Review Queue'!$AC$2:$AC$64,'Review Queue'!$C$2:$C$64,$A2,'Review Queue'!$D$2:$D$64,$B2)-SUMIFS('Review Queue'!$P$2:$P$64,'Review Queue'!$C$2:$C$64,$A2,'Review Queue'!$D$2:$D$64,$B2) -> 0 | H2: =SUMIFS('All Comparisons'!$Q$2:$Q$561,'All Comparisons'!$C$2:$C$561,$A2,'All Comparisons'!$D$2:$D$561,$B2)+SUMIFS('Review Queue'!$AD$2:$AD$64,'Review Queue'!$C$2:$C$64,$A2,'Review Queue'!$D$2:$D$64,$B2)-SUMIFS('Review Queue'!$Q$2:$Q$64,'Review Queue'!$C$2:$C$64,$A2,'Review Queue'!$D$2:$D$64,$B2) -> 0 | I2: =IFERROR(F2/(F2+G2),0) -> 1 | J2: =IFERROR(F2/(F2+H2),0) -> 1 | K2: =IFERROR(2*I2*J2/(I2+J2),0) -> 1 | L2: =COUNTIFS('Review Queue'!$C$2:$C$64,$A2,'Review Queue'!$D$2:$D$64,$B2,'Review Queue'!$Y$2:$Y$64,"<>Reviewed",'Review Queue'!$X$2:$X$64,"<>Yes") -> 2 | M2: =COUNTIFS('Review Queue'!$C$2:$C$64,$A2,'Review Queue'!$D$2:$D$64,$B2,'Review Queue'!$AA$2:$AA$64,"INCOMPLETE") -> 0
A3: ACM | B3: Besluitvormend Orgaan | C3: =COUNTIFS('All Comparisons'!$C$2:$C$561,$A3,'All Comparisons'!$D$2:$D$561,$B3)-COUNTIFS('Review Queue'!$C$2:$C$64,$A3,'Review Queue'!$D$2:$D$64,$B3,'Review Queue'!$X$2:$X$64,"Yes") -> 20 | D3: =SUMIFS('All Comparisons'!$R$2:$R$561,'All Comparisons'!$C$2:$C$561,$A3,'All Comparisons'!$D$2:$D$561,$B3)+SUMIFS('Review Queue'!$AE$2:$AE$64,'Review Queue'!$C$2:$C$64,$A3,'Review Queue'!$D$2:$D$64,$B3)-SUMIFS('Review Queue'!$R$2:$R$64,'Review Queue'!$C$2:$C$64,$A3,'Review Queue'!$D$2:$D$64,$B3) -> 20 | E3: =IFERROR(D3/C3,0) -> 1 | F3: =SUMIFS('All Comparisons'!$O$2:$O$561,'All Comparisons'!$C$2:$C$561,$A3,'All Comparisons'!$D$2:$D$561,$B3)+SUMIFS('Review Queue'!$AB$2:$AB$64,'Review Queue'!$C$2:$C$64,$A3,'Review Queue'!$D$2:$D$64,$B3)-SUMIFS('Review Queue'!$O$2:$O$64,'Review Queue'!$C$2:$C$64,$A3,'Review Queue'!$D$2:$D$64,$B3) -> 20 | G3: =SUMIFS('All Comparisons'!$P$2:$P$561,'All Comparisons'!$C$2:$C$561,$A3,'All Comparisons'!$D$2:$D$561,$B3)+SUMIFS('Review Queue'!$AC$2:$AC$64,'Review Queue'!$C$2:$C$64,$A3,'Review Queue'!$D$2:$D$64,$B3)-SUMIFS('Review Queue'!$P$2:$P$64,'Review Queue'!$C$2:$C$64,$A3,'Review Queue'!$D$2:$D$64,$B3) -> 0 | H3: =SUMIFS('All Comparisons'!$Q$2:$Q$561,'All Comparisons'!$C$2:$C$561,$A3,'All Comparisons'!$D$2:$D$561,$B3)+SUMIFS('Review Queue'!$AD$2:$AD$64,'Review Queue'!$C$2:$C$64,$A3,'Review Queue'!$D$2:$D$64,$B3)-SUMIFS('Review Queue'!$Q$2:$Q$64,'Review Queue'!$C$2:$C$64,$A3,'Review Queue'!$D$2:$D$64,$B3) -> 0 | I3: =IFERROR(F3/(F3+G3),0) -> 1 | J3: =IFERROR(F3/(F3+H3),0) -> 1 | K3: =IFERROR(2*I3*J3/(I3+J3),0) -> 1 | L3: =COUNTIFS('Review Queue'!$C$2:$C$64,$A3,'Review Queue'!$D$2:$D$64,$B3,'Review Queue'!$Y$2:$Y$64,"<>Reviewed",'Review Queue'!$X$2:$X$64,"<>Yes") -> 2 | M3: =COUNTIFS('Review Queue'!$C$2:$C$64,$A3,'Review Queue'!$D$2:$D$64,$B3,'Review Queue'!$AA$2:$AA$64,"INCOMPLETE") -> 0
A4: ACM | B4: Rechtshandeling | C4: =COUNTIFS('All Comparisons'!$C$2:$C$561,$A4,'All Comparisons'!$D$2:$D$561,$B4)-COUNTIFS('Review Queue'!$C$2:$C$64,$A4,'Review Queue'!$D$2:$D$64,$B4,'Review Queue'!$X$2:$X$64,"Yes") -> 20 | D4: =SUMIFS('All Comparisons'!$R$2:$R$561,'All Comparisons'!$C$2:$C$561,$A4,'All Comparisons'!$D$2:$D$561,$B4)+SUMIFS('Review Queue'!$AE$2:$AE$64,'Review Queue'!$C$2:$C$64,$A4,'Review Queue'!$D$2:$D$64,$B4)-SUMIFS('Review Queue'!$R$2:$R$64,'Review Queue'!$C$2:$C$64,$A4,'Review Queue'!$D$2:$D$64,$B4) -> 19 | E4: =IFERROR(D4/C4,0) -> 0.95 | F4: =SUMIFS('All Comparisons'!$O$2:$O$561,'All Comparisons'!$C$2:$C$561,$A4,'All Comparisons'!$D$2:$D$561,$B4)+SUMIFS('Review Queue'!$AB$2:$AB$64,'Review Queue'!$C$2:$C$64,$A4,'Review Queue'!$D$2:$D$64,$B4)-SUMIFS('Review Queue'!$O$2:$O$64,'Review Queue'!$C$2:$C$64,$A4,'Review Queue'!$D$2:$D$64,$B4) -> 19 | G4: =SUMIFS('All Comparisons'!$P$2:$P$561,'All Comparisons'!$C$2:$C$561,$A4,'All Comparisons'!$D$2:$D$561,$B4)+SUMIFS('Review Queue'!$AC$2:$AC$64,'Review Queue'!$C$2:$C$64,$A4,'Review Queue'!$D$2:$D$64,$B4)-SUMIFS('Review Queue'!$P$2:$P$64,'Review Queue'!$C$2:$C$64,$A4,'Review Queue'!$D$2:$D$64,$B4) -> 1 | H4: =SUMIFS('All Comparisons'!$Q$2:$Q$561,'All Comparisons'!$C$2:$C$561,$A4,'All Comparisons'!$D$2:$D$561,$B4)+SUMIFS('Review Queue'!$AD$2:$AD$64,'Review Queue'!$C$2:$C$64,$A4,'Review Queue'!$D$2:$D$64,$B4)-SUMIFS('Review Queue'!$Q$2:$Q$64,'Review Queue'!$C$2:$C$64,$A4,'Review Queue'!$D$2:$D$64,$B4) -> 1 | I4: =IFERROR(F4/(F4+G4),0) -> 0.95 | J4: =IFERROR(F4/(F4+H4),0) -> 0.95 | K4: =IFERROR(2*I4*J4/(I4+J4),0) -> 0.95 | L4: =COUNTIFS('Review Queue'!$C$2:$C$64,$A4,'Review Queue'!$D$2:$D$64,$B4,'Review Queue'!$Y$2:$Y$64,"<>Reviewed",'Review Queue'!$X$2:$X$64,"<>Yes") -> 3 | M4: =COUNTIFS('Review Queue'!$C$2:$C$64,$A4,'Review Queue'!$D$2:$D$64,$B4,'Review Queue'!$AA$2:$AA$64,"INCOMPLETE") -> 0
A5: ACM | B5: Rechtsobject | C5: =COUNTIFS('All Comparisons'!$C$2:$C$561,$A5,'All Comparisons'!$D$2:$D$561,$B5)-COUNTIFS('Review Queue'!$C$2:$C$64,$A5,'Review Queue'!$D$2:$D$64,$B5,'Review Queue'!$X$2:$X$64,"Yes") -> 20 | D5: =SUMIFS('All Comparisons'!$R$2:$R$561,'All Comparisons'!$C$2:$C$561,$A5,'All Comparisons'!$D$2:$D$561,$B5)+SUMIFS('Review Queue'!$AE$2:$AE$64,'Review Queue'!$C$2:$C$64,$A5,'Review Queue'!$D$2:$D$64,$B5)-SUMIFS('Review Queue'!$R$2:$R$64,'Review Queue'!$C$2:$C$64,$A5,'Review Queue'!$D$2:$D$64,$B5) -> 20 | E5: =IFERROR(D5/C5,0) -> 1 | F5: =SUMIFS('All Comparisons'!$O$2:$O$561,'All Comparisons'!$C$2:$C$561,$A5,'All Comparisons'!$D$2:$D$561,$B5)+SUMIFS('Review Queue'!$AB$2:$AB$64,'Review Queue'!$C$2:$C$64,$A5,'Review Queue'!$D$2:$D$64,$B5)-SUMIFS('Review Queue'!$O$2:$O$64,'Review Queue'!$C$2:$C$64,$A5,'Review Queue'!$D$2:$D$64,$B5) -> 21 | G5: =SUMIFS('All Comparisons'!$P$2:$P$561,'All Comparisons'!$C$2:$C$561,$A5,'All Comparisons'!$D$2:$D$561,$B5)+SUMIFS('Review Queue'!$AC$2:$AC$64,'Review Queue'!$C$2:$C$64,$A5,'Review Queue'!$D$2:$D$64,$B5)-SUMIFS('Review Queue'!$P$2:$P$64,'Review Queue'!$C$2:$C$64,$A5,'Review Queue'!$D$2:$D$64,$B5) -> 0 | H5: =SUMIFS('All Comparisons'!$Q$2:$Q$561,'All Comparisons'!$C$2:$C$561,$A5,'All Comparisons'!$D$2:$D$561,$B5)+SUMIFS('Review Queue'!$AD$2:$AD$64,'Review Queue'!$C$2:$C$64,$A5,'Review Queue'!$D$2:$D$64,$B5)-SUMIFS('Review Queue'!$Q$2:$Q$64,'Review Queue'!$C$2:$C$64,$A5,'Review Queue'!$D$2:$D$64,$B5) -> 0 | I5: =IFERROR(F5/(F5+G5),0) -> 1 | J5: =IFERROR(F5/(F5+H5),0) -> 1 | K5: =IFERROR(2*I5*J5/(I5+J5),0) -> 1 | L5: =COUNTIFS('Review Queue'!$C$2:$C$64,$A5,'Review Queue'!$D$2:$D$64,$B5,'Review Queue'!$Y$2:$Y$64,"<>Reviewed",'Review Queue'!$X$2:$X$64,"<>Yes") -> 1 | M5: =COUNTIFS('Review Queue'!$C$2:$C$64,$A5,'Review Queue'!$D$2:$D$64,$B5,'Review Queue'!$AA$2:$AA$64,"INCOMPLETE") -> 0
A6: ACM | B6: Overall | C6: =COUNTIFS('All Comparisons'!$C$2:$C$561,$A6)-COUNTIFS('Review Queue'!$C$2:$C$64,$A6,'Review Queue'!$X$2:$X$64,"Yes") -> 80 | D6: =SUMIFS('All Comparisons'!$R$2:$R$561,'All Comparisons'!$C$2:$C$561,$A6)+SUMIFS('Review Queue'!$AE$2:$AE$64,'Review Queue'!$C$2:$C$64,$A6)-SUMIFS('Review Queue'!$R$2:$R$64,'Review Queue'!$C$2:$C$64,$A6) -> 79 | E6: =IFERROR(D6/C6,0) -> 0.9875 | F6: =SUMIFS('All Comparisons'!$O$2:$O$561,'All Comparisons'!$C$2:$C$561,$A6)+SUMIFS('Review Queue'!$AB$2:$AB$64,'Review Queue'!$C$2:$C$64,$A6)-SUMIFS('Review Queue'!$O$2:$O$64,'Review Queue'!$C$2:$C$64,$A6) -> 82 | G6: =SUMIFS('All Comparisons'!$P$2:$P$561,'All Comparisons'!$C$2:$C$561,$A6)+SUMIFS('Review Queue'!$AC$2:$AC$64,'Review Queue'!$C$2:$C$64,$A6)-SUMIFS('Review Queue'!$P$2:$P$64,'Review Queue'!$C$2:$C$64,$A6) -> 1 | H6: =SUMIFS('All Comparisons'!$Q$2:$Q$561,'All Comparisons'!$C$2:$C$561,$A6)+SUMIFS('Review Queue'!$AD$2:$AD$64,'Review Queue'!$C$2:$C$64,$A6)-SUMIFS('Review Queue'!$Q$2:$Q$64,'Review Queue'!$C$2:$C$64,$A6) -> 1 | I6: =IFERROR(F6/(F6+G6),0) -> 0.98795181 | J6: =IFERROR(F6/(F6+H6),0) -> 0.98795181 | K6: =IFERROR(2*I6*J6/(I6+J6),0) -> 0.98795181 | L6: =COUNTIFS('Review Queue'!$C$2:$C$64,$A6,'Review Queue'!$Y$2:$Y$64,"<>Reviewed",'Review Queue'!$X$2:$X$64,"<>Yes") -> 8 | M6: =COUNTIFS('Review Queue'!$C$2:$C$64,$A6,'Review Queue'!$AA$2:$AA$64,"INCOMPLETE") -> 0
A7: ANVS | B7: Ontvanger | C7: =COUNTIFS('All Comparisons'!$C$2:$C$561,$A7,'All Comparisons'!$D$2:$D$561,$B7)-COUNTIFS('Review Queue'!$C$2:$C$64,$A7,'Review Queue'!$D$2:$D$64,$B7,'Review Queue'!$X$2:$X$64,"Yes") -> 20 | D7: =SUMIFS('All Comparisons'!$R$2:$R$561,'All Comparisons'!$C$2:$C$561,$A7,'All Comparisons'!$D$2:$D$561,$B7)+SUMIFS('Review Queue'!$AE$2:$AE$64,'Review Queue'!$C$2:$C$64,$A7,'Review Queue'!$D$2:$D$64,$B7)-SUMIFS('Review Queue'!$R$2:$R$64,'Review Queue'!$C$2:$C$64,$A7,'Review Queue'!$D$2:$D$64,$B7) -> 20 | E7: =IFERROR(D7/C7,0) -> 1 | F7: =SUMIFS('All Comparisons'!$O$2:$O$561,'All Comparisons'!$C$2:$C$561,$A7,'All Comparisons'!$D$2:$D$561,$B7)+SUMIFS('Review Queue'!$AB$2:$AB$64,'Review Queue'!$C$2:$C$64,$A7,'Review Queue'!$D$2:$D$64,$B7)-SUMIFS('Review Queue'!$O$2:$O$64,'Review Queue'!$C$2:$C$64,$A7,'Review Queue'!$D$2:$D$64,$B7) -> 20 | G7: =SUMIFS('All Comparisons'!$P$2:$P$561,'All Comparisons'!$C$2:$C$561,$A7,'All Comparisons'!$D$2:$D$561,$B7)+SUMIFS('Review Queue'!$AC$2:$AC$64,'Review Queue'!$C$2:$C$64,$A7,'Review Queue'!$D$2:$D$64,$B7)-SUMIFS('Review Queue'!$P$2:$P$64,'Review Queue'!$C$2:$C$64,$A7,'Review Queue'!$D$2:$D$64,$B7) -> 0 | H7: =SUMIFS('All Comparisons'!$Q$2:$Q$561,'All Comparisons'!$C$2:$C$561,$A7,'All Comparisons'!$D$2:$D$561,$B7)+SUMIFS('Review Queue'!$AD$2:$AD$64,'Review Queue'!$C$2:$C$64,$A7,'Review Queue'!$D$2:$D$64,$B7)-SUMIFS('Review Queue'!$Q$2:$Q$64,'Review Queue'!$C$2:$C$64,$A7,'Review Queue'!$D$2:$D$64,$B7) -> 0 | I7: =IFERROR(F7/(F7+G7),0) -> 1 | J7: =IFERROR(F7/(F7+H7),0) -> 1 | K7: =IFERROR(2*I7*J7/(I7+J7),0) -> 1 | L7: =COUNTIFS('Review Queue'!$C$2:$C$64,$A7,'Review Queue'!$D$2:$D$64,$B7,'Review Queue'!$Y$2:$Y$64,"<>Reviewed",'Review Queue'!$X$2:$X$64,"<>Yes") -> 4 | M7: =COUNTIFS('Review Queue'!$C$2:$C$64,$A7,'Review Queue'!$D$2:$D$64,$B7,'Review Queue'!$AA$2:$AA$64,"INCOMPLETE") -> 0
A8: ANVS | B8: Besluitvormend Orgaan | C8: =COUNTIFS('All Comparisons'!$C$2:$C$561,$A8,'All Comparisons'!$D$2:$D$561,$B8)-COUNTIFS('Review Queue'!$C$2:$C$64,$A8,'Review Queue'!$D$2:$D$64,$B8,'Review Queue'!$X$2:$X$64,"Yes") -> 20 | D8: =SUMIFS('All Comparisons'!$R$2:$R$561,'All Comparisons'!$C$2:$C$561,$A8,'All Comparisons'!$D$2:$D$561,$B8)+SUMIFS('Review Queue'!$AE$2:$AE$64,'Review Queue'!$C$2:$C$64,$A8,'Review Queue'!$D$2:$D$64,$B8)-SUMIFS('Review Queue'!$R$2:$R$64,'Review Queue'!$C$2:$C$64,$A8,'Review Queue'!$D$2:$D$64,$B8) -> 20 | E8: =IFERROR(D8/C8,0) -> 1 | F8: =SUMIFS('All Comparisons'!$O$2:$O$561,'All Comparisons'!$C$2:$C$561,$A8,'All Comparisons'!$D$2:$D$561,$B8)+SUMIFS('Review Queue'!$AB$2:$AB$64,'Review Queue'!$C$2:$C$64,$A8,'Review Queue'!$D$2:$D$64,$B8)-SUMIFS('Review Queue'!$O$2:$O$64,'Review Queue'!$C$2:$C$64,$A8,'Review Queue'!$D$2:$D$64,$B8) -> 20 | G8: =SUMIFS('All Comparisons'!$P$2:$P$561,'All Comparisons'!$C$2:$C$561,$A8,'All Comparisons'!$D$2:$D$561,$B8)+SUMIFS('Review Queue'!$AC$2:$AC$64,'Review Queue'!$C$2:$C$64,$A8,'Review Queue'!$D$2:$D$64,$B8)-SUMIFS('Review Queue'!$P$2:$P$64,'Review Queue'!$C$2:$C$64,$A8,'Review Queue'!$D$2:$D$64,$B8) -> 0 | H8: =SUMIFS('All Comparisons'!$Q$2:$Q$561,'All Comparisons'!$C$2:$C$561,$A8,'All Comparisons'!$D$2:$D$561,$B8)+SUMIFS('Review Queue'!$AD$2:$AD$64,'Review Queue'!$C$2:$C$64,$A8,'Review Queue'!$D$2:$D$64,$B8)-SUMIFS('Review Queue'!$Q$2:$Q$64,'Review Queue'!$C$2:$C$64,$A8,'Review Queue'!$D$2:$D$64,$B8) -> 0 | I8: =IFERROR(F8/(F8+G8),0) -> 1 | J8: =IFERROR(F8/(F8+H8),0) -> 1 | K8: =IFERROR(2*I8*J8/(I8+J8),0) -> 1 | L8: =COUNTIFS('Review Queue'!$C$2:$C$64,$A8,'Review Queue'!$D$2:$D$64,$B8,'Review Queue'!$Y$2:$Y$64,"<>Reviewed",'Review Queue'!$X$2:$X$64,"<>Yes") -> 0 | M8: =COUNTIFS('Review Queue'!$C$2:$C$64,$A8,'Review Queue'!$D$2:$D$64,$B8,'Review Queue'!$AA$2:$AA$64,"INCOMPLETE") -> 0
A9: ANVS | B9: Rechtshandeling | C9: =COUNTIFS('All Comparisons'!$C$2:$C$561,$A9,'All Comparisons'!$D$2:$D$561,$B9)-COUNTIFS('Review Queue'!$C$2:$C$64,$A9,'Review Queue'!$D$2:$D$64,$B9,'Review Queue'!$X$2:$X$64,"Yes") -> 20 | D9: =SUMIFS('All Comparisons'!$R$2:$R$561,'All Comparisons'!$C$2:$C$561,$A9,'All Comparisons'!$D$2:$D$561,$B9)+SUMIFS('Review Queue'!$AE$2:$AE$64,'Review Queue'!$C$2:$C$64,$A9,'Review Queue'!$D$2:$D$64,$B9)-SUMIFS('Review Queue'!$R$2:$R$64,'Review Queue'!$C$2:$C$64,$A9,'Review Queue'!$D$2:$D$64,$B9) -> 19 | E9: =IFERROR(D9/C9,0) -> 0.95 | F9: =SUMIFS('All Comparisons'!$O$2:$O$561,'All Comparisons'!$C$2:$C$561,$A9,'All Comparisons'!$D$2:$D$561,$B9)+SUMIFS('Review Queue'!$AB$2:$AB$64,'Review Queue'!$C$2:$C$64,$A9,'Review Queue'!$D$2:$D$64,$B9)-SUMIFS('Review Queue'!$O$2:$O$64,'Review Queue'!$C$2:$C$64,$A9,'Review Queue'!$D$2:$D$64,$B9) -> 20 | G9: =SUMIFS('All Comparisons'!$P$2:$P$561,'All Comparisons'!$C$2:$C$561,$A9,'All Comparisons'!$D$2:$D$561,$B9)+SUMIFS('Review Queue'!$AC$2:$AC$64,'Review Queue'!$C$2:$C$64,$A9,'Review Queue'!$D$2:$D$64,$B9)-SUMIFS('Review Queue'!$P$2:$P$64,'Review Queue'!$C$2:$C$64,$A9,'Review Queue'!$D$2:$D$64,$B9) -> 1 | H9: =SUMIFS('All Comparisons'!$Q$2:$Q$561,'All Comparisons'!$C$2:$C$561,$A9,'All Comparisons'!$D$2:$D$561,$B9)+SUMIFS('Review Queue'!$AD$2:$AD$64,'Review Queue'!$C$2:$C$64,$A9,'Review Queue'!$D$2:$D$64,$B9)-SUMIFS('Review Queue'!$Q$2:$Q$64,'Review Queue'!$C$2:$C$64,$A9,'Review Queue'!$D$2:$D$64,$B9) -> 1 | I9: =IFERROR(F9/(F9+G9),0) -> 0.95238095 | J9: =IFERROR(F9/(F9+H9),0) -> 0.95238095 | K9: =IFERROR(2*I9*J9/(I9+J9),0) -> 0.95238095 | L9: =COUNTIFS('Review Queue'!$C$2:$C$64,$A9,'Review Queue'!$D$2:$D$64,$B9,'Review Queue'!$Y$2:$Y$64,"<>Reviewed",'Review Queue'!$X$2:$X$64,"<>Yes") -> 3 | M9: =COUNTIFS('Review Queue'!$C$2:$C$64,$A9,'Review Queue'!$D$2:$D$64,$B9,'Review Queue'!$AA$2:$AA$64,"INCOMPLETE") -> 0
A10: ANVS | B10: Rechtsobject | C10: =COUNTIFS('All Comparisons'!$C$2:$C$561,$A10,'All Comparisons'!$D$2:$D$561,$B10)-COUNTIFS('Review Queue'!$C$2:$C$64,$A10,'Review Queue'!$D$2:$D$64,$B10,'Review Queue'!$X$2:$X$64,"Yes") -> 20 | D10: =SUMIFS('All Comparisons'!$R$2:$R$561,'All Comparisons'!$C$2:$C$561,$A10,'All Comparisons'!$D$2:$D$561,$B10)+SUMIFS('Review Queue'!$AE$2:$AE$64,'Review Queue'!$C$2:$C$64,$A10,'Review Queue'!$D$2:$D$64,$B10)-SUMIFS('Review Queue'!$R$2:$R$64,'Review Queue'!$C$2:$C$64,$A10,'Review Queue'!$D$2:$D$64,$B10) -> 20 | E10: =IFERROR(D10/C10,0) -> 1 | F10: =SUMIFS('All Comparisons'!$O$2:$O$561,'All Comparisons'!$C$2:$C$561,$A10,'All Comparisons'!$D$2:$D$561,$B10)+SUMIFS('Review Queue'!$AB$2:$AB$64,'Review Queue'!$C$2:$C$64,$A10,'Review Queue'!$D$2:$D$64,$B10)-SUMIFS('Review Queue'!$O$2:$O$64,'Review Queue'!$C$2:$C$64,$A10,'Review Queue'!$D$2:$D$64,$B10) -> 20 | G10: =SUMIFS('All Comparisons'!$P$2:$P$561,'All Comparisons'!$C$2:$C$561,$A10,'All Comparisons'!$D$2:$D$561,$B10)+SUMIFS('Review Queue'!$AC$2:$AC$64,'Review Queue'!$C$2:$C$64,$A10,'Review Queue'!$D$2:$D$64,$B10)-SUMIFS('Review Queue'!$P$2:$P$64,'Review Queue'!$C$2:$C$64,$A10,'Review Queue'!$D$2:$D$64,$B10) -> 0 | H10: =SUMIFS('All Comparisons'!$Q$2:$Q$561,'All Comparisons'!$C$2:$C$561,$A10,'All Comparisons'!$D$2:$D$561,$B10)+SUMIFS('Review Queue'!$AD$2:$AD$64,'Review Queue'!$C$2:$C$64,$A10,'Review Queue'!$D$2:$D$64,$B10)-SUMIFS('Review Queue'!$Q$2:$Q$64,'Review Queue'!$C$2:$C$64,$A10,'Review Queue'!$D$2:$D$64,$B10) -> 0 | I10: =IFERROR(F10/(F10+G10),0) -> 1 | J10: =IFERROR(F10/(F10+H10),0) -> 1 | K10: =IFERROR(2*I10*J10/(I10+J10),0) -> 1 | L10: =COUNTIFS('Review Queue'!$C$2:$C$64,$A10,'Review Queue'!$D$2:$D$64,$B10,'Review Queue'!$Y$2:$Y$64,"<>Reviewed",'Review Queue'!$X$2:$X$64,"<>Yes") -> 0 | M10: =COUNTIFS('Review Queue'!$C$2:$C$64,$A10,'Review Queue'!$D$2:$D$64,$B10,'Review Queue'!$AA$2:$AA$64,"INCOMPLETE") -> 0
A11: ANVS | B11: Overall | C11: =COUNTIFS('All Comparisons'!$C$2:$C$561,$A11)-COUNTIFS('Review Queue'!$C$2:$C$64,$A11,'Review Queue'!$X$2:$X$64,"Yes") -> 80 | D11: =SUMIFS('All Comparisons'!$R$2:$R$561,'All Comparisons'!$C$2:$C$561,$A11)+SUMIFS('Review Queue'!$AE$2:$AE$64,'Review Queue'!$C$2:$C$64,$A11)-SUMIFS('Review Queue'!$R$2:$R$64,'Review Queue'!$C$2:$C$64,$A11) -> 79 | E11: =IFERROR(D11/C11,0) -> 0.9875 | F11: =SUMIFS('All Comparisons'!$O$2:$O$561,'All Comparisons'!$C$2:$C$561,$A11)+SUMIFS('Review Queue'!$AB$2:$AB$64,'Review Queue'!$C$2:$C$64,$A11)-SUMIFS('Review Queue'!$O$2:$O$64,'Review Queue'!$C$2:$C$64,$A11) -> 80 | G11: =SUMIFS('All Comparisons'!$P$2:$P$561,'All Comparisons'!$C$2:$C$561,$A11)+SUMIFS('Review Queue'!$AC$2:$AC$64,'Review Queue'!$C$2:$C$64,$A11)-SUMIFS('Review Queue'!$P$2:$P$64,'Review Queue'!$C$2:$C$64,$A11) -> 1 | H11: =SUMIFS('All Comparisons'!$Q$2:$Q$561,'All Comparisons'!$C$2:$C$561,$A11)+SUMIFS('Review Queue'!$AD$2:$AD$64,'Review Queue'!$C$2:$C$64,$A11)-SUMIFS('Review Queue'!$Q$2:$Q$64,'Review Queue'!$C$2:$C$64,$A11) -> 1 | I11: =IFERROR(F11/(F11+G11),0) -> 0.98765432 | J11: =IFERROR(F11/(F11+H11),0) -> 0.98765432 | K11: =IFERROR(2*I11*J11/(I11+J11),0) -> 0.98765432 | L11: =COUNTIFS('Review Queue'!$C$2:$C$64,$A11,'Review Queue'!$Y$2:$Y$64,"<>Reviewed",'Review Queue'!$X$2:$X$64,"<>Yes") -> 7 | M11: =COUNTIFS('Review Queue'!$C$2:$C$64,$A11,'Review Queue'!$AA$2:$AA$64,"INCOMPLETE") -> 0
A12: AP | B12: Ontvanger | C12: =COUNTIFS('All Comparisons'!$C$2:$C$561,$A12,'All Comparisons'!$D$2:$D$561,$B12)-COUNTIFS('Review Queue'!$C$2:$C$64,$A12,'Review Queue'!$D$2:$D$64,$B12,'Review Queue'!$X$2:$X$64,"Yes") -> 20 | D12: =SUMIFS('All Comparisons'!$R$2:$R$561,'All Comparisons'!$C$2:$C$561,$A12,'All Comparisons'!$D$2:$D$561,$B12)+SUMIFS('Review Queue'!$AE$2:$AE$64,'Review Queue'!$C$2:$C$64,$A12,'Review Queue'!$D$2:$D$64,$B12)-SUMIFS('Review Queue'!$R$2:$R$64,'Review Queue'!$C$2:$C$64,$A12,'Review Queue'!$D$2:$D$64,$B12) -> 20 | E12: =IFERROR(D12/C12,0) -> 1 | F12: =SUMIFS('All Comparisons'!$O$2:$O$561,'All Comparisons'!$C$2:$C$561,$A12,'All Comparisons'!$D$2:$D$561,$B12)+SUMIFS('Review Queue'!$AB$2:$AB$64,'Review Queue'!$C$2:$C$64,$A12,'Review Queue'!$D$2:$D$64,$B12)-SUMIFS('Review Queue'!$O$2:$O$64,'Review Queue'!$C$2:$C$64,$A12,'Review Queue'!$D$2:$D$64,$B12) -> 20 | G12: =SUMIFS('All Comparisons'!$P$2:$P$561,'All Comparisons'!$C$2:$C$561,$A12,'All Comparisons'!$D$2:$D$561,$B12)+SUMIFS('Review Queue'!$AC$2:$AC$64,'Review Queue'!$C$2:$C$64,$A12,'Review Queue'!$D$2:$D$64,$B12)-SUMIFS('Review Queue'!$P$2:$P$64,'Review Queue'!$C$2:$C$64,$A12,'Review Queue'!$D$2:$D$64,$B12) -> 0 | H12: =SUMIFS('All Comparisons'!$Q$2:$Q$561,'All Comparisons'!$C$2:$C$561,$A12,'All Comparisons'!$D$2:$D$561,$B12)+SUMIFS('Review Queue'!$AD$2:$AD$64,'Review Queue'!$C$2:$C$64,$A12,'Review Queue'!$D$2:$D$64,$B12)-SUMIFS('Review Queue'!$Q$2:$Q$64,'Review Queue'!$C$2:$C$64,$A12,'Review Queue'!$D$2:$D$64,$B12) -> 0 | I12: =IFERROR(F12/(F12+G12),0) -> 1 | J12: =IFERROR(F12/(F12+H12),0) -> 1 | K12: =IFERROR(2*I12*J12/(I12+J12),0) -> 1 | L12: =COUNTIFS('Review Queue'!$C$2:$C$64,$A12,'Review Queue'!$D$2:$D$64,$B12,'Review Queue'!$Y$2:$Y$64,"<>Reviewed",'Review Queue'!$X$2:$X$64,"<>Yes") -> 9 | M12: =COUNTIFS('Review Queue'!$C$2:$C$64,$A12,'Review Queue'!$D$2:$D$64,$B12,'Review Queue'!$AA$2:$AA$64,"INCOMPLETE") -> 0
A13: AP | B13: Besluitvormend Orgaan | C13: =COUNTIFS('All Comparisons'!$C$2:$C$561,$A13,'All Comparisons'!$D$2:$D$561,$B13)-COUNTIFS('Review Queue'!$C$2:$C$64,$A13,'Review Queue'!$D$2:$D$64,$B13,'Review Queue'!$X$2:$X$64,"Yes") -> 20 | D13: =SUMIFS('All Comparisons'!$R$2:$R$561,'All Comparisons'!$C$2:$C$561,$A13,'All Comparisons'!$D$2:$D$561,$B13)+SUMIFS('Review Queue'!$AE$2:$AE$64,'Review Queue'!$C$2:$C$64,$A13,'Review Queue'!$D$2:$D$64,$B13)-SUMIFS('Review Queue'!$R$2:$R$64,'Review Queue'!$C$2:$C$64,$A13,'Review Queue'!$D$2:$D$64,$B13) -> 20 | E13: =IFERROR(D13/C13,0) -> 1 | F13: =SUMIFS('All Comparisons'!$O$2:$O$561,'All Comparisons'!$C$2:$C$561,$A13,'All Comparisons'!$D$2:$D$561,$B13)+SUMIFS('Review Queue'!$AB$2:$AB$64,'Review Queue'!$C$2:$C$64,$A13,'Review Queue'!$D$2:$D$64,$B13)-SUMIFS('Review Queue'!$O$2:$O$64,'Review Queue'!$C$2:$C$64,$A13,'Review Queue'!$D$2:$D$64,$B13) -> 20 | G13: =SUMIFS('All Comparisons'!$P$2:$P$561,'All Comparisons'!$C$2:$C$561,$A13,'All Comparisons'!$D$2:$D$561,$B13)+SUMIFS('Review Queue'!$AC$2:$AC$64,'Review Queue'!$C$2:$C$64,$A13,'Review Queue'!$D$2:$D$64,$B13)-SUMIFS('Review Queue'!$P$2:$P$64,'Review Queue'!$C$2:$C$64,$A13,'Review Queue'!$D$2:$D$64,$B13) -> 0 | H13: =SUMIFS('All Comparisons'!$Q$2:$Q$561,'All Comparisons'!$C$2:$C$561,$A13,'All Comparisons'!$D$2:$D$561,$B13)+SUMIFS('Review Queue'!$AD$2:$AD$64,'Review Queue'!$C$2:$C$64,$A13,'Review Queue'!$D$2:$D$64,$B13)-SUMIFS('Review Queue'!$Q$2:$Q$64,'Review Queue'!$C$2:$C$64,$A13,'Review Queue'!$D$2:$D$64,$B13) -> 0 | I13: =IFERROR(F13/(F13+G13),0) -> 1 | J13: =IFERROR(F13/(F13+H13),0) -> 1 | K13: =IFERROR(2*I13*J13/(I13+J13),0) -> 1 | L13: =COUNTIFS('Review Queue'!$C$2:$C$64,$A13,'Review Queue'!$D$2:$D$64,$B13,'Review Queue'!$Y$2:$Y$64,"<>Reviewed",'Review Queue'!$X$2:$X$64,"<>Yes") -> 1 | M13: =COUNTIFS('Review Queue'!$C$2:$C$64,$A13,'Review Queue'!$D$2:$D$64,$B13,'Review Queue'!$AA$2:$AA$64,"INCOMPLETE") -> 0
A14: AP | B14: Rechtshandeling | C14: =COUNTIFS('All Comparisons'!$C$2:$C$561,$A14,'All Comparisons'!$D$2:$D$561,$B14)-COUNTIFS('Review Queue'!$C$2:$C$64,$A14,'Review Queue'!$D$2:$D$64,$B14,'Review Queue'!$X$2:$X$64,"Yes") -> 20 | D14: =SUMIFS('All Comparisons'!$R$2:$R$561,'All Comparisons'!$C$2:$C$561,$A14,'All Comparisons'!$D$2:$D$561,$B14)+SUMIFS('Review Queue'!$AE$2:$AE$64,'Review Queue'!$C$2:$C$64,$A14,'Review Queue'!$D$2:$D$64,$B14)-SUMIFS('Review Queue'!$R$2:$R$64,'Review Queue'!$C$2:$C$64,$A14,'Review Queue'!$D$2:$D$64,$B14) -> 20 | E14: =IFERROR(D14/C14,0) -> 1 | F14: =SUMIFS('All Comparisons'!$O$2:$O$561,'All Comparisons'!$C$2:$C$561,$A14,'All Comparisons'!$D$2:$D$561,$B14)+SUMIFS('Review Queue'!$AB$2:$AB$64,'Review Queue'!$C$2:$C$64,$A14,'Review Queue'!$D$2:$D$64,$B14)-SUMIFS('Review Queue'!$O$2:$O$64,'Review Queue'!$C$2:$C$64,$A14,'Review Queue'!$D$2:$D$64,$B14) -> 20 | G14: =SUMIFS('All Comparisons'!$P$2:$P$561,'All Comparisons'!$C$2:$C$561,$A14,'All Comparisons'!$D$2:$D$561,$B14)+SUMIFS('Review Queue'!$AC$2:$AC$64,'Review Queue'!$C$2:$C$64,$A14,'Review Queue'!$D$2:$D$64,$B14)-SUMIFS('Review Queue'!$P$2:$P$64,'Review Queue'!$C$2:$C$64,$A14,'Review Queue'!$D$2:$D$64,$B14) -> 0 | H14: =SUMIFS('All Comparisons'!$Q$2:$Q$561,'All Comparisons'!$C$2:$C$561,$A14,'All Comparisons'!$D$2:$D$561,$B14)+SUMIFS('Review Queue'!$AD$2:$AD$64,'Review Queue'!$C$2:$C$64,$A14,'Review Queue'!$D$2:$D$64,$B14)-SUMIFS('Review Queue'!$Q$2:$Q$64,'Review Queue'!$C$2:$C$64,$A14,'Review Queue'!$D$2:$D$64,$B14) -> 0 | I14: =IFERROR(F14/(F14+G14),0) -> 1 | J14: =IFERROR(F14/(F14+H14),0) -> 1 | K14: =IFERROR(2*I14*J14/(I14+J14),0) -> 1 | L14: =COUNTIFS('Review Queue'!$C$2:$C$64,$A14,'Review Queue'!$D$2:$D$64,$B14,'Review Queue'!$Y$2:$Y$64,"<>Reviewed",'Review Queue'!$X$2:$X$64,"<>Yes") -> 1 | M14: =COUNTIFS('Review Queue'!$C$2:$C$64,$A14,'Review Queue'!$D$2:$D$64,$B14,'Review Queue'!$AA$2:$AA$64,"INCOMPLETE") -> 0
A15: AP | B15: Rechtsobject | C15: =COUNTIFS('All Comparisons'!$C$2:$C$561,$A15,'All Comparisons'!$D$2:$D$561,$B15)-COUNTIFS('Review Queue'!$C$2:$C$64,$A15,'Review Queue'!$D$2:$D$64,$B15,'Review Queue'!$X$2:$X$64,"Yes") -> 20 | D15: =SUMIFS('All Comparisons'!$R$2:$R$561,'All Comparisons'!$C$2:$C$561,$A15,'All Comparisons'!$D$2:$D$561,$B15)+SUMIFS('Review Queue'!$AE$2:$AE$64,'Review Queue'!$C$2:$C$64,$A15,'Review Queue'!$D$2:$D$64,$B15)-SUMIFS('Review Queue'!$R$2:$R$64,'Review Queue'!$C$2:$C$64,$A15,'Review Queue'!$D$2:$D$64,$B15) -> 19 | E15: =IFERROR(D15/C15,0) -> 0.95 | F15: =SUMIFS('All Comparisons'!$O$2:$O$561,'All Comparisons'!$C$2:$C$561,$A15,'All Comparisons'!$D$2:$D$561,$B15)+SUMIFS('Review Queue'!$AB$2:$AB$64,'Review Queue'!$C$2:$C$64,$A15,'Review Queue'!$D$2:$D$64,$B15)-SUMIFS('Review Queue'!$O$2:$O$64,'Review Queue'!$C$2:$C$64,$A15,'Review Queue'!$D$2:$D$64,$B15) -> 19 | G15: =SUMIFS('All Comparisons'!$P$2:$P$561,'All Comparisons'!$C$2:$C$561,$A15,'All Comparisons'!$D$2:$D$561,$B15)+SUMIFS('Review Queue'!$AC$2:$AC$64,'Review Queue'!$C$2:$C$64,$A15,'Review Queue'!$D$2:$D$64,$B15)-SUMIFS('Review Queue'!$P$2:$P$64,'Review Queue'!$C$2:$C$64,$A15,'Review Queue'!$D$2:$D$64,$B15) -> 1 | H15: =SUMIFS('All Comparisons'!$Q$2:$Q$561,'All Comparisons'!$C$2:$C$561,$A15,'All Comparisons'!$D$2:$D$561,$B15)+SUMIFS('Review Queue'!$AD$2:$AD$64,'Review Queue'!$C$2:$C$64,$A15,'Review Queue'!$D$2:$D$64,$B15)-SUMIFS('Review Queue'!$Q$2:$Q$64,'Review Queue'!$C$2:$C$64,$A15,'Review Queue'!$D$2:$D$64,$B15) -> 0 | I15: =IFERROR(F15/(F15+G15),0) -> 0.95 | J15: =IFERROR(F15/(F15+H15),0) -> 1 | K15: =IFERROR(2*I15*J15/(I15+J15),0) -> 0.97435897 | L15: =COUNTIFS('Review Queue'!$C$2:$C$64,$A15,'Review Queue'!$D$2:$D$64,$B15,'Review Queue'!$Y$2:$Y$64,"<>Reviewed",'Review Queue'!$X$2:$X$64,"<>Yes") -> 1 | M15: =COUNTIFS('Review Queue'!$C$2:$C$64,$A15,'Review Queue'!$D$2:$D$64,$B15,'Review Queue'!$AA$2:$AA$64,"INCOMPLETE") -> 0
A16: AP | B16: Overall | C16: =COUNTIFS('All Comparisons'!$C$2:$C$561,$A16)-COUNTIFS('Review Queue'!$C$2:$C$64,$A16,'Review Queue'!$X$2:$X$64,"Yes") -> 80 | D16: =SUMIFS('All Comparisons'!$R$2:$R$561,'All Comparisons'!$C$2:$C$561,$A16)+SUMIFS('Review Queue'!$AE$2:$AE$64,'Review Queue'!$C$2:$C$64,$A16)-SUMIFS('Review Queue'!$R$2:$R$64,'Review Queue'!$C$2:$C$64,$A16) -> 79 | E16: =IFERROR(D16/C16,0) -> 0.9875 | F16: =SUMIFS('All Comparisons'!$O$2:$O$561,'All Comparisons'!$C$2:$C$561,$A16)+SUMIFS('Review Queue'!$AB$2:$AB$64,'Review Queue'!$C$2:$C$64,$A16)-SUMIFS('Review Queue'!$O$2:$O$64,'Review Queue'!$C$2:$C$64,$A16) -> 79 | G16: =SUMIFS('All Comparisons'!$P$2:$P$561,'All Comparisons'!$C$2:$C$561,$A16)+SUMIFS('Review Queue'!$AC$2:$AC$64,'Review Queue'!$C$2:$C$64,$A16)-SUMIFS('Review Queue'!$P$2:$P$64,'Review Queue'!$C$2:$C$64,$A16) -> 1 | H16: =SUMIFS('All Comparisons'!$Q$2:$Q$561,'All Comparisons'!$C$2:$C$561,$A16)+SUMIFS('Review Queue'!$AD$2:$AD$64,'Review Queue'!$C$2:$C$64,$A16)-SUMIFS('Review Queue'!$Q$2:$Q$64,'Review Queue'!$C$2:$C$64,$A16) -> 0 | I16: =IFERROR(F16/(F16+G16),0) -> 0.9875 | J16: =IFERROR(F16/(F16+H16),0) -> 1 | K16: =IFERROR(2*I16*J16/(I16+J16),0) -> 0.99371069 | L16: =COUNTIFS('Review Queue'!$C$2:$C$64,$A16,'Review Queue'!$Y$2:$Y$64,"<>Reviewed",'Review Queue'!$X$2:$X$64,"<>Yes") -> 12 | M16: =COUNTIFS('Review Queue'!$C$2:$C$64,$A16,'Review Queue'!$AA$2:$AA$64,"INCOMPLETE") -> 0
A17: DRE | B17: Ontvanger | C17: =COUNTIFS('All Comparisons'!$C$2:$C$561,$A17,'All Comparisons'!$D$2:$D$561,$B17)-COUNTIFS('Review Queue'!$C$2:$C$64,$A17,'Review Queue'!$D$2:$D$64,$B17,'Review Queue'!$X$2:$X$64,"Yes") -> 20 | D17: =SUMIFS('All Comparisons'!$R$2:$R$561,'All Comparisons'!$C$2:$C$561,$A17,'All Comparisons'!$D$2:$D$561,$B17)+SUMIFS('Review Queue'!$AE$2:$AE$64,'Review Queue'!$C$2:$C$64,$A17,'Review Queue'!$D$2:$D$64,$B17)-SUMIFS('Review Queue'!$R$2:$R$64,'Review Queue'!$C$2:$C$64,$A17,'Review Queue'!$D$2:$D$64,$B17) -> 18 | E17: =IFERROR(D17/C17,0) -> 0.9 | F17: =SUMIFS('All Comparisons'!$O$2:$O$561,'All Comparisons'!$C$2:$C$561,$A17,'All Comparisons'!$D$2:$D$561,$B17)+SUMIFS('Review Queue'!$AB$2:$AB$64,'Review Queue'!$C$2:$C$64,$A17,'Review Queue'!$D$2:$D$64,$B17)-SUMIFS('Review Queue'!$O$2:$O$64,'Review Queue'!$C$2:$C$64,$A17,'Review Queue'!$D$2:$D$64,$B17) -> 18 | G17: =SUMIFS('All Comparisons'!$P$2:$P$561,'All Comparisons'!$C$2:$C$561,$A17,'All Comparisons'!$D$2:$D$561,$B17)+SUMIFS('Review Queue'!$AC$2:$AC$64,'Review Queue'!$C$2:$C$64,$A17,'Review Queue'!$D$2:$D$64,$B17)-SUMIFS('Review Queue'!$P$2:$P$64,'Review Queue'!$C$2:$C$64,$A17,'Review Queue'!$D$2:$D$64,$B17) -> 1 | H17: =SUMIFS('All Comparisons'!$Q$2:$Q$561,'All Comparisons'!$C$2:$C$561,$A17,'All Comparisons'!$D$2:$D$561,$B17)+SUMIFS('Review Queue'!$AD$2:$AD$64,'Review Queue'!$C$2:$C$64,$A17,'Review Queue'!$D$2:$D$64,$B17)-SUMIFS('Review Queue'!$Q$2:$Q$64,'Review Queue'!$C$2:$C$64,$A17,'Review Queue'!$D$2:$D$64,$B17) -> 2 | I17: =IFERROR(F17/(F17+G17),0) -> 0.94736842 | J17: =IFERROR(F17/(F17+H17),0) -> 0.9 | K17: =IFERROR(2*I17*J17/(I17+J17),0) -> 0.92307692 | L17: =COUNTIFS('Review Queue'!$C$2:$C$64,$A17,'Review Queue'!$D$2:$D$64,$B17,'Review Queue'!$Y$2:$Y$64,"<>Reviewed",'Review Queue'!$X$2:$X$64,"<>Yes") -> 3 | M17: =COUNTIFS('Review Queue'!$C$2:$C$64,$A17,'Review Queue'!$D$2:$D$64,$B17,'Review Queue'!$AA$2:$AA$64,"INCOMPLETE") -> 0
A18: DRE | B18: Besluitvormend Orgaan | C18: =COUNTIFS('All Comparisons'!$C$2:$C$561,$A18,'All Comparisons'!$D$2:$D$561,$B18)-COUNTIFS('Review Queue'!$C$2:$C$64,$A18,'Review Queue'!$D$2:$D$64,$B18,'Review Queue'!$X$2:$X$64,"Yes") -> 20 | D18: =SUMIFS('All Comparisons'!$R$2:$R$561,'All Comparisons'!$C$2:$C$561,$A18,'All Comparisons'!$D$2:$D$561,$B18)+SUMIFS('Review Queue'!$AE$2:$AE$64,'Review Queue'!$C$2:$C$64,$A18,'Review Queue'!$D$2:$D$64,$B18)-SUMIFS('Review Queue'!$R$2:$R$64,'Review Queue'!$C$2:$C$64,$A18,'Review Queue'!$D$2:$D$64,$B18) -> 19 | E18: =IFERROR(D18/C18,0) -> 0.95 | F18: =SUMIFS('All Comparisons'!$O$2:$O$561,'All Comparisons'!$C$2:$C$561,$A18,'All Comparisons'!$D$2:$D$561,$B18)+SUMIFS('Review Queue'!$AB$2:$AB$64,'Review Queue'!$C$2:$C$64,$A18,'Review Queue'!$D$2:$D$64,$B18)-SUMIFS('Review Queue'!$O$2:$O$64,'Review Queue'!$C$2:$C$64,$A18,'Review Queue'!$D$2:$D$64,$B18) -> 19 | G18: =SUMIFS('All Comparisons'!$P$2:$P$561,'All Comparisons'!$C$2:$C$561,$A18,'All Comparisons'!$D$2:$D$561,$B18)+SUMIFS('Review Queue'!$AC$2:$AC$64,'Review Queue'!$C$2:$C$64,$A18,'Review Queue'!$D$2:$D$64,$B18)-SUMIFS('Review Queue'!$P$2:$P$64,'Review Queue'!$C$2:$C$64,$A18,'Review Queue'!$D$2:$D$64,$B18) -> 1 | H18: =SUMIFS('All Comparisons'!$Q$2:$Q$561,'All Comparisons'!$C$2:$C$561,$A18,'All Comparisons'!$D$2:$D$561,$B18)+SUMIFS('Review Queue'!$AD$2:$AD$64,'Review Queue'!$C$2:$C$64,$A18,'Review Queue'!$D$2:$D$64,$B18)-SUMIFS('Review Queue'!$Q$2:$Q$64,'Review Queue'!$C$2:$C$64,$A18,'Review Queue'!$D$2:$D$64,$B18) -> 1 | I18: =IFERROR(F18/(F18+G18),0) -> 0.95 | J18: =IFERROR(F18/(F18+H18),0) -> 0.95 | K18: =IFERROR(2*I18*J18/(I18+J18),0) -> 0.95 | L18: =COUNTIFS('Review Queue'!$C$2:$C$64,$A18,'Review Queue'!$D$2:$D$64,$B18,'Review Queue'!$Y$2:$Y$64,"<>Reviewed",'Review Queue'!$X$2:$X$64,"<>Yes") -> 1 | M18: =COUNTIFS('Review Queue'!$C$2:$C$64,$A18,'Review Queue'!$D$2:$D$64,$B18,'Review Queue'!$AA$2:$AA$64,"INCOMPLETE") -> 0
A19: DRE | B19: Rechtshandeling | C19: =COUNTIFS('All Comparisons'!$C$2:$C$561,$A19,'All Comparisons'!$D$2:$D$561,$B19)-COUNTIFS('Review Queue'!$C$2:$C$64,$A19,'Review Queue'!$D$2:$D$64,$B19,'Review Queue'!$X$2:$X$64,"Yes") -> 20 | D19: =SUMIFS('All Comparisons'!$R$2:$R$561,'All Comparisons'!$C$2:$C$561,$A19,'All Comparisons'!$D$2:$D$561,$B19)+SUMIFS('Review Queue'!$AE$2:$AE$64,'Review Queue'!$C$2:$C$64,$A19,'Review Queue'!$D$2:$D$64,$B19)-SUMIFS('Review Queue'!$R$2:$R$64,'Review Queue'!$C$2:$C$64,$A19,'Review Queue'!$D$2:$D$64,$B19) -> 20 | E19: =IFERROR(D19/C19,0) -> 1 | F19: =SUMIFS('All Comparisons'!$O$2:$O$561,'All Comparisons'!$C$2:$C$561,$A19,'All Comparisons'!$D$2:$D$561,$B19)+SUMIFS('Review Queue'!$AB$2:$AB$64,'Review Queue'!$C$2:$C$64,$A19,'Review Queue'!$D$2:$D$64,$B19)-SUMIFS('Review Queue'!$O$2:$O$64,'Review Queue'!$C$2:$C$64,$A19,'Review Queue'!$D$2:$D$64,$B19) -> 20 | G19: =SUMIFS('All Comparisons'!$P$2:$P$561,'All Comparisons'!$C$2:$C$561,$A19,'All Comparisons'!$D$2:$D$561,$B19)+SUMIFS('Review Queue'!$AC$2:$AC$64,'Review Queue'!$C$2:$C$64,$A19,'Review Queue'!$D$2:$D$64,$B19)-SUMIFS('Review Queue'!$P$2:$P$64,'Review Queue'!$C$2:$C$64,$A19,'Review Queue'!$D$2:$D$64,$B19) -> 0 | H19: =SUMIFS('All Comparisons'!$Q$2:$Q$561,'All Comparisons'!$C$2:$C$561,$A19,'All Comparisons'!$D$2:$D$561,$B19)+SUMIFS('Review Queue'!$AD$2:$AD$64,'Review Queue'!$C$2:$C$64,$A19,'Review Queue'!$D$2:$D$64,$B19)-SUMIFS('Review Queue'!$Q$2:$Q$64,'Review Queue'!$C$2:$C$64,$A19,'Review Queue'!$D$2:$D$64,$B19) -> 0 | I19: =IFERROR(F19/(F19+G19),0) -> 1 | J19: =IFERROR(F19/(F19+H19),0) -> 1 | K19: =IFERROR(2*I19*J19/(I19+J19),0) -> 1 | L19: =COUNTIFS('Review Queue'!$C$2:$C$64,$A19,'Review Queue'!$D$2:$D$64,$B19,'Review Queue'!$Y$2:$Y$64,"<>Reviewed",'Review Queue'!$X$2:$X$64,"<>Yes") -> 1 | M19: =COUNTIFS('Review Queue'!$C$2:$C$64,$A19,'Review Queue'!$D$2:$D$64,$B19,'Review Queue'!$AA$2:$AA$64,"INCOMPLETE") -> 0
A20: DRE | B20: Rechtsobject | C20: =COUNTIFS('All Comparisons'!$C$2:$C$561,$A20,'All Comparisons'!$D$2:$D$561,$B20)-COUNTIFS('Review Queue'!$C$2:$C$64,$A20,'Review Queue'!$D$2:$D$64,$B20,'Review Queue'!$X$2:$X$64,"Yes") -> 20 | D20: =SUMIFS('All Comparisons'!$R$2:$R$561,'All Comparisons'!$C$2:$C$561,$A20,'All Comparisons'!$D$2:$D$561,$B20)+SUMIFS('Review Queue'!$AE$2:$AE$64,'Review Queue'!$C$2:$C$64,$A20,'Review Queue'!$D$2:$D$64,$B20)-SUMIFS('Review Queue'!$R$2:$R$64,'Review Queue'!$C$2:$C$64,$A20,'Review Queue'!$D$2:$D$64,$B20) -> 20 | E20: =IFERROR(D20/C20,0) -> 1 | F20: =SUMIFS('All Comparisons'!$O$2:$O$561,'All Comparisons'!$C$2:$C$561,$A20,'All Comparisons'!$D$2:$D$561,$B20)+SUMIFS('Review Queue'!$AB$2:$AB$64,'Review Queue'!$C$2:$C$64,$A20,'Review Queue'!$D$2:$D$64,$B20)-SUMIFS('Review Queue'!$O$2:$O$64,'Review Queue'!$C$2:$C$64,$A20,'Review Queue'!$D$2:$D$64,$B20) -> 20 | G20: =SUMIFS('All Comparisons'!$P$2:$P$561,'All Comparisons'!$C$2:$C$561,$A20,'All Comparisons'!$D$2:$D$561,$B20)+SUMIFS('Review Queue'!$AC$2:$AC$64,'Review Queue'!$C$2:$C$64,$A20,'Review Queue'!$D$2:$D$64,$B20)-SUMIFS('Review Queue'!$P$2:$P$64,'Review Queue'!$C$2:$C$64,$A20,'Review Queue'!$D$2:$D$64,$B20) -> 0 | H20: =SUMIFS('All Comparisons'!$Q$2:$Q$561,'All Comparisons'!$C$2:$C$561,$A20,'All Comparisons'!$D$2:$D$561,$B20)+SUMIFS('Review Queue'!$AD$2:$AD$64,'Review Queue'!$C$2:$C$64,$A20,'Review Queue'!$D$2:$D$64,$B20)-SUMIFS('Review Queue'!$Q$2:$Q$64,'Review Queue'!$C$2:$C$64,$A20,'Review Queue'!$D$2:$D$64,$B20) -> 0 | I20: =IFERROR(F20/(F20+G20),0) -> 1 | J20: =IFERROR(F20/(F20+H20),0) -> 1 | K20: =IFERROR(2*I20*J20/(I20+J20),0) -> 1 | L20: =COUNTIFS('Review Queue'!$C$2:$C$64,$A20,'Review Queue'!$D$2:$D$64,$B20,'Review Queue'!$Y$2:$Y$64,"<>Reviewed",'Review Queue'!$X$2:$X$64,"<>Yes") -> 0 | M20: =COUNTIFS('Review Queue'!$C$2:$C$64,$A20,'Review Queue'!$D$2:$D$64,$B20,'Review Queue'!$AA$2:$AA$64,"INCOMPLETE") -> 0
A21: DRE | B21: Overall | C21: =COUNTIFS('All Comparisons'!$C$2:$C$561,$A21)-COUNTIFS('Review Queue'!$C$2:$C$64,$A21,'Review Queue'!$X$2:$X$64,"Yes") -> 80 | D21: =SUMIFS('All Comparisons'!$R$2:$R$561,'All Comparisons'!$C$2:$C$561,$A21)+SUMIFS('Review Queue'!$AE$2:$AE$64,'Review Queue'!$C$2:$C$64,$A21)-SUMIFS('Review Queue'!$R$2:$R$64,'Review Queue'!$C$2:$C$64,$A21) -> 77 | E21: =IFERROR(D21/C21,0) -> 0.9625 | F21: =SUMIFS('All Comparisons'!$O$2:$O$561,'All Comparisons'!$C$2:$C$561,$A21)+SUMIFS('Review Queue'!$AB$2:$AB$64,'Review Queue'!$C$2:$C$64,$A21)-SUMIFS('Review Queue'!$O$2:$O$64,'Review Queue'!$C$2:$C$64,$A21) -> 77 | G21: =SUMIFS('All Comparisons'!$P$2:$P$561,'All Comparisons'!$C$2:$C$561,$A21)+SUMIFS('Review Queue'!$AC$2:$AC$64,'Review Queue'!$C$2:$C$64,$A21)-SUMIFS('Review Queue'!$P$2:$P$64,'Review Queue'!$C$2:$C$64,$A21) -> 2 | H21: =SUMIFS('All Comparisons'!$Q$2:$Q$561,'All Comparisons'!$C$2:$C$561,$A21)+SUMIFS('Review Queue'!$AD$2:$AD$64,'Review Queue'!$C$2:$C$64,$A21)-SUMIFS('Review Queue'!$Q$2:$Q$64,'Review Queue'!$C$2:$C$64,$A21) -> 3 | I21: =IFERROR(F21/(F21+G21),0) -> 0.97468354 | J21: =IFERROR(F21/(F21+H21),0) -> 0.9625 | K21: =IFERROR(2*I21*J21/(I21+J21),0) -> 0.96855346 | L21: =COUNTIFS('Review Queue'!$C$2:$C$64,$A21,'Review Queue'!$Y$2:$Y$64,"<>Reviewed",'Review Queue'!$X$2:$X$64,"<>Yes") -> 5 | M21: =COUNTIFS('Review Queue'!$C$2:$C$64,$A21,'Review Queue'!$AA$2:$AA$64,"INCOMPLETE") -> 0
A22: KSA | B22: Ontvanger | C22: =COUNTIFS('All Comparisons'!$C$2:$C$561,$A22,'All Comparisons'!$D$2:$D$561,$B22)-COUNTIFS('Review Queue'!$C$2:$C$64,$A22,'Review Queue'!$D$2:$D$64,$B22,'Review Queue'!$X$2:$X$64,"Yes") -> 20 | D22: =SUMIFS('All Comparisons'!$R$2:$R$561,'All Comparisons'!$C$2:$C$561,$A22,'All Comparisons'!$D$2:$D$561,$B22)+SUMIFS('Review Queue'!$AE$2:$AE$64,'Review Queue'!$C$2:$C$64,$A22,'Review Queue'!$D$2:$D$64,$B22)-SUMIFS('Review Queue'!$R$2:$R$64,'Review Queue'!$C$2:$C$64,$A22,'Review Queue'!$D$2:$D$64,$B22) -> 17 | E22: =IFERROR(D22/C22,0) -> 0.85 | F22: =SUMIFS('All Comparisons'!$O$2:$O$561,'All Comparisons'!$C$2:$C$561,$A22,'All Comparisons'!$D$2:$D$561,$B22)+SUMIFS('Review Queue'!$AB$2:$AB$64,'Review Queue'!$C$2:$C$64,$A22,'Review Queue'!$D$2:$D$64,$B22)-SUMIFS('Review Queue'!$O$2:$O$64,'Review Queue'!$C$2:$C$64,$A22,'Review Queue'!$D$2:$D$64,$B22) -> 17 | G22: =SUMIFS('All Comparisons'!$P$2:$P$561,'All Comparisons'!$C$2:$C$561,$A22,'All Comparisons'!$D$2:$D$561,$B22)+SUMIFS('Review Queue'!$AC$2:$AC$64,'Review Queue'!$C$2:$C$64,$A22,'Review Queue'!$D$2:$D$64,$B22)-SUMIFS('Review Queue'!$P$2:$P$64,'Review Queue'!$C$2:$C$64,$A22,'Review Queue'!$D$2:$D$64,$B22) -> 3 | H22: =SUMIFS('All Comparisons'!$Q$2:$Q$561,'All Comparisons'!$C$2:$C$561,$A22,'All Comparisons'!$D$2:$D$561,$B22)+SUMIFS('Review Queue'!$AD$2:$AD$64,'Review Queue'!$C$2:$C$64,$A22,'Review Queue'!$D$2:$D$64,$B22)-SUMIFS('Review Queue'!$Q$2:$Q$64,'Review Queue'!$C$2:$C$64,$A22,'Review Queue'!$D$2:$D$64,$B22) -> 3 | I22: =IFERROR(F22/(F22+G22),0) -> 0.85 | J22: =IFERROR(F22/(F22+H22),0) -> 0.85 | K22: =IFERROR(2*I22*J22/(I22+J22),0) -> 0.85 | L22: =COUNTIFS('Review Queue'!$C$2:$C$64,$A22,'Review Queue'!$D$2:$D$64,$B22,'Review Queue'!$Y$2:$Y$64,"<>Reviewed",'Review Queue'!$X$2:$X$64,"<>Yes") -> 6 | M22: =COUNTIFS('Review Queue'!$C$2:$C$64,$A22,'Review Queue'!$D$2:$D$64,$B22,'Review Queue'!$AA$2:$AA$64,"INCOMPLETE") -> 0
A23: KSA | B23: Besluitvormend Orgaan | C23: =COUNTIFS('All Comparisons'!$C$2:$C$561,$A23,'All Comparisons'!$D$2:$D$561,$B23)-COUNTIFS('Review Queue'!$C$2:$C$64,$A23,'Review Queue'!$D$2:$D$64,$B23,'Review Queue'!$X$2:$X$64,"Yes") -> 20 | D23: =SUMIFS('All Comparisons'!$R$2:$R$561,'All Comparisons'!$C$2:$C$561,$A23,'All Comparisons'!$D$2:$D$561,$B23)+SUMIFS('Review Queue'!$AE$2:$AE$64,'Review Queue'!$C$2:$C$64,$A23,'Review Queue'!$D$2:$D$64,$B23)-SUMIFS('Review Queue'!$R$2:$R$64,'Review Queue'!$C$2:$C$64,$A23,'Review Queue'!$D$2:$D$64,$B23) -> 20 | E23: =IFERROR(D23/C23,0) -> 1 | F23: =SUMIFS('All Comparisons'!$O$2:$O$561,'All Comparisons'!$C$2:$C$561,$A23,'All Comparisons'!$D$2:$D$561,$B23)+SUMIFS('Review Queue'!$AB$2:$AB$64,'Review Queue'!$C$2:$C$64,$A23,'Review Queue'!$D$2:$D$64,$B23)-SUMIFS('Review Queue'!$O$2:$O$64,'Review Queue'!$C$2:$C$64,$A23,'Review Queue'!$D$2:$D$64,$B23) -> 20 | G23: =SUMIFS('All Comparisons'!$P$2:$P$561,'All Comparisons'!$C$2:$C$561,$A23,'All Comparisons'!$D$2:$D$561,$B23)+SUMIFS('Review Queue'!$AC$2:$AC$64,'Review Queue'!$C$2:$C$64,$A23,'Review Queue'!$D$2:$D$64,$B23)-SUMIFS('Review Queue'!$P$2:$P$64,'Review Queue'!$C$2:$C$64,$A23,'Review Queue'!$D$2:$D$64,$B23) -> 0 | H23: =SUMIFS('All Comparisons'!$Q$2:$Q$561,'All Comparisons'!$C$2:$C$561,$A23,'All Comparisons'!$D$2:$D$561,$B23)+SUMIFS('Review Queue'!$AD$2:$AD$64,'Review Queue'!$C$2:$C$64,$A23,'Review Queue'!$D$2:$D$64,$B23)-SUMIFS('Review Queue'!$Q$2:$Q$64,'Review Queue'!$C$2:$C$64,$A23,'Review Queue'!$D$2:$D$64,$B23) -> 0 | I23: =IFERROR(F23/(F23+G23),0) -> 1 | J23: =IFERROR(F23/(F23+H23),0) -> 1 | K23: =IFERROR(2*I23*J23/(I23+J23),0) -> 1 | L23: =COUNTIFS('Review Queue'!$C$2:$C$64,$A23,'Review Queue'!$D$2:$D$64,$B23,'Review Queue'!$Y$2:$Y$64,"<>Reviewed",'Review Queue'!$X$2:$X$64,"<>Yes") -> 1 | M23: =COUNTIFS('Review Queue'!$C$2:$C$64,$A23,'Review Queue'!$D$2:$D$64,$B23,'Review Queue'!$AA$2:$AA$64,"INCOMPLETE") -> 0
A24: KSA | B24: Rechtshandeling | C24: =COUNTIFS('All Comparisons'!$C$2:$C$561,$A24,'All Comparisons'!$D$2:$D$561,$B24)-COUNTIFS('Review Queue'!$C$2:$C$64,$A24,'Review Queue'!$D$2:$D$64,$B24,'Review Queue'!$X$2:$X$64,"Yes") -> 20 | D24: =SUMIFS('All Comparisons'!$R$2:$R$561,'All Comparisons'!$C$2:$C$561,$A24,'All Comparisons'!$D$2:$D$561,$B24)+SUMIFS('Review Queue'!$AE$2:$AE$64,'Review Queue'!$C$2:$C$64,$A24,'Review Queue'!$D$2:$D$64,$B24)-SUMIFS('Review Queue'!$R$2:$R$64,'Review Queue'!$C$2:$C$64,$A24,'Review Queue'!$D$2:$D$64,$B24) -> 20 | E24: =IFERROR(D24/C24,0) -> 1 | F24: =SUMIFS('All Comparisons'!$O$2:$O$561,'All Comparisons'!$C$2:$C$561,$A24,'All Comparisons'!$D$2:$D$561,$B24)+SUMIFS('Review Queue'!$AB$2:$AB$64,'Review Queue'!$C$2:$C$64,$A24,'Review Queue'!$D$2:$D$64,$B24)-SUMIFS('Review Queue'!$O$2:$O$64,'Review Queue'!$C$2:$C$64,$A24,'Review Queue'!$D$2:$D$64,$B24) -> 20 | G24: =SUMIFS('All Comparisons'!$P$2:$P$561,'All Comparisons'!$C$2:$C$561,$A24,'All Comparisons'!$D$2:$D$561,$B24)+SUMIFS('Review Queue'!$AC$2:$AC$64,'Review Queue'!$C$2:$C$64,$A24,'Review Queue'!$D$2:$D$64,$B24)-SUMIFS('Review Queue'!$P$2:$P$64,'Review Queue'!$C$2:$C$64,$A24,'Review Queue'!$D$2:$D$64,$B24) -> 0 | H24: =SUMIFS('All Comparisons'!$Q$2:$Q$561,'All Comparisons'!$C$2:$C$561,$A24,'All Comparisons'!$D$2:$D$561,$B24)+SUMIFS('Review Queue'!$AD$2:$AD$64,'Review Queue'!$C$2:$C$64,$A24,'Review Queue'!$D$2:$D$64,$B24)-SUMIFS('Review Queue'!$Q$2:$Q$64,'Review Queue'!$C$2:$C$64,$A24,'Review Queue'!$D$2:$D$64,$B24) -> 0 | I24: =IFERROR(F24/(F24+G24),0) -> 1 | J24: =IFERROR(F24/(F24+H24),0) -> 1 | K24: =IFERROR(2*I24*J24/(I24+J24),0) -> 1 | L24: =COUNTIFS('Review Queue'!$C$2:$C$64,$A24,'Review Queue'!$D$2:$D$64,$B24,'Review Queue'!$Y$2:$Y$64,"<>Reviewed",'Review Queue'!$X$2:$X$64,"<>Yes") -> 0 | M24: =COUNTIFS('Review Queue'!$C$2:$C$64,$A24,'Review Queue'!$D$2:$D$64,$B24,'Review Queue'!$AA$2:$AA$64,"INCOMPLETE") -> 0
A25: KSA | B25: Rechtsobject | C25: =COUNTIFS('All Comparisons'!$C$2:$C$561,$A25,'All Comparisons'!$D$2:$D$561,$B25)-COUNTIFS('Review Queue'!$C$2:$C$64,$A25,'Review Queue'!$D$2:$D$64,$B25,'Review Queue'!$X$2:$X$64,"Yes") -> 20 | D25: =SUMIFS('All Comparisons'!$R$2:$R$561,'All Comparisons'!$C$2:$C$561,$A25,'All Comparisons'!$D$2:$D$561,$B25)+SUMIFS('Review Queue'!$AE$2:$AE$64,'Review Queue'!$C$2:$C$64,$A25,'Review Queue'!$D$2:$D$64,$B25)-SUMIFS('Review Queue'!$R$2:$R$64,'Review Queue'!$C$2:$C$64,$A25,'Review Queue'!$D$2:$D$64,$B25) -> 20 | E25: =IFERROR(D25/C25,0) -> 1 | F25: =SUMIFS('All Comparisons'!$O$2:$O$561,'All Comparisons'!$C$2:$C$561,$A25,'All Comparisons'!$D$2:$D$561,$B25)+SUMIFS('Review Queue'!$AB$2:$AB$64,'Review Queue'!$C$2:$C$64,$A25,'Review Queue'!$D$2:$D$64,$B25)-SUMIFS('Review Queue'!$O$2:$O$64,'Review Queue'!$C$2:$C$64,$A25,'Review Queue'!$D$2:$D$64,$B25) -> 20 | G25: =SUMIFS('All Comparisons'!$P$2:$P$561,'All Comparisons'!$C$2:$C$561,$A25,'All Comparisons'!$D$2:$D$561,$B25)+SUMIFS('Review Queue'!$AC$2:$AC$64,'Review Queue'!$C$2:$C$64,$A25,'Review Queue'!$D$2:$D$64,$B25)-SUMIFS('Review Queue'!$P$2:$P$64,'Review Queue'!$C$2:$C$64,$A25,'Review Queue'!$D$2:$D$64,$B25) -> 0 | H25: =SUMIFS('All Comparisons'!$Q$2:$Q$561,'All Comparisons'!$C$2:$C$561,$A25,'All Comparisons'!$D$2:$D$561,$B25)+SUMIFS('Review Queue'!$AD$2:$AD$64,'Review Queue'!$C$2:$C$64,$A25,'Review Queue'!$D$2:$D$64,$B25)-SUMIFS('Review Queue'!$Q$2:$Q$64,'Review Queue'!$C$2:$C$64,$A25,'Review Queue'!$D$2:$D$64,$B25) -> 0 | I25: =IFERROR(F25/(F25+G25),0) -> 1 | J25: =IFERROR(F25/(F25+H25),0) -> 1 | K25: =IFERROR(2*I25*J25/(I25+J25),0) -> 1 | L25: =COUNTIFS('Review Queue'!$C$2:$C$64,$A25,'Review Queue'!$D$2:$D$64,$B25,'Review Queue'!$Y$2:$Y$64,"<>Reviewed",'Review Queue'!$X$2:$X$64,"<>Yes") -> 1 | M25: =COUNTIFS('Review Queue'!$C$2:$C$64,$A25,'Review Queue'!$D$2:$D$64,$B25,'Review Queue'!$AA$2:$AA$64,"INCOMPLETE") -> 0
A26: KSA | B26: Overall | C26: =COUNTIFS('All Comparisons'!$C$2:$C$561,$A26)-COUNTIFS('Review Queue'!$C$2:$C$64,$A26,'Review Queue'!$X$2:$X$64,"Yes") -> 80 | D26: =SUMIFS('All Comparisons'!$R$2:$R$561,'All Comparisons'!$C$2:$C$561,$A26)+SUMIFS('Review Queue'!$AE$2:$AE$64,'Review Queue'!$C$2:$C$64,$A26)-SUMIFS('Review Queue'!$R$2:$R$64,'Review Queue'!$C$2:$C$64,$A26) -> 77 | E26: =IFERROR(D26/C26,0) -> 0.9625 | F26: =SUMIFS('All Comparisons'!$O$2:$O$561,'All Comparisons'!$C$2:$C$561,$A26)+SUMIFS('Review Queue'!$AB$2:$AB$64,'Review Queue'!$C$2:$C$64,$A26)-SUMIFS('Review Queue'!$O$2:$O$64,'Review Queue'!$C$2:$C$64,$A26) -> 77 | G26: =SUMIFS('All Comparisons'!$P$2:$P$561,'All Comparisons'!$C$2:$C$561,$A26)+SUMIFS('Review Queue'!$AC$2:$AC$64,'Review Queue'!$C$2:$C$64,$A26)-SUMIFS('Review Queue'!$P$2:$P$64,'Review Queue'!$C$2:$C$64,$A26) -> 3 | H26: =SUMIFS('All Comparisons'!$Q$2:$Q$561,'All Comparisons'!$C$2:$C$561,$A26)+SUMIFS('Review Queue'!$AD$2:$AD$64,'Review Queue'!$C$2:$C$64,$A26)-SUMIFS('Review Queue'!$Q$2:$Q$64,'Review Queue'!$C$2:$C$64,$A26) -> 3 | I26: =IFERROR(F26/(F26+G26),0) -> 0.9625 | J26: =IFERROR(F26/(F26+H26),0) -> 0.9625 | K26: =IFERROR(2*I26*J26/(I26+J26),0) -> 0.9625 | L26: =COUNTIFS('Review Queue'!$C$2:$C$64,$A26,'Review Queue'!$Y$2:$Y$64,"<>Reviewed",'Review Queue'!$X$2:$X$64,"<>Yes") -> 8 | M26: =COUNTIFS('Review Queue'!$C$2:$C$64,$A26,'Review Queue'!$AA$2:$AA$64,"INCOMPLETE") -> 0
A27: ROT | B27: Ontvanger | C27: =COUNTIFS('All Comparisons'!$C$2:$C$561,$A27,'All Comparisons'!$D$2:$D$561,$B27)-COUNTIFS('Review Queue'!$C$2:$C$64,$A27,'Review Queue'!$D$2:$D$64,$B27,'Review Queue'!$X$2:$X$64,"Yes") -> 20 | D27: =SUMIFS('All Comparisons'!$R$2:$R$561,'All Comparisons'!$C$2:$C$561,$A27,'All Comparisons'!$D$2:$D$561,$B27)+SUMIFS('Review Queue'!$AE$2:$AE$64,'Review Queue'!$C$2:$C$64,$A27,'Review Queue'!$D$2:$D$64,$B27)-SUMIFS('Review Queue'!$R$2:$R$64,'Review Queue'!$C$2:$C$64,$A27,'Review Queue'!$D$2:$D$64,$B27) -> 6 | E27: =IFERROR(D27/C27,0) -> 0.3 | F27: =SUMIFS('All Comparisons'!$O$2:$O$561,'All Comparisons'!$C$2:$C$561,$A27,'All Comparisons'!$D$2:$D$561,$B27)+SUMIFS('Review Queue'!$AB$2:$AB$64,'Review Queue'!$C$2:$C$64,$A27,'Review Queue'!$D$2:$D$64,$B27)-SUMIFS('Review Queue'!$O$2:$O$64,'Review Queue'!$C$2:$C$64,$A27,'Review Queue'!$D$2:$D$64,$B27) -> 0 | G27: =SUMIFS('All Comparisons'!$P$2:$P$561,'All Comparisons'!$C$2:$C$561,$A27,'All Comparisons'!$D$2:$D$561,$B27)+SUMIFS('Review Queue'!$AC$2:$AC$64,'Review Queue'!$C$2:$C$64,$A27,'Review Queue'!$D$2:$D$64,$B27)-SUMIFS('Review Queue'!$P$2:$P$64,'Review Queue'!$C$2:$C$64,$A27,'Review Queue'!$D$2:$D$64,$B27) -> 0 | H27: =SUMIFS('All Comparisons'!$Q$2:$Q$561,'All Comparisons'!$C$2:$C$561,$A27,'All Comparisons'!$D$2:$D$561,$B27)+SUMIFS('Review Queue'!$AD$2:$AD$64,'Review Queue'!$C$2:$C$64,$A27,'Review Queue'!$D$2:$D$64,$B27)-SUMIFS('Review Queue'!$Q$2:$Q$64,'Review Queue'!$C$2:$C$64,$A27,'Review Queue'!$D$2:$D$64,$B27) -> 14 | I27: =IFERROR(F27/(F27+G27),0) -> 0 | J27: =IFERROR(F27/(F27+H27),0) -> 0 | K27: =IFERROR(2*I27*J27/(I27+J27),0) -> 0 | L27: =COUNTIFS('Review Queue'!$C$2:$C$64,$A27,'Review Queue'!$D$2:$D$64,$B27,'Review Queue'!$Y$2:$Y$64,"<>Reviewed",'Review Queue'!$X$2:$X$64,"<>Yes") -> 14 | M27: =COUNTIFS('Review Queue'!$C$2:$C$64,$A27,'Review Queue'!$D$2:$D$64,$B27,'Review Queue'!$AA$2:$AA$64,"INCOMPLETE") -> 0
A28: ROT | B28: Besluitvormend Orgaan | C28: =COUNTIFS('All Comparisons'!$C$2:$C$561,$A28,'All Comparisons'!$D$2:$D$561,$B28)-COUNTIFS('Review Queue'!$C$2:$C$64,$A28,'Review Queue'!$D$2:$D$64,$B28,'Review Queue'!$X$2:$X$64,"Yes") -> 20 | D28: =SUMIFS('All Comparisons'!$R$2:$R$561,'All Comparisons'!$C$2:$C$561,$A28,'All Comparisons'!$D$2:$D$561,$B28)+SUMIFS('Review Queue'!$AE$2:$AE$64,'Review Queue'!$C$2:$C$64,$A28,'Review Queue'!$D$2:$D$64,$B28)-SUMIFS('Review Queue'!$R$2:$R$64,'Review Queue'!$C$2:$C$64,$A28,'Review Queue'!$D$2:$D$64,$B28) -> 20 | E28: =IFERROR(D28/C28,0) -> 1 | F28: =SUMIFS('All Comparisons'!$O$2:$O$561,'All Comparisons'!$C$2:$C$561,$A28,'All Comparisons'!$D$2:$D$561,$B28)+SUMIFS('Review Queue'!$AB$2:$AB$64,'Review Queue'!$C$2:$C$64,$A28,'Review Queue'!$D$2:$D$64,$B28)-SUMIFS('Review Queue'!$O$2:$O$64,'Review Queue'!$C$2:$C$64,$A28,'Review Queue'!$D$2:$D$64,$B28) -> 20 | G28: =SUMIFS('All Comparisons'!$P$2:$P$561,'All Comparisons'!$C$2:$C$561,$A28,'All Comparisons'!$D$2:$D$561,$B28)+SUMIFS('Review Queue'!$AC$2:$AC$64,'Review Queue'!$C$2:$C$64,$A28,'Review Queue'!$D$2:$D$64,$B28)-SUMIFS('Review Queue'!$P$2:$P$64,'Review Queue'!$C$2:$C$64,$A28,'Review Queue'!$D$2:$D$64,$B28) -> 0 | H28: =SUMIFS('All Comparisons'!$Q$2:$Q$561,'All Comparisons'!$C$2:$C$561,$A28,'All Comparisons'!$D$2:$D$561,$B28)+SUMIFS('Review Queue'!$AD$2:$AD$64,'Review Queue'!$C$2:$C$64,$A28,'Review Queue'!$D$2:$D$64,$B28)-SUMIFS('Review Queue'!$Q$2:$Q$64,'Review Queue'!$C$2:$C$64,$A28,'Review Queue'!$D$2:$D$64,$B28) -> 0 | I28: =IFERROR(F28/(F28+G28),0) -> 1 | J28: =IFERROR(F28/(F28+H28),0) -> 1 | K28: =IFERROR(2*I28*J28/(I28+J28),0) -> 1 | L28: =COUNTIFS('Review Queue'!$C$2:$C$64,$A28,'Review Queue'!$D$2:$D$64,$B28,'Review Queue'!$Y$2:$Y$64,"<>Reviewed",'Review Queue'!$X$2:$X$64,"<>Yes") -> 0 | M28: =COUNTIFS('Review Queue'!$C$2:$C$64,$A28,'Review Queue'!$D$2:$D$64,$B28,'Review Queue'!$AA$2:$AA$64,"INCOMPLETE") -> 0
A29: ROT | B29: Rechtshandeling | C29: =COUNTIFS('All Comparisons'!$C$2:$C$561,$A29,'All Comparisons'!$D$2:$D$561,$B29)-COUNTIFS('Review Queue'!$C$2:$C$64,$A29,'Review Queue'!$D$2:$D$64,$B29,'Review Queue'!$X$2:$X$64,"Yes") -> 20 | D29: =SUMIFS('All Comparisons'!$R$2:$R$561,'All Comparisons'!$C$2:$C$561,$A29,'All Comparisons'!$D$2:$D$561,$B29)+SUMIFS('Review Queue'!$AE$2:$AE$64,'Review Queue'!$C$2:$C$64,$A29,'Review Queue'!$D$2:$D$64,$B29)-SUMIFS('Review Queue'!$R$2:$R$64,'Review Queue'!$C$2:$C$64,$A29,'Review Queue'!$D$2:$D$64,$B29) -> 20 | E29: =IFERROR(D29/C29,0) -> 1 | F29: =SUMIFS('All Comparisons'!$O$2:$O$561,'All Comparisons'!$C$2:$C$561,$A29,'All Comparisons'!$D$2:$D$561,$B29)+SUMIFS('Review Queue'!$AB$2:$AB$64,'Review Queue'!$C$2:$C$64,$A29,'Review Queue'!$D$2:$D$64,$B29)-SUMIFS('Review Queue'!$O$2:$O$64,'Review Queue'!$C$2:$C$64,$A29,'Review Queue'!$D$2:$D$64,$B29) -> 20 | G29: =SUMIFS('All Comparisons'!$P$2:$P$561,'All Comparisons'!$C$2:$C$561,$A29,'All Comparisons'!$D$2:$D$561,$B29)+SUMIFS('Review Queue'!$AC$2:$AC$64,'Review Queue'!$C$2:$C$64,$A29,'Review Queue'!$D$2:$D$64,$B29)-SUMIFS('Review Queue'!$P$2:$P$64,'Review Queue'!$C$2:$C$64,$A29,'Review Queue'!$D$2:$D$64,$B29) -> 0 | H29: =SUMIFS('All Comparisons'!$Q$2:$Q$561,'All Comparisons'!$C$2:$C$561,$A29,'All Comparisons'!$D$2:$D$561,$B29)+SUMIFS('Review Queue'!$AD$2:$AD$64,'Review Queue'!$C$2:$C$64,$A29,'Review Queue'!$D$2:$D$64,$B29)-SUMIFS('Review Queue'!$Q$2:$Q$64,'Review Queue'!$C$2:$C$64,$A29,'Review Queue'!$D$2:$D$64,$B29) -> 0 | I29: =IFERROR(F29/(F29+G29),0) -> 1 | J29: =IFERROR(F29/(F29+H29),0) -> 1 | K29: =IFERROR(2*I29*J29/(I29+J29),0) -> 1 | L29: =COUNTIFS('Review Queue'!$C$2:$C$64,$A29,'Review Queue'!$D$2:$D$64,$B29,'Review Queue'!$Y$2:$Y$64,"<>Reviewed",'Review Queue'!$X$2:$X$64,"<>Yes") -> 1 | M29: =COUNTIFS('Review Queue'!$C$2:$C$64,$A29,'Review Queue'!$D$2:$D$64,$B29,'Review Queue'!$AA$2:$AA$64,"INCOMPLETE") -> 0
A30: ROT | B30: Rechtsobject | C30: =COUNTIFS('All Comparisons'!$C$2:$C$561,$A30,'All Comparisons'!$D$2:$D$561,$B30)-COUNTIFS('Review Queue'!$C$2:$C$64,$A30,'Review Queue'!$D$2:$D$64,$B30,'Review Queue'!$X$2:$X$64,"Yes") -> 20 | D30: =SUMIFS('All Comparisons'!$R$2:$R$561,'All Comparisons'!$C$2:$C$561,$A30,'All Comparisons'!$D$2:$D$561,$B30)+SUMIFS('Review Queue'!$AE$2:$AE$64,'Review Queue'!$C$2:$C$64,$A30,'Review Queue'!$D$2:$D$64,$B30)-SUMIFS('Review Queue'!$R$2:$R$64,'Review Queue'!$C$2:$C$64,$A30,'Review Queue'!$D$2:$D$64,$B30) -> 20 | E30: =IFERROR(D30/C30,0) -> 1 | F30: =SUMIFS('All Comparisons'!$O$2:$O$561,'All Comparisons'!$C$2:$C$561,$A30,'All Comparisons'!$D$2:$D$561,$B30)+SUMIFS('Review Queue'!$AB$2:$AB$64,'Review Queue'!$C$2:$C$64,$A30,'Review Queue'!$D$2:$D$64,$B30)-SUMIFS('Review Queue'!$O$2:$O$64,'Review Queue'!$C$2:$C$64,$A30,'Review Queue'!$D$2:$D$64,$B30) -> 20 | G30: =SUMIFS('All Comparisons'!$P$2:$P$561,'All Comparisons'!$C$2:$C$561,$A30,'All Comparisons'!$D$2:$D$561,$B30)+SUMIFS('Review Queue'!$AC$2:$AC$64,'Review Queue'!$C$2:$C$64,$A30,'Review Queue'!$D$2:$D$64,$B30)-SUMIFS('Review Queue'!$P$2:$P$64,'Review Queue'!$C$2:$C$64,$A30,'Review Queue'!$D$2:$D$64,$B30) -> 0 | H30: =SUMIFS('All Comparisons'!$Q$2:$Q$561,'All Comparisons'!$C$2:$C$561,$A30,'All Comparisons'!$D$2:$D$561,$B30)+SUMIFS('Review Queue'!$AD$2:$AD$64,'Review Queue'!$C$2:$C$64,$A30,'Review Queue'!$D$2:$D$64,$B30)-SUMIFS('Review Queue'!$Q$2:$Q$64,'Review Queue'!$C$2:$C$64,$A30,'Review Queue'!$D$2:$D$64,$B30) -> 0 | I30: =IFERROR(F30/(F30+G30),0) -> 1 | J30: =IFERROR(F30/(F30+H30),0) -> 1 | K30: =IFERROR(2*I30*J30/(I30+J30),0) -> 1 | L30: =COUNTIFS('Review Queue'!$C$2:$C$64,$A30,'Review Queue'!$D$2:$D$64,$B30,'Review Queue'!$Y$2:$Y$64,"<>Reviewed",'Review Queue'!$X$2:$X$64,"<>Yes") -> 1 | M30: =COUNTIFS('Review Queue'!$C$2:$C$64,$A30,'Review Queue'!$D$2:$D$64,$B30,'Review Queue'!$AA$2:$AA$64,"INCOMPLETE") -> 0
A31: ROT | B31: Overall | C31: =COUNTIFS('All Comparisons'!$C$2:$C$561,$A31)-COUNTIFS('Review Queue'!$C$2:$C$64,$A31,'Review Queue'!$X$2:$X$64,"Yes") -> 80 | D31: =SUMIFS('All Comparisons'!$R$2:$R$561,'All Comparisons'!$C$2:$C$561,$A31)+SUMIFS('Review Queue'!$AE$2:$AE$64,'Review Queue'!$C$2:$C$64,$A31)-SUMIFS('Review Queue'!$R$2:$R$64,'Review Queue'!$C$2:$C$64,$A31) -> 66 | E31: =IFERROR(D31/C31,0) -> 0.825 | F31: =SUMIFS('All Comparisons'!$O$2:$O$561,'All Comparisons'!$C$2:$C$561,$A31)+SUMIFS('Review Queue'!$AB$2:$AB$64,'Review Queue'!$C$2:$C$64,$A31)-SUMIFS('Review Queue'!$O$2:$O$64,'Review Queue'!$C$2:$C$64,$A31) -> 60 | G31: =SUMIFS('All Comparisons'!$P$2:$P$561,'All Comparisons'!$C$2:$C$561,$A31)+SUMIFS('Review Queue'!$AC$2:$AC$64,'Review Queue'!$C$2:$C$64,$A31)-SUMIFS('Review Queue'!$P$2:$P$64,'Review Queue'!$C$2:$C$64,$A31) -> 0 | H31: =SUMIFS('All Comparisons'!$Q$2:$Q$561,'All Comparisons'!$C$2:$C$561,$A31)+SUMIFS('Review Queue'!$AD$2:$AD$64,'Review Queue'!$C$2:$C$64,$A31)-SUMIFS('Review Queue'!$Q$2:$Q$64,'Review Queue'!$C$2:$C$64,$A31) -> 14 | I31: =IFERROR(F31/(F31+G31),0) -> 1 | J31: =IFERROR(F31/(F31+H31),0) -> 0.81081081 | K31: =IFERROR(2*I31*J31/(I31+J31),0) -> 0.89552239 | L31: =COUNTIFS('Review Queue'!$C$2:$C$64,$A31,'Review Queue'!$Y$2:$Y$64,"<>Reviewed",'Review Queue'!$X$2:$X$64,"<>Yes") -> 16 | M31: =COUNTIFS('Review Queue'!$C$2:$C$64,$A31,'Review Queue'!$AA$2:$AA$64,"INCOMPLETE") -> 0
A32: Rijksoverheid | B32: Ontvanger | C32: =COUNTIFS('All Comparisons'!$C$2:$C$561,$A32,'All Comparisons'!$D$2:$D$561,$B32)-COUNTIFS('Review Queue'!$C$2:$C$64,$A32,'Review Queue'!$D$2:$D$64,$B32,'Review Queue'!$X$2:$X$64,"Yes") -> 20 | D32: =SUMIFS('All Comparisons'!$R$2:$R$561,'All Comparisons'!$C$2:$C$561,$A32,'All Comparisons'!$D$2:$D$561,$B32)+SUMIFS('Review Queue'!$AE$2:$AE$64,'Review Queue'!$C$2:$C$64,$A32,'Review Queue'!$D$2:$D$64,$B32)-SUMIFS('Review Queue'!$R$2:$R$64,'Review Queue'!$C$2:$C$64,$A32,'Review Queue'!$D$2:$D$64,$B32) -> 18 | E32: =IFERROR(D32/C32,0) -> 0.9 | F32: =SUMIFS('All Comparisons'!$O$2:$O$561,'All Comparisons'!$C$2:$C$561,$A32,'All Comparisons'!$D$2:$D$561,$B32)+SUMIFS('Review Queue'!$AB$2:$AB$64,'Review Queue'!$C$2:$C$64,$A32,'Review Queue'!$D$2:$D$64,$B32)-SUMIFS('Review Queue'!$O$2:$O$64,'Review Queue'!$C$2:$C$64,$A32,'Review Queue'!$D$2:$D$64,$B32) -> 18 | G32: =SUMIFS('All Comparisons'!$P$2:$P$561,'All Comparisons'!$C$2:$C$561,$A32,'All Comparisons'!$D$2:$D$561,$B32)+SUMIFS('Review Queue'!$AC$2:$AC$64,'Review Queue'!$C$2:$C$64,$A32,'Review Queue'!$D$2:$D$64,$B32)-SUMIFS('Review Queue'!$P$2:$P$64,'Review Queue'!$C$2:$C$64,$A32,'Review Queue'!$D$2:$D$64,$B32) -> 2 | H32: =SUMIFS('All Comparisons'!$Q$2:$Q$561,'All Comparisons'!$C$2:$C$561,$A32,'All Comparisons'!$D$2:$D$561,$B32)+SUMIFS('Review Queue'!$AD$2:$AD$64,'Review Queue'!$C$2:$C$64,$A32,'Review Queue'!$D$2:$D$64,$B32)-SUMIFS('Review Queue'!$Q$2:$Q$64,'Review Queue'!$C$2:$C$64,$A32,'Review Queue'!$D$2:$D$64,$B32) -> 2 | I32: =IFERROR(F32/(F32+G32),0) -> 0.9 | J32: =IFERROR(F32/(F32+H32),0) -> 0.9 | K32: =IFERROR(2*I32*J32/(I32+J32),0) -> 0.9 | L32: =COUNTIFS('Review Queue'!$C$2:$C$64,$A32,'Review Queue'!$D$2:$D$64,$B32,'Review Queue'!$Y$2:$Y$64,"<>Reviewed",'Review Queue'!$X$2:$X$64,"<>Yes") -> 2 | M32: =COUNTIFS('Review Queue'!$C$2:$C$64,$A32,'Review Queue'!$D$2:$D$64,$B32,'Review Queue'!$AA$2:$AA$64,"INCOMPLETE") -> 0
A33: Rijksoverheid | B33: Besluitvormend Orgaan | C33: =COUNTIFS('All Comparisons'!$C$2:$C$561,$A33,'All Comparisons'!$D$2:$D$561,$B33)-COUNTIFS('Review Queue'!$C$2:$C$64,$A33,'Review Queue'!$D$2:$D$64,$B33,'Review Queue'!$X$2:$X$64,"Yes") -> 20 | D33: =SUMIFS('All Comparisons'!$R$2:$R$561,'All Comparisons'!$C$2:$C$561,$A33,'All Comparisons'!$D$2:$D$561,$B33)+SUMIFS('Review Queue'!$AE$2:$AE$64,'Review Queue'!$C$2:$C$64,$A33,'Review Queue'!$D$2:$D$64,$B33)-SUMIFS('Review Queue'!$R$2:$R$64,'Review Queue'!$C$2:$C$64,$A33,'Review Queue'!$D$2:$D$64,$B33) -> 17 | E33: =IFERROR(D33/C33,0) -> 0.85 | F33: =SUMIFS('All Comparisons'!$O$2:$O$561,'All Comparisons'!$C$2:$C$561,$A33,'All Comparisons'!$D$2:$D$561,$B33)+SUMIFS('Review Queue'!$AB$2:$AB$64,'Review Queue'!$C$2:$C$64,$A33,'Review Queue'!$D$2:$D$64,$B33)-SUMIFS('Review Queue'!$O$2:$O$64,'Review Queue'!$C$2:$C$64,$A33,'Review Queue'!$D$2:$D$64,$B33) -> 17 | G33: =SUMIFS('All Comparisons'!$P$2:$P$561,'All Comparisons'!$C$2:$C$561,$A33,'All Comparisons'!$D$2:$D$561,$B33)+SUMIFS('Review Queue'!$AC$2:$AC$64,'Review Queue'!$C$2:$C$64,$A33,'Review Queue'!$D$2:$D$64,$B33)-SUMIFS('Review Queue'!$P$2:$P$64,'Review Queue'!$C$2:$C$64,$A33,'Review Queue'!$D$2:$D$64,$B33) -> 1 | H33: =SUMIFS('All Comparisons'!$Q$2:$Q$561,'All Comparisons'!$C$2:$C$561,$A33,'All Comparisons'!$D$2:$D$561,$B33)+SUMIFS('Review Queue'!$AD$2:$AD$64,'Review Queue'!$C$2:$C$64,$A33,'Review Queue'!$D$2:$D$64,$B33)-SUMIFS('Review Queue'!$Q$2:$Q$64,'Review Queue'!$C$2:$C$64,$A33,'Review Queue'!$D$2:$D$64,$B33) -> 3 | I33: =IFERROR(F33/(F33+G33),0) -> 0.94444444 | J33: =IFERROR(F33/(F33+H33),0) -> 0.85 | K33: =IFERROR(2*I33*J33/(I33+J33),0) -> 0.89473684 | L33: =COUNTIFS('Review Queue'!$C$2:$C$64,$A33,'Review Queue'!$D$2:$D$64,$B33,'Review Queue'!$Y$2:$Y$64,"<>Reviewed",'Review Queue'!$X$2:$X$64,"<>Yes") -> 3 | M33: =COUNTIFS('Review Queue'!$C$2:$C$64,$A33,'Review Queue'!$D$2:$D$64,$B33,'Review Queue'!$AA$2:$AA$64,"INCOMPLETE") -> 0
A34: Rijksoverheid | B34: Rechtshandeling | C34: =COUNTIFS('All Comparisons'!$C$2:$C$561,$A34,'All Comparisons'!$D$2:$D$561,$B34)-COUNTIFS('Review Queue'!$C$2:$C$64,$A34,'Review Queue'!$D$2:$D$64,$B34,'Review Queue'!$X$2:$X$64,"Yes") -> 20 | D34: =SUMIFS('All Comparisons'!$R$2:$R$561,'All Comparisons'!$C$2:$C$561,$A34,'All Comparisons'!$D$2:$D$561,$B34)+SUMIFS('Review Queue'!$AE$2:$AE$64,'Review Queue'!$C$2:$C$64,$A34,'Review Queue'!$D$2:$D$64,$B34)-SUMIFS('Review Queue'!$R$2:$R$64,'Review Queue'!$C$2:$C$64,$A34,'Review Queue'!$D$2:$D$64,$B34) -> 20 | E34: =IFERROR(D34/C34,0) -> 1 | F34: =SUMIFS('All Comparisons'!$O$2:$O$561,'All Comparisons'!$C$2:$C$561,$A34,'All Comparisons'!$D$2:$D$561,$B34)+SUMIFS('Review Queue'!$AB$2:$AB$64,'Review Queue'!$C$2:$C$64,$A34,'Review Queue'!$D$2:$D$64,$B34)-SUMIFS('Review Queue'!$O$2:$O$64,'Review Queue'!$C$2:$C$64,$A34,'Review Queue'!$D$2:$D$64,$B34) -> 20 | G34: =SUMIFS('All Comparisons'!$P$2:$P$561,'All Comparisons'!$C$2:$C$561,$A34,'All Comparisons'!$D$2:$D$561,$B34)+SUMIFS('Review Queue'!$AC$2:$AC$64,'Review Queue'!$C$2:$C$64,$A34,'Review Queue'!$D$2:$D$64,$B34)-SUMIFS('Review Queue'!$P$2:$P$64,'Review Queue'!$C$2:$C$64,$A34,'Review Queue'!$D$2:$D$64,$B34) -> 0 | H34: =SUMIFS('All Comparisons'!$Q$2:$Q$561,'All Comparisons'!$C$2:$C$561,$A34,'All Comparisons'!$D$2:$D$561,$B34)+SUMIFS('Review Queue'!$AD$2:$AD$64,'Review Queue'!$C$2:$C$64,$A34,'Review Queue'!$D$2:$D$64,$B34)-SUMIFS('Review Queue'!$Q$2:$Q$64,'Review Queue'!$C$2:$C$64,$A34,'Review Queue'!$D$2:$D$64,$B34) -> 0 | I34: =IFERROR(F34/(F34+G34),0) -> 1 | J34: =IFERROR(F34/(F34+H34),0) -> 1 | K34: =IFERROR(2*I34*J34/(I34+J34),0) -> 1 | L34: =COUNTIFS('Review Queue'!$C$2:$C$64,$A34,'Review Queue'!$D$2:$D$64,$B34,'Review Queue'!$Y$2:$Y$64,"<>Reviewed",'Review Queue'!$X$2:$X$64,"<>Yes") -> 0 | M34: =COUNTIFS('Review Queue'!$C$2:$C$64,$A34,'Review Queue'!$D$2:$D$64,$B34,'Review Queue'!$AA$2:$AA$64,"INCOMPLETE") -> 0
A35: Rijksoverheid | B35: Rechtsobject | C35: =COUNTIFS('All Comparisons'!$C$2:$C$561,$A35,'All Comparisons'!$D$2:$D$561,$B35)-COUNTIFS('Review Queue'!$C$2:$C$64,$A35,'Review Queue'!$D$2:$D$64,$B35,'Review Queue'!$X$2:$X$64,"Yes") -> 20 | D35: =SUMIFS('All Comparisons'!$R$2:$R$561,'All Comparisons'!$C$2:$C$561,$A35,'All Comparisons'!$D$2:$D$561,$B35)+SUMIFS('Review Queue'!$AE$2:$AE$64,'Review Queue'!$C$2:$C$64,$A35,'Review Queue'!$D$2:$D$64,$B35)-SUMIFS('Review Queue'!$R$2:$R$64,'Review Queue'!$C$2:$C$64,$A35,'Review Queue'!$D$2:$D$64,$B35) -> 20 | E35: =IFERROR(D35/C35,0) -> 1 | F35: =SUMIFS('All Comparisons'!$O$2:$O$561,'All Comparisons'!$C$2:$C$561,$A35,'All Comparisons'!$D$2:$D$561,$B35)+SUMIFS('Review Queue'!$AB$2:$AB$64,'Review Queue'!$C$2:$C$64,$A35,'Review Queue'!$D$2:$D$64,$B35)-SUMIFS('Review Queue'!$O$2:$O$64,'Review Queue'!$C$2:$C$64,$A35,'Review Queue'!$D$2:$D$64,$B35) -> 20 | G35: =SUMIFS('All Comparisons'!$P$2:$P$561,'All Comparisons'!$C$2:$C$561,$A35,'All Comparisons'!$D$2:$D$561,$B35)+SUMIFS('Review Queue'!$AC$2:$AC$64,'Review Queue'!$C$2:$C$64,$A35,'Review Queue'!$D$2:$D$64,$B35)-SUMIFS('Review Queue'!$P$2:$P$64,'Review Queue'!$C$2:$C$64,$A35,'Review Queue'!$D$2:$D$64,$B35) -> 0 | H35: =SUMIFS('All Comparisons'!$Q$2:$Q$561,'All Comparisons'!$C$2:$C$561,$A35,'All Comparisons'!$D$2:$D$561,$B35)+SUMIFS('Review Queue'!$AD$2:$AD$64,'Review Queue'!$C$2:$C$64,$A35,'Review Queue'!$D$2:$D$64,$B35)-SUMIFS('Review Queue'!$Q$2:$Q$64,'Review Queue'!$C$2:$C$64,$A35,'Review Queue'!$D$2:$D$64,$B35) -> 0 | I35: =IFERROR(F35/(F35+G35),0) -> 1 | J35: =IFERROR(F35/(F35+H35),0) -> 1 | K35: =IFERROR(2*I35*J35/(I35+J35),0) -> 1 | L35: =COUNTIFS('Review Queue'!$C$2:$C$64,$A35,'Review Queue'!$D$2:$D$64,$B35,'Review Queue'!$Y$2:$Y$64,"<>Reviewed",'Review Queue'!$X$2:$X$64,"<>Yes") -> 2 | M35: =COUNTIFS('Review Queue'!$C$2:$C$64,$A35,'Review Queue'!$D$2:$D$64,$B35,'Review Queue'!$AA$2:$AA$64,"INCOMPLETE") -> 0
A36: Rijksoverheid | B36: Overall | C36: =COUNTIFS('All Comparisons'!$C$2:$C$561,$A36)-COUNTIFS('Review Queue'!$C$2:$C$64,$A36,'Review Queue'!$X$2:$X$64,"Yes") -> 80 | D36: =SUMIFS('All Comparisons'!$R$2:$R$561,'All Comparisons'!$C$2:$C$561,$A36)+SUMIFS('Review Queue'!$AE$2:$AE$64,'Review Queue'!$C$2:$C$64,$A36)-SUMIFS('Review Queue'!$R$2:$R$64,'Review Queue'!$C$2:$C$64,$A36) -> 75 | E36: =IFERROR(D36/C36,0) -> 0.9375 | F36: =SUMIFS('All Comparisons'!$O$2:$O$561,'All Comparisons'!$C$2:$C$561,$A36)+SUMIFS('Review Queue'!$AB$2:$AB$64,'Review Queue'!$C$2:$C$64,$A36)-SUMIFS('Review Queue'!$O$2:$O$64,'Review Queue'!$C$2:$C$64,$A36) -> 75 | G36: =SUMIFS('All Comparisons'!$P$2:$P$561,'All Comparisons'!$C$2:$C$561,$A36)+SUMIFS('Review Queue'!$AC$2:$AC$64,'Review Queue'!$C$2:$C$64,$A36)-SUMIFS('Review Queue'!$P$2:$P$64,'Review Queue'!$C$2:$C$64,$A36) -> 3 | H36: =SUMIFS('All Comparisons'!$Q$2:$Q$561,'All Comparisons'!$C$2:$C$561,$A36)+SUMIFS('Review Queue'!$AD$2:$AD$64,'Review Queue'!$C$2:$C$64,$A36)-SUMIFS('Review Queue'!$Q$2:$Q$64,'Review Queue'!$C$2:$C$64,$A36) -> 5 | I36: =IFERROR(F36/(F36+G36),0) -> 0.96153846 | J36: =IFERROR(F36/(F36+H36),0) -> 0.9375 | K36: =IFERROR(2*I36*J36/(I36+J36),0) -> 0.94936709 | L36: =COUNTIFS('Review Queue'!$C$2:$C$64,$A36,'Review Queue'!$Y$2:$Y$64,"<>Reviewed",'Review Queue'!$X$2:$X$64,"<>Yes") -> 7 | M36: =COUNTIFS('Review Queue'!$C$2:$C$64,$A36,'Review Queue'!$AA$2:$AA$64,"INCOMPLETE") -> 0

Sheet Review Queue
A1: evaluation_id | B1: document_id | C1: authority | D1: feature | E1: annotator_1_raw | F1: annotator_(2, 3)_raw | G1: annotator_1_normalized | H1: annotator_(2, 3)_normalized | I1: annotator_1_spans | J1: annotator_(2, 3)_spans | K1: matched_values | L1: unmatched_annotator_1 | M1: unmatched_annotator_(2, 3) | N1: auto_category | O1: auto_TP | P1: auto_FP | Q1: auto_FN | R1: auto_full_agreement | S1: annotator_1_reviewed | T1: annotator_(2, 3)_reviewed | U1: manual_TP | V1: manual_FP | W1: manual_FN | X1: exclude | Y1: reviewer_status | Z1: reviewer_notes | AA1: override_check | AB1: final_TP | AC1: final_FP | AD1: final_FN | AE1: final_full_agreement | AF1: evidence_snippet
A2: ACM__ontheffing_12285_104259-ontheffingbesluit-albermarle.txt::Besluitvormend Orgaan | B2: ACM__ontheffing_12285_104259-ontheffingbesluit-albermarle.txt | C2: ACM | D2: Besluitvormend Orgaan | E2: De Autoriteit Consument en Markt | F2: Autoriteit Consument en Markt | G2: de autoriteit consument en markt | H2: autoriteit consument en markt | I2: De Autoriteit Consument en Markt [20914:20946] | J2: Autoriteit Consument en Markt [21249:21278] | L2: de autoriteit consument en markt | M2: autoriteit consument en markt | N2: Minor boundary/extent difference | O2: 0 | P2: 1 | Q2: 1 | R2: 0 | S2: De Autoriteit Consument en Markt | T2: Autoriteit Consument en Markt | U2: 1 | V2: 0 | W2: 0 | X2: No | Y2: Needs review | AA2: =IF(X2="Yes","Excluded",IF(COUNTA(U2:W2)=0,"Auto",IF(COUNTA(U2:W2)=3,"Manual","INCOMPLETE"))) -> Manual | AB2: =IF(X2="Yes",0,IF(AA2="Manual",U2,O2)) -> 1 | AC2: =IF(X2="Yes",0,IF(AA2="Manual",V2,P2)) -> 0 | AD2: =IF(X2="Yes",0,IF(AA2="Manual",W2,Q2)) -> 0 | AE2: =IF(X2="Yes","",IF(AND(AC2=0,AD2=0),1,0)) -> 1 | AF2: [...] de E-wet, hoeft ACM niet verder te beoordelen of de aanvraag voldoet aan de eisen van de E-wet. Daarom honoreert ACM de aanvraag op grond van artikel 15, eerste lid, onderdeel b, van de E-wet niet. ## 5 Dictum 25. De Autoriteit Consument en Markt besluit de aanvraag van Albemarle Catalysts Company B.V. af te wijzen. 26. Van dit besluit wordt mededeling gedaan in de Staatscourant. Voorts publiceert de Autoriteit Consument en Markt dit besluit op de internetpagina van de Autoriteit Consument en Markt. Den Haag, Datum: 18 november 2013 Autoriteit Consument en Markt namens deze, w.g. dr. F.J.H. Don bestuurslid Tegen dit besluit kan degene, wiens belang rechtstreeks bij dit besluit is betrokken, binnen zes weken na bekendmaking beroep instellen bij het College van Beroep voor [...]
A3: ACM__vergunning_11108_gazprom-marketing-trading-ltd-besluit-vergunning-gas-2011-07-01.txt::Besluitvormend Orgaan | B3: ACM__vergunning_11108_gazprom-marketing-trading-ltd-besluit-vergunning-gas-2011-07-01.txt | C3: ACM | D3: Besluitvormend Orgaan | E3: De Minister van Economische Zaken, Landbouw en Innovatie | G3: de minister van economische zaken, landbouw en innovatie | H3: <NONE> | I3: De Minister van Economische Zaken, Landbouw en Innovatie [13278:13334] | L3: de minister van economische zaken, landbouw en innovatie | N3: One annotator omitted feature | O3: 0 | P3: 1 | Q3: 0 | R3: 0 | S3: De Minister van Economische Zaken, Landbouw en Innovatie | X3: No | Y3: Needs review | AA3: =IF(X3="Yes","Excluded",IF(COUNTA(U3:W3)=0,"Auto",IF(COUNTA(U3:W3)=3,"Manual","INCOMPLETE"))) -> Auto | AB3: =IF(X3="Yes",0,IF(AA3="Manual",U3,O3)) -> 0 | AC3: =IF(X3="Yes",0,IF(AA3="Manual",V3,P3)) -> 1 | AD3: =IF(X3="Yes",0,IF(AA3="Manual",W3,Q3)) -> 0 | AE3: =IF(X3="Yes","",IF(AND(AC3=0,AD3=0),1,0)) -> 0 | AF3: [...] orden op de internetpagina van de Energiekamer NMa. 31. Dit besluit treedt in werking met ingang van de dag waarop het conform artikel 3:41 van de Algemene wet bestuursrecht is bekend gemaakt. Den Haag, Datum: De Minister van Economische Zaken, Landbouw en Innovatie namens deze: Janine Verweij Clustermanager Consumentenmarkt Tegen dit besluit kan degene, wiens belang rechtstreeks bij dit besluit is betrokken, binnen zes weken na de dag van bekendmaking van dit besluit een gem [...]
A4: ACM__vergunning_besluit-intrekken-vergunning-elektriciteit-energie-der-nederlanden.txt::Ontvanger | B4: ACM__vergunning_besluit-intrekken-vergunning-elektriciteit-energie-der-nederlanden.txt | C4: ACM | D4: Ontvanger | E4: EdN | F4: Energie der Nederlanden B.V. | G4: edn | H4: energie der nederlanden b.v | I4: EdN [4139:4142] | J4: Energie der Nederlanden B.V. [858:886] | L4: edn | M4: energie der nederlanden b.v | N4: Different value selected | O4: 0 | P4: 1 | Q4: 1 | R4: 0 | S4: EdN | T4: Energie der Nederlanden B.V. | U4: 1 | V4: 0 | W4: 0 | X4: No | Y4: Needs review | AA4: =IF(X4="Yes","Excluded",IF(COUNTA(U4:W4)=0,"Auto",IF(COUNTA(U4:W4)=3,"Manual","INCOMPLETE"))) -> Manual | AB4: =IF(X4="Yes",0,IF(AA4="Manual",U4,O4)) -> 1 | AC4: =IF(X4="Yes",0,IF(AA4="Manual",V4,P4)) -> 0 | AD4: =IF(X4="Yes",0,IF(AA4="Manual",W4,Q4)) -> 0 | AE4: =IF(X4="Yes","",IF(AND(AC4=0,AD4=0),1,0)) -> 1 | AF4: [...] beschikken over een aansluiting op een net met een totale maximale doorlaatwaarde van ten hoogste 3*80 A (hierna: kleinverbruikers) 3 . 2. Bij besluit van 23 juli 2013 is de statutaire naam van Anode B.V. gewijzigd in Energie der Nederlanden B.V. (hierna: EdN) 4 3. EdN heeft de ACM in een brief van 31 augustus 2017 gevraagd om de vergunning aan EdN in te trekken. 4. In zijn brief van 31 augustus 2017 heeft de rechtsgeldige vertegenwoordiger van EdN verklaard dat EdN geen elektriciteit meer levert aan kleinverbruikers. Daarnaast heeft EdN verklaard geen kleinverbruikende klanten meer in haar portefeuille te hebben. Dat betekent dat er dus geen overdracht van klanten aan een andere, vergunninghoudende energieleverancier hoeft plaats te vinden. ## II. Juridisch Kader 5. Het is verboden om zonder vergunning elektriciteit te leveren aan kleinverbruikers. Dit is bepaald in artikel 95a, eerste lid, van de Elektriciteitswet 1998. 6. De minister kan een op basis van artikel 95d van de Elektriciteitswet 1998 verleende vergunning voor het leveren van elektriciteit aan kleinverbruikers intrekken. Dit kan de minister op basis van artikel 95f, eerste lid, van de Elektriciteitswet 1998. 7. Een vergunning kan op basis van artikel 95f, eerste lid, Elektriciteitswet 1998 worden ingetrokken als de vergunninghouder: - a. hierom vraagt; ^ Artikel 95f, eerste lid, sub a, van de Elektriciteitswet 1998 3 Besluit tot verlening vergunning met kenmerk 102461/3.BT827 4 Artikel 95a, eerste lid, van de Elektriciteitswet 1998 Besluit tot naamswijziging van vergunning met kenmerk ACM/DC/2013/202834 2511 WB Den Haag 070 722 20 00 Openbaar - b. niet meer voldoet aan de verplichting, zoals beschreven in artikel 95b van de Elektriciteitswet 1998; - c. de voorschriften of opgelegde beperkingen niet nakomt; - d. bij de aanvraag onjuiste of onvolledige gegevens heeft gegeven. De vergunning wordt ingetrokken als blijkt dat, wanneer de vergunninghouder wel de juiste en volledige gegevens had ingediend, de ACM dan een andere beschikking had afgegeven; - e. naar het oordeel van de minister om andere redenen niet langer in staat moet worden geacht de vergunde activiteit of de voorwaarden voor de vergunning na te komen; - f. de voorschriften volgens de artikelen 95k en 95I van de Elektriciteitswet 1998 niet nakomt. 8. Bij 'Besluit mandaat, volmacht en machtiging ACM' 5 heeft de minister mandaat, volmacht en machtiging verleend aan de ACM tot onder andere het nemen van besluiten die verband houden met artikel 95f, eerste lid, van de Elektriciteitswet 1998. 9. Bij 'Besluit organisatie, mandaat, volmacht en machtiging ACM 2013' 6 heeft de directie Consumenten van de ACM mandaat en machtiging gekregen voor het nemen van besluiten en het verrichten van overige handelingen die verband houden met de Elektriciteitswet 1998 voor zover deze specifiek met consumentenbelangen te maken hebben. De directeur en teammanagers van de Directie Consumenten zijn bevoegd om een beslissing te nemen op deze aanvraag. ## Ill Beoordeling 10. De ACM acht het aannemelijk dat EdN de activiteiten waarvoor het de leveringsvergunning had, niet langer beoefent. Hiermee is het belang om de verleende vergunning in stand te houden komen te vervallen. * Besluit van 2 april 2013, Stcrt. 2013, nr. 9333 Besluit van 2 april 2013, Stcrt. 2013, nr. 9697 ## IV. Besluit 11. De minister besluit de vergunning voor het leveren van elektriciteit aan kleinverbruikers 7 van EdN in te trekken 8 . 12. De openbare versie van dit besluit publiceert ACM op haar website. 13. Dit besluit treedt in werking met ingang van de dag waarop het bekend is gemaakt 9 . Den Haag, 15 september 2017 (datum f [...]
A5: ACM__ontheffing_wijzigingsbesluit-ontheffing-voor-het-gesloten-distributiesysteem-van-medisch-centrum-leeuwarden.txt::Ontvanger | B5: ACM__ontheffing_wijzigingsbesluit-ontheffing-voor-het-gesloten-distributiesysteem-van-medisch-centrum-leeuwarden.txt | C5: ACM | D5: Ontvanger | E5: Medisch Centrum Leeuwarden B.V. | F5: Medisch Centrum Leeuwarden | G5: medisch centrum leeuwarden b.v | H5: medisch centrum leeuwarden | I5: Medisch Centrum Leeuwarden B.V. [9793:9824] | J5: Medisch Centrum Leeuwarden [9793:9819] | L5: medisch centrum leeuwarden b.v | M5: medisch centrum leeuwarden | N5: Minor boundary/extent difference | O5: 0 | P5: 1 | Q5: 1 | R5: 0 | S5: Medisch Centrum Leeuwarden B.V. | T5: Medisch Centrum Leeuwarden | U5: 1 | V5: 0 | W5: 0 | X5: No | Y5: Needs review | AA5: =IF(X5="Yes","Excluded",IF(COUNTA(U5:W5)=0,"Auto",IF(COUNTA(U5:W5)=3,"Manual","INCOMPLETE"))) -> Manual | AB5: =IF(X5="Yes",0,IF(AA5="Manual",U5,O5)) -> 1 | AC5: =IF(X5="Yes",0,IF(AA5="Manual",V5,P5)) -> 0 | AD5: =IF(X5="Yes",0,IF(AA5="Manual",W5,Q5)) -> 0 | AE5: =IF(X5="Yes","",IF(AND(AC5=0,AD5=0),1,0)) -> 1 | AF5: [...] l 15, eerste lid, onderdeel c, van de E-wet. ## 4 Dictum 21. De Autoriteit Consument en Markt besluit op grond van artikel 15, eerste lid, van de E-wet de ontheffing die zij heeft verleend op 11 december 2019 aan Medisch Centrum Leeuwarden B.V. te wijzigen. 22. Het onderhavige wijzigingsbesluit beperkt zich tot wijziging van het aantal op het GDS aangesloten afnemers en de wijziging van de geografische afbakening van het GDS op de Achlumerdijk 2 te Harlingen [...]
A6: ACM__vergunning_12805_wijziging-tenaamstelling-eneco-business-bv-in-eneco-zakelijk-bv-elektriciteit-2014-04-08.txt::Rechtshandeling | B6: ACM__vergunning_12805_wijziging-tenaamstelling-eneco-business-bv-in-eneco-zakelijk-bv-elektriciteit-2014-04-08.txt | C6: ACM | D6: Rechtshandeling | E6: naam gesteld | F6: wijziging | G6: naam gesteld | H6: wijziging | I6: naam gesteld [5391:5403] | J6: wijziging [4605:4614] | L6: naam gesteld | M6: wijziging | N6: Different value selected | O6: 0 | P6: 1 | Q6: 1 | R6: 0 | S6: naam gesteld | T6: wijziging | X6: No | Y6: Needs review | AA6: =IF(X6="Yes","Excluded",IF(COUNTA(U6:W6)=0,"Auto",IF(COUNTA(U6:W6)=3,"Manual","INCOMPLETE"))) -> Auto | AB6: =IF(X6="Yes",0,IF(AA6="Manual",U6,O6)) -> 0 | AC6: =IF(X6="Yes",0,IF(AA6="Manual",V6,P6)) -> 1 | AD6: =IF(X6="Yes",0,IF(AA6="Manual",W6,Q6)) -> 1 | AE6: =IF(X6="Yes","",IF(AND(AC6=0,AD6=0),1,0)) -> 0 | AF6: [...] jziging aangetoond dat de bedrijfsnaam is gewijzigd in Eneco Zakelijk BV. 14. ACM komt op basis van de verklaring van de rechtsgeldige vertegenwoordigers tot het oordeel dat het onderhavige besluit zich beperkt tot een wijziging in de tenaamstelling van de vergunning en geen enkele betrekking heeft op de organisatorische, technische en financiele kwaliteit van de aanvrager. 15. ACM merkt bij randnummer 14 op dat het onderhavige besluit niet vooraf is gegaan door een toetsing op de vereiste financiele, technische en organisatorische kwaliteit als beschreven in het juridisch kader, alsmede het nalevingsgedrag inzake de overige wettelijke verplichtingen die rusten op de aanvrager. ACM heeft het recht om op ieder moment deze kwaliteiten to controleren. ## IV. Besluit 16. Gelet op artikel 95d, eerste lid, van de Elektriciteitswet 1998, het Besluit en het bovenstaande, besluit de Minister van Economische Zaken dat de leveringsvergunning welke ten name is gesteld van Eneco Business BV op naam gesteld wordt van Eneco Zakelijk BV. 17. Van dit besluit wordt mededeling gedaan in de Staatscourant. Een versie van dit besluit zal tevens gepubliceerd worden op de website van ACM. ## Autoriteit Consument &amp; Markt Auto [...]
A7: ACM__ontheffing_besluit-ter-goedkeuring-van-de-methode-van-huntsman.txt::Rechtshandeling | B7: ACM__ontheffing_besluit-ter-goedkeuring-van-de-methode-van-huntsman.txt | C7: ACM | D7: Rechtshandeling | E7: keurt | goed | F7: keurt | G7: goed | keurt | H7: keurt | I7: keurt [38989:38994] || goed [39085:39089] | J7: keurt [38989:38994] | K7: keurt | L7: goed | N7: Partially overlapping value sets | O7: 1 | P7: 1 | Q7: 0 | R7: 0 | S7: keurt | goed | T7: keurt | U7: 1 | V7: 0 | W7: 0 | X7: No | Y7: Needs review | AA7: =IF(X7="Yes","Excluded",IF(COUNTA(U7:W7)=0,"Auto",IF(COUNTA(U7:W7)=3,"Manual","INCOMPLETE"))) -> Manual | AB7: =IF(X7="Yes",0,IF(AA7="Manual",U7,O7)) -> 1 | AC7: =IF(X7="Yes",0,IF(AA7="Manual",V7,P7)) -> 0 | AD7: =IF(X7="Yes",0,IF(AA7="Manual",W7,Q7)) -> 0 | AE7: =IF(X7="Yes","",IF(AND(AC7=0,AD7=0),1,0)) -> 1 | AF7: [...] k van het HvJ van 9 oktober 2008, zaak C-239/07 (Sabatauskas e.a.) en de de Conclusie van de Adv. Gen. Kokott van 12 juni 2008, zaak C-239/07 (Sabatauskas e.a.). ## 5. Dictum 46. De Autoriteit Consument en Markt keurt de van kracht zijnde methode van Huntsman Holland B.V. voor de berekening van de tarieven goed. Den Haag, Datum: 29-1-2018 w.g. Autoriteit Consument en Markt namens deze, dr. F.J.H. Don bestuurslid Tegen dit besluit kan degene wiens belang daarbij rechtstreeks is betrokken, binnen zes weken na de d [...]
A8: ACM__vergunning_11108_gazprom-marketing-trading-ltd-besluit-vergunning-gas-2011-07-01.txt::Rechtshandeling | B8: ACM__vergunning_11108_gazprom-marketing-trading-ltd-besluit-vergunning-gas-2011-07-01.txt | C8: ACM | D8: Rechtshandeling | E8: verlenen | F8: De Minister van Economische Zaken, Landbouw en Innovatie | verlenen | G8: verlenen | H8: de minister van economische zaken, landbouw en innovatie | verlenen | I8: verlenen [11571:11579] | J8: De Minister van Economische Zaken, Landbouw en Innovatie [13278:13334] || verlenen [102:110] | K8: verlenen | M8: de minister van economische zaken, landbouw en innovatie | N8: Partially overlapping value sets | O8: 1 | P8: 0 | Q8: 1 | R8: 0 | S8: verlenen | T8: De Minister van Economische Zaken, Landbouw en Innovatie | verlenen | U8: 1 | V8: 0 | W8: 0 | X8: No | Y8: Needs review | AA8: =IF(X8="Yes","Excluded",IF(COUNTA(U8:W8)=0,"Auto",IF(COUNTA(U8:W8)=3,"Manual","INCOMPLETE"))) -> Manual | AB8: =IF(X8="Yes",0,IF(AA8="Manual",U8,O8)) -> 1 | AC8: =IF(X8="Yes",0,IF(AA8="Manual",V8,P8)) -> 0 | AD8: =IF(X8="Yes",0,IF(AA8="Manual",W8,Q8)) -> 0 | AE8: =IF(X8="Yes","",IF(AND(AC8=0,AD8=0),1,0)) -> 1 | AF8: ## ENERGIEKAMER NMA Nummer : ## BESLUIT 102560\_2 Betreft: Retail Ltd. Besluit tot het verlenen van een vergunning voor de levering van gas aan kleinverbruikers op grond van artikel 45, eerste lid van de Gaswet aan Gazprom Marketing &amp; Trading I. 1. 2. 3. 4. 5. Aanvraag en procedure Op 21 april 2011 heeft Gazprom Marketing &amp; Trading Retail Ltd. (hierna: GMTR) bij de Mededingingsautoriteit (hierna: Energiekamer NMa) een aanvraag voor een vergunning directeur van de Directie Regulering Energie en Vervoer van de Nederlandse ingediend, als bedoeld in artikel 45, eerste lid van de Gaswet. Aanleiding voor deze aanvraag is het voornemen van GMTR om gas te leveren aan kleinverbruikers, als bedoeld in artikel 43, eerste lid van de Gaswet. Op 28 april 2011 heeft de Energiekamer NMa de ontvangst van de (incomplete) aanvraag van 1 vermelding van de ontbrekende gegevens en bescheiden, is GMTR hierbij uitgenodigd om de de vergunning voor het leveren van gas aan kleinverbruikers aan GMTR bevestigd. aanvraag aan te vullen. Op 2 mei 2011 heeft GMTR (schriftelijk) de laatste ontbrekende stukken aangeleverd. Onder 2 gegevens en bescheiden. De Energiekamer NMa heeft de aanvraag per die datum in Daarmee bevat de aanvraag van GMTR de door artikel 2, tweede lid van het Besluit behandeling genomen. Tijdens de behandeling van de aanvraag heeft GMTR op verzoek van de Energiekamer NMa 45, eerste lid sub a Gaswet. tevens overige (aanvullende) gegevens verstrekt over haar kwaliteiten, als bedoeld in artikel 1 Per brief met kenmerk 102560\_2/2.B1087 2 Besluit van 2 juni 2003,Stb.2003, nr. 234, laatstelijk gewijzigd bij besluit van 5 april 2005, Stb. 2005, nr. 200 vereiste ## II. Juridisch Kader 6. Op grond van artikel 43, eerste lid van de Gaswet is het verboden om zonder vergunning gas te leveren aan afnemers die naar een op het verbruik in voorgaande jaren gegronde verwachting minder dan 170.000 m 3 gas per jaar verbruiken. 7. De Minister van Economische Zaken, Landbouw en Innovatie (hierna: de Minister) verleent op grond van artikel 45, eerste lid van de Gaswet op aanvraag een vergunning indien de aanvrager genoegzaam aantoont dat hij: 3. (b) redelijkerwijs in staat kan worden geacht de verplichtingen als opgenomen in hoofdstuk 5 van de Gaswet na te komen. 4. (a) beschikt over de benodigde organisatorische, financiële en technische kwaliteiten voor een goede uitvoering van zijn taak; 8. Bij 'Besluit mandaat, volmacht en machtiging raad van bestuur van de Nederlands Mededingingsautoriteit' 3 heeft de Minister mandaat, volmacht en machtiging verleend aan de Raad van Bestuur van de Nederlandse Mededingingsautoriteit (hierna: de Raad) tot onder andere het nemen van besluiten die verband houden met artikel 45, eerste lid, van de Gaswet. 9. Bij 'Besluit organisatie, mandaat, volmacht en machtiging NMa 2009 4 heeft de Raad op zijn beurt mandaat en machtiging verleend aan de (plaatsvervangend) directeur en de clustermanagers van de Directie Regulering Energie en Vervoer van de Nederlandse Mededingingsautoriteit voor het nemen van besluiten en het verrichten van overige handelingen die verband houden met de Elektriciteitswet 1998 en de Gaswet. De (plaatsvervangend) directeur en de clustermanagers van de Directie Regulering Energie en Vervoer zijn aldus bevoegd om het onderhavige besluit (in ondermandaat) te nemen. 10. In het 'Besluit vergunning levering gas aan kleinverbruikers' 5 (hierna: het Besluit) zijn de criteria van artikel 45, eerste lid Gaswet uitgewerkt en nadere regels gesteld met betrekking tot de inhoud van en de procedure voor aanvraag van een vergunning. Criteria voor beoordeling van de aanvraag 11. In artikel 3 van het Besluit zijn de criteria van artikel 45, eerste lid Gaswet uitgewerkt. In onderdeel III. van het onderhavige besluit met opschrift 'Beoordeling' wordt nader op deze criteria in gegaan. 3 Besluit van 1 juli 2005, Stcrt. 2005, 126, laatstelijk gewijzigd bij besluit van 10 mei 2010, Stcrt. 2010, 7606 4 Besluit van 29 september 2009, Stcrt. 2009, nr. 14819, laatstelijk gewijzigd bij besluit van 6 april 2010, 5 Besluit van 2 juni 2003, Stb. 2003, nr. 234, laatstelijk gewijzigd bij besluit van 5 april 2005, Stb. 2005, nr.200 Stcrt . 2010, nr. 9370 Inhoud van en procedure voor aanvraag 12. Een aanvraag dient op grond van artikel 2, eerste lid van het Besluit te worden ingediend bij de directeur van de Directie Regulering Energie en Vervoer. In artikel 2, tweede lid van het Besluit is bepaald welke gegevens de aanvraag ten minste dient te bevatten. Op grond van artikel 4:2, tweede lid van de Algemene wet bestuursrecht kan bij de vergunningaanvraag aanvullende informatie worden gevoegd of kan door de Energiekamer NMa hierom worden gevraagd, indien deze informatie benodigd is voor het beoordelen van de aanvraag. 6 ## III. Beoordeling ## Introductie De Energiekamer NMa beoordeelt in het hierna volgende of GMTR, conform artikel 45, eerste lid van de Gaswet, genoegzaam heeft aangetoond te beschikken over 1) de vereiste organisatorische, financiële en technische kwaliteiten, en 2) redelijkerwijs in staat kan worden geacht de verplichtingen uit hoofdstuk 5 van de Gaswet na te komen. Organisatorische, financiële en technische kwaliteiten (artikel 45, eerste lid onder a Gaswet) 13. In artikel 3, tweede lid onder a tot en met d van het Besluit is bepaald wanneer de aanvrager beschikt over de benodigde organisatorische, financiële en technische kwaliteiten voor een goede uitvoering van zijn taak. ## Overbrugging uitgaven en inkomsten (sub a) 14. Op grond van artikel 3, tweede lid onder a van het Besluit is vereist dat de aanvrager financieel in staat is om de termijn tussen uitgaven voor inkoop van gas en transportcapaciteit en de inkomsten van kleinverbruikers te overbruggen. Op basis van de verstrekte gegevens en bescheiden is de Energiekamer NMa van oordeel dat GMTR genoegzaam heeft aangetoond aan dit vereiste te voldoen. ## Administratieve organisatie en controle (sub b) 15. Op grond van artikel 3, tweede lid onder b van het Besluit is vereist dat de aanvrager beschikt over een goede administratieve organisatie, met inbegrip van de financiële administratie, en over een goede interne of externe controle hierop. Op basis van de verstrekte gegevens en bescheiden is de Energiekamer NMa van oordeel dat GMTR genoegzaam heeft aangetoond aan dit vereiste te voldoen. ## Non-faillissement (sub c) / geen surseance van betaling (sub d) 16. Op grond van artikel 3, tweede lid onder c en d van het Besluit is vereist dat de aanvrager niet in staat van faillissement verkeert en hem geen surseance van betaling is verleend. GMTR heeft in dit verband informatie verstrekt van Companies House, een uitvoerend agentschap in Engeland van het 'Department for Business, Innnovation and Skills' dat verantwoordelijk is 6 Besluit van 2 juni 2003, Stb. 2003, nr. 234, p.7 voor de registratie van bedrijfsinformatie zoals vastgelegd in de 'Companies Act 2006' en aanverwante wetgeving. Hieruit is gebleken dat GMTR niet in staat van faillissement verkeert en dat voor GMTR geen surseance van betaling is aangevraagd. Op basis van de gegevens en bescheiden is de Energiekamer van oordeel dat GMTR genoegzaam heeft aangetoond aan voornoemd vereiste te voldoen. Nakoming van de verplichtingen in hoofdstuk 5 Gaswet (artikel 45, eerste lid onder b Gaswet) 17. In artikel 3, eerste lid van het Besluit is bepaald wanneer de aanvrager redelijkerwijs in staat kan worden geacht te verplichtingen als opgenomen in hoofdstuk 5 van de Gaswet na te komen. ## Inkoop- en transportcontracten 18. Op grond van artikel 3, eerste lid van het Besluit is vereist dat de aanvrager over zodanige inkoop- en transportcontracten (hierna: gasinkoop contracten) beschikt dat hij, gelet op de verwachten afzet, in staat zal zijn om op betrouwbare wijze zorg te dragen voor de levering van gas aan iedere kleinverbruiker die daarom verzoekt. GMTR heeft ten behoeve van de dienstverlening voor gas een overeenkomst gesloten met [VERTROUWELIJK] voor [VERTROUWELIJK]. Deze overeenkomst ziet op de verkoop en de levering van gas en aanverwante diensten. De Energiekamer NMa is van oordeel dat voornoemde overeenkomst waarborgt dat GMTR, gelet op haar afzetprognoses, [VERTROUWELIJK] in staat zal zijn om op een betrouwbare wijze zorg te dragen voor de levering van gas aan iedere kleinverbruiker die daarom verzoekt. Op basis van de gegevens en bescheiden is de Energiekamer NMa aldus van oordeel dat GMTR [VERTROUWELIJK] genoegzaam heeft aangetoond aan dit vereiste te voldoen. 19. Met betrekking tot de gasinkoop [VERTROUWELIJK] heeft GMTR verklaard [VERTROUWELIJK]. [VERTROUWELIJK] De Energiekamer NMa ziet aanleiding tot het opnemen van een specifiek voorschrift in de vergunning teneinde erop toe te zien dat GMTR [VERTROUWELIJK] gelet op de te verwachte afzet, in staat zal zijn om op betrouwbare wijze zorg te dragen voor de levering van gas aan iedere kleinverbruiker die daarom verzoekt. ## Redelijke voorwaarden 21. In artikel 3, derde lid van het Besluit is bepaald dat een aanvrager redelijke voorwaarden hanteert, indien deze voldoen aan de vereisten als opgenomen in de onderdelen a tot en met d van dit artikel. ## Offertes en overeenkomsten (sub a) /betalingsregeling (sub b)/ regeling voor het opzeggen en ontbinden (sub c) 22. Op grond van artikel 3, derde lid onderdeel a van het Besluit is vereist dat de aanvrager duidelijke offertes en overeenkomsten hanteert, waarin de hoogte van de tarieven en de opbouw hiervan is aangegeven. Op grond van artikel 3, derde lid onderdeel b en c van het Besluit is voorts vereist dat de aanvrager een transparante en redelijke betalingsregeling hanteert, alsmede een transparante en redelijke regeling voor het opzeggen en ontbinden van overeenkomsten. GMTR heeft in dit verband onder meer voorbeelden verstrekt van offertes, overeenkomsten en voorwaarden voor de levering van gas aan kleinverbruikers. Op basis van de gegevens en bescheiden is de Energiekamer NMa van oordeel dat GMTR genoegzaam heeft aangetoond aan de voornoemde vereisten te voldoen. ## Klachten- en geschillenregeling (sub d) 23. Op grond van artikel 3, derde lid onderdeel d van het Besluit is vereist dat de aanvrager in staat is om klachten en geschillen op adequate wijze te behandelen. GMTR heeft in dit verband een toereikende beschrijving van haar interne klachtenprocedure overgelegd, alsmede een bewijs van registratie bij de Geschillencommissie Energie en Water. Op basis van de gegevens en bescheiden is de Energiekamer NMa van oordeel dat GMTR genoegzaam heeft aangetoond aan de voornoemde vereisten te voldoen. ## IV. Besluit 24. De Energiekamer NMa is - onder verwijzing naar onderdeel III. van onderhavig besluit - van oordeel dat Gazprom Marketing &amp; Trading Retail Ltd. genoegzaam heeft aangetoond te beschikken over de benodigde organisatorische, financiële en technische kwaliteiten voor de goede uitvoering van zijn taak, alsmede redelijkerwijs in staat kan worden geacht om de verplichtingen als opgenomen in hoofdstuk 5 van de Gaswet na te komen, als bedoeld in artikel 45, eerste lid van de Gaswet. 25. Met inachtneming van artikel 45, eerste lid van de Gaswet en het Besluit vergunning levering gas aan kleinverbruikers, besluit de Energiekamer NMa namens de Minister aan Gazprom Marketing &amp; Trading Retail Ltd. een vergunning te verlenen voor het leveren van gas aan kleinverbruikers. 26. Aan de vergunning wordt het voorschrift verbonden dat Gazprom Marketing &amp; Trading Retail Ltd. onverwijld opgave doet aan de directeur van de Energiekamer NMa van wijzigingen in de bij aanvraag verstrekte gegevens en bescheiden. Hieronder wordt verstaan tenminste de artikel 2, tweede lid, sub b, e, f en g, van het Besluit opgenomen gegevens en bescheiden, alsmede de overige (aanvullende) gegevens omtrent haar (verwachte) financiële, technische en organisatorische kwaliteiten. 27. Aan de vergunning wordt voorts het voorschrift verbonden dat GMTR [VERTROUWELIJK] dient aan te tonen [VERTROUWELIJK] in staat te zullen zijn op een betrouwbare wijze zorg te dragen voor de levering van gas aan iedere kleinverbruiker die daarom verzoekt. 28. Aan de vergunning wordt tenslotte het voorschrift verbonden dat Gazprom Marketing &amp; Trading Retail Ltd. jaarlijks binnen één maand na vaststelling haar jaarrekening als bedoeld in artikel 2:361 e.v. BW aan de directeur van de Directie Regulering Energie en Vervoer toezendt. 29. Hierbij wordt gewezen op de bevoegdheid van de Minister om, conform artikel 47, eerste lid van de Gaswet, de vergunning van Gazprom Marketing &amp; Trading Retail Ltd. in te trekken, onder meer in het geval de in de vergunning opgenomen voorschriften niet worden nagekomen. 30. Van dit besluit wordt mededeling gedaan in de Staatscourant. Een versie van dit besluit zal tevens gepubliceerd worden op de internetpagina van de Energiekamer NMa. 31. Dit besluit treedt in werking met ingang van de dag waarop het conform artikel 3:41 van de Algemene wet bestuursrecht is bekend gemaakt. Den Haag, Datum: De Minister van Economische Zaken, Landbouw en Innovatie namens deze: Janine Verweij Clustermanager Consumentenmarkt Tegen dit besluit kan degene, wiens belang rechtstreeks bij dit besluit is betrokken, binnen zes weken na de dag van bekendmaking van dit besluit een gem [...]
A9: ACM__vergunning_12805_wijziging-tenaamstelling-eneco-business-bv-in-eneco-zakelijk-bv-elektriciteit-2014-04-08.txt::Rechtsobject | B9: ACM__vergunning_12805_wijziging-tenaamstelling-eneco-business-bv-in-eneco-zakelijk-bv-elektriciteit-2014-04-08.txt | C9: ACM | D9: Rechtsobject | E9: leveringsvergunning | F9: tenaamstelling van de vergunning | G9: leveringsvergunning | H9: tenaamstelling van de vergunning | I9: leveringsvergunning [5320:5339] | J9: tenaamstelling van de vergunning [4621:4653] | L9: leveringsvergunning | M9: tenaamstelling van de vergunning | N9: Different value selected | O9: 0 | P9: 1 | Q9: 1 | R9: 0 | S9: leveringsvergunning | T9: tenaamstelling van de vergunning | U9: 1 | V9: 0 | W9: 0 | X9: No | Y9: Needs review | AA9: =IF(X9="Yes","Excluded",IF(COUNTA(U9:W9)=0,"Auto",IF(COUNTA(U9:W9)=3,"Manual","INCOMPLETE"))) -> Manual | AB9: =IF(X9="Yes",0,IF(AA9="Manual",U9,O9)) -> 1 | AC9: =IF(X9="Yes",0,IF(AA9="Manual",V9,P9)) -> 0 | AD9: =IF(X9="Yes",0,IF(AA9="Manual",W9,Q9)) -> 0 | AE9: =IF(X9="Yes","",IF(AND(AC9=0,AD9=0),1,0)) -> 1 | AF9: [...] nd dat de bedrijfsnaam is gewijzigd in Eneco Zakelijk BV. 14. ACM komt op basis van de verklaring van de rechtsgeldige vertegenwoordigers tot het oordeel dat het onderhavige besluit zich beperkt tot een wijziging in de tenaamstelling van de vergunning en geen enkele betrekking heeft op de organisatorische, technische en financiele kwaliteit van de aanvrager. 15. ACM merkt bij randnummer 14 op dat het onderhavige besluit niet vooraf is gegaan door een toetsing op de vereiste financiele, technische en organisatorische kwaliteit als beschreven in het juridisch kader, alsmede het nalevingsgedrag inzake de overige wettelijke verplichtingen die rusten op de aanvrager. ACM heeft het recht om op ieder moment deze kwaliteiten to controleren. ## IV. Besluit 16. Gelet op artikel 95d, eerste lid, van de Elektriciteitswet 1998, het Besluit en het bovenstaande, besluit de Minister van Economische Zaken dat de leveringsvergunning welke ten name is gesteld van Eneco Business BV op naam gesteld wordt van Eneco Zakelijk BV. 17. Van dit besluit wordt mededeling gedaan in de Staatscourant. Een versie van dit besluit zal tevens gepubliceerd worden op [...]
A10: ANVS__PUC_3976_32_1.txt::Ontvanger | B10: ANVS__PUC_3976_32_1.txt | C10: ANVS | D10: Ontvanger | E10: Tata Steel IJmuiden B.V. | F10: Corus Staal B.V. | G10: tata steel ijmuiden b.v | H10: corus staal b.v | I10: Tata Steel IJmuiden B.V. [1810:1834] | J10: Corus Staal B.V. [200:216] | L10: tata steel ijmuiden b.v | M10: corus staal b.v | N10: Different value selected | O10: 0 | P10: 1 | Q10: 1 | R10: 0 | S10: Tata Steel IJmuiden B.V. | T10: Corus Staal B.V. | U10: 1 | V10: 0 | W10: 0 | X10: No | Y10: Needs review | AA10: =IF(X10="Yes","Excluded",IF(COUNTA(U10:W10)=0,"Auto",IF(COUNTA(U10:W10)=3,"Manual","INCOMPLETE"))) -> Manual | AB10: =IF(X10="Yes",0,IF(AA10="Manual",U10,O10)) -> 1 | AC10: =IF(X10="Yes",0,IF(AA10="Manual",V10,P10)) -> 0 | AD10: =IF(X10="Yes",0,IF(AA10="Manual",W10,Q10)) -> 0 | AE10: =IF(X10="Yes","",IF(AND(AC10=0,AD10=0),1,0)) -> 1 | AF10: No. 2010/1950-07 DE MINISTER VAN VOLKSHUISVESTING RUIMTELIJKE ORDENING EN MILIEUBEHEER Mede namens de minister van Sociale Zaken en Werkgelegenheid; Gezien de brief d.d. 1 september 2010 van Corus Staal B.V. (hierna te noemen Tata Steel IJmuiden B.V.) te Velsen-Noord (gemeente Velsen), strekkende tot wijziging van een vergunning als bedoeld in artikel 29 van de Kernenergiewet en als bedoeld in hoofdstuk 4, artikel 23, van het Besluit stralingsbescherming; Gelet op de artikelen 29-31 en 34 van de Kernenergiewet en het bepaalde in hoofdstuk 4 van het Besluit stralingsbescherming; Gelet op de d.d. 7 mei 1998, onder nr. 98/469 S, AI/CK/VCR/KEW, verleende vergunning, laatstelijk gewijzigd d.d. 18 juni 2009, onder nr. 2009/0991-06; Overwegende, dat de naam van de vergunninghouder is gewijzigd; Overwegende, dat de in de aanvraag bedoelde handelingen voorkomen in bijlage 1 (gerechtvaardigde handelingen en werkzaamheden) van de Regeling bekendmaking rechtvaardiging gebruik van ioniserende straling; Overwegende, dat de aanvrager reeds eerder een overeenkomstige vergunning met betrekking tot dezelfde plaats was verleend en niet is te verwachten dat door gebruikmaking van de vergunning nadeliger gevolgen voor mensen, dieren, planten en goederen kunnen worden veroorzaakt dan bij de eerder verleende vergunning in aanmerking is genomen; Gelet op artikel 20.5 van de Wet milieubeheer; Overwegende, dat om redenen van continuïteit van werkzaamheden in het onderhavige geval een zo spoedig mogelijke inwerkingtreding van deze vergunning noodzakelijk is. B E S L U I T : De d.d. 7 mei 1998, onder nr. 98/469 S, AI/CK/VCR/KEW, verleende vergunning, laatstelijk gewijzigd d.d. 18 juni 2009, onder nr. 2009/0991-06, wordt gewijzigd, zodat deze thans luidt als volgt: Aan Tata Steel IJmuiden B.V., Wenckebachstraat 1 te Velsen-Noord (gemeente Velsen), wordt vergunning verleend voor: - -het verrichten van handelingen met ioniserende straling uitzendende toestellen. - -het verrichten van handelingen met radioac [...]
A11: ANVS__PUC_1559_32_1.txt::Ontvanger | B11: ANVS__PUC_1559_32_1.txt | C11: ANVS | D11: Ontvanger | E11: de Technische Universiteit Eindhoven | F11: Technische Universiteit Eindhoven | G11: de technische universiteit eindhoven | H11: technische universiteit eindhoven | I11: de Technische Universiteit Eindhoven [3015:3051] | J11: Technische Universiteit Eindhoven [329:362] | L11: de technische universiteit eindhoven | M11: technische universiteit eindhoven | N11: Minor boundary/extent difference | O11: 0 | P11: 1 | Q11: 1 | R11: 0 | S11: de Technische Universiteit Eindhoven | T11: Technische Universiteit Eindhoven | U11: 1 | V11: 0 | W11: 0 | X11: No | Y11: Needs review | AA11: =IF(X11="Yes","Excluded",IF(COUNTA(U11:W11)=0,"Auto",IF(COUNTA(U11:W11)=3,"Manual","INCOMPLETE"))) -> Manual | AB11: =IF(X11="Yes",0,IF(AA11="Manual",U11,O11)) -> 1 | AC11: =IF(X11="Yes",0,IF(AA11="Manual",V11,P11)) -> 0 | AD11: =IF(X11="Yes",0,IF(AA11="Manual",W11,Q11)) -> 0 | AE11: =IF(X11="Yes","",IF(AND(AC11=0,AD11=0),1,0)) -> 1 | AF11: [...] 2004/84161 ## DE STAATSSECRETARIS VAN SOCIALE ZAKEN EN WERKGELEGENHEID Mede namens de Staatssecretaris van Volkshuisvesting, Ruimtelijke Ordening en Milieubeheer; Gezien de aanvraag d.d. 18 november 2004 van de Technische Universiteit Eindhoven te Eindhoven, om wijziging van een vergunning als bedoeld in hoofdstuk 4, artikel 23, van het Besluit stralingsbescherming; Gelet op artikel 34 van de Kernenergiewet en het bepaalde in hoofdstuk 4 van het Besluit stralingsbescherming; Gelet op de verleende vergunningen: - -d.d. 27 november 1981, nr. 64649, DGMH/S; - -d.d. 1 juli 2004, nr. 2004/46248, AI/IO/BES; Overwegende, dat de vergunning wordt aangevraagd tegen de achtergrond van het navolgende feitencomplex. De aanvrager beschikt over een viertal vergunningen als bedoeld in artikel 29 en 34 van de Kernenergiewet, waaronder een complexvergunning onder nummer 64649, DGMH/S, d.d. 27 november 1981. In deze vergunning zijn alle regelingen vastgelegd die betrekking hebben op de interne organisatie en de uitvoering van de stralingsbescherming. Verder is de vergunning qua bewoording en systematiek gebaseerd op het vroegere Besluit stralenbescherming Kernenergiewet. Om alle aspecten met betrekking tot de bescherming van mensen, dieren, planten en goederen en het Besluit stralingsbescherming goed te kunnen beoordelen zullen zoveel mogelijk alle handelingen in één vergunning worden ondergebracht. De aanvrager geeft ook aan dat wordt gestreefd om voor 1 juli 2005 een allesomvattende aanvraag in te dienen; Overwegende, dat alle handelingen met de versneller vallen binnen de verantwoordelijkheid van de Stralingsbeschermingseenheid van de Technische Universiteit Eindhoven, vastgelegd in de specifieke regeling in bijlage A5 SBD 02-1050 van de aanvraag d.d. 30 september 2002; Overwegende, dat alle vastgelegde interne voorschriften en procedures bindend zijn voor allen die binnen de locatie van de Technische Universiteit Eindhoven, al dan niet in dienstverband van de Technische Universiteit Eindhoven, werkzaam zijn; Overwegende, dat het stralingshygiënisch beleid van de Technische Universiteit Eindhoven er op gericht is de blootstelling zo laag als redelijkerwijs mogelijk te doen zijn; Overwegende, dat reeds eerder een vergunning is verleend voor een versneller op dezelfde locatie en niet is te verwachten dat door het gebruik nadeliger gevolgen voor mensen, dieren, planten en goederen kunnen worden veroorzaakt dan bij de eerder verleende vergunning in aanmerking is genomen; Gelet op artikel 20.5 van de Wet milieubeheer; Overwegende, dat om redenen van continuïteit van werkzaamheden in het onderhavige geval een zo spoedig mogelijk in werking treden van de vergunning noodzakelijk is. ## B E S L U I T : De d.d. 1 juli 2004, onder nr. 2004/46248, AI/IO/BES, verleende vergunning, wordt gewijzigd zodat deze thans luidt als volgt: Aan de Technische Universiteit Eindhoven, Den Dolech 2 te Eindhoven, wordt tot 1 juli 2005 vergunning verleend voor: - -het verrichten van handelingen met een toestel; - -het verrichten van onderzoeks- en ontwikkelingswerk aan een toestel. ## In deze ve [...]
A12: ANVS__PUC_3848_32_1.txt::Ontvanger | B12: ANVS__PUC_3848_32_1.txt | C12: ANVS | D12: Ontvanger | E12: de Centrale Organisatie Voor Radioactief Afval (COVRA) N.V. | F12: de Centrale Organisatie Voor Radioactief Afval (COVRA) | G12: de centrale organisatie voor radioactief afval (covra) n.v | H12: de centrale organisatie voor radioactief afval (covra) | I12: de Centrale Organisatie Voor Radioactief Afval (COVRA) N.V. [2196:2255] | J12: de Centrale Organisatie Voor Radioactief Afval (COVRA) [2196:2250] | L12: de centrale organisatie voor radioactief afval (covra) n.v | M12: de centrale organisatie voor radioactief afval (covra) | N12: Minor boundary/extent difference | O12: 0 | P12: 1 | Q12: 1 | R12: 0 | S12: de Centrale Organisatie Voor Radioactief Afval (COVRA) N.V. | T12: de Centrale Organisatie Voor Radioactief Afval (COVRA) | U12: 1 | V12: 0 | W12: 0 | X12: No | Y12: Needs review | AA12: =IF(X12="Yes","Excluded",IF(COUNTA(U12:W12)=0,"Auto",IF(COUNTA(U12:W12)=3,"Manual","INCOMPLETE"))) -> Manual | AB12: =IF(X12="Yes",0,IF(AA12="Manual",U12,O12)) -> 1 | AC12: =IF(X12="Yes",0,IF(AA12="Manual",V12,P12)) -> 0 | AD12: =IF(X12="Yes",0,IF(AA12="Manual",W12,Q12)) -> 0 | AE12: =IF(X12="Yes","",IF(AND(AC12=0,AD12=0),1,0)) -> 1 | AF12: [...] ende, dat om redenen van continuïteit van werkzaamheden in het onderhavige geval een zo spoedig mogelijke vervoer van de bedoelde splijtstoffen naar de plaats van bestemming noodzakelijk is. ## B E S L U I T : Aan de Centrale Organisatie Voor Radioactief Afval (COVRA) N.V., Spanjeweg 1 te Vlissingen-Oost, wordt vergunning verleend voor het vervoeren over de weg over Nederlands grondgebied en het aansluitend buiten Nederlands grondgebied (doen) brengen van de volgende zending: aantal ze [...]
A13: ANVS__PUC_4207_32_1.txt::Ontvanger | B13: ANVS__PUC_4207_32_1.txt | C13: ANVS | D13: Ontvanger | E13: de Stichting Amphia Ziekenhuis | F13: Stichting Amphia Ziekenhuis | G13: de stichting amphia ziekenhuis | H13: stichting amphia ziekenhuis | I13: de Stichting Amphia Ziekenhuis [1059:1089] | J13: Stichting Amphia Ziekenhuis [221:248] | L13: de stichting amphia ziekenhuis | M13: stichting amphia ziekenhuis | N13: Minor boundary/extent difference | O13: 0 | P13: 1 | Q13: 1 | R13: 0 | S13: de Stichting Amphia Ziekenhuis | T13: Stichting Amphia Ziekenhuis | U13: 1 | V13: 0 | W13: 0 | X13: No | Y13: Needs review | AA13: =IF(X13="Yes","Excluded",IF(COUNTA(U13:W13)=0,"Auto",IF(COUNTA(U13:W13)=3,"Manual","INCOMPLETE"))) -> Manual | AB13: =IF(X13="Yes",0,IF(AA13="Manual",U13,O13)) -> 1 | AC13: =IF(X13="Yes",0,IF(AA13="Manual",V13,P13)) -> 0 | AD13: =IF(X13="Yes",0,IF(AA13="Manual",W13,Q13)) -> 0 | AE13: =IF(X13="Yes","",IF(AND(AC13=0,AD13=0),1,0)) -> 1 | AF13: [...] o.2011/0259-08 No. 2011/0259-08 <!-- image --> ## DE MINISTER VAN ECONOMISCHE ZAKEN, LANDBOUW EN INNOVATIE Gezien de aanvraag d.d. 22 februari 2011 en de daarop aanvullende informatie d.d. 26 april 2011, van de Stichting Amphia Ziekenhuis te Breda, om wijziging van een vergunning als bedoeld in artikel 29 van de Kernenergiewet en als bedoeld in hoofdstuk 4, artikel 23, van het Besluit stralingsbescherming; Gelet op de artikelen 29-31 en 34 van de Kernenergiewet en het bepaalde in hoofdstuk 4 van het Besluit stralingsbescherming; Gelet op de d.d. 14 augustus 2000, onder nr. 2000/21704, AI/CK/B/KEW, verleende vergunning, laatstelijk gewijzigd d.d. 28 mei 2010, onder nr. 2010/1000-05; Overwegende, dat de in de aanvraag bedoelde handelingen voorkomen in bijlage 1 (gerechtvaardigde handelingen en werkzaamheden) van de Regeling bekendmaking rechtvaardiging gebruik van ioniserende straling. ## BESLUIT: D i i i gewijzigd d.d. 28 mei 2010, onder nr. 2010/1000-05 wordt gewijzigd, zodat deze thans luidt als volgt: Aan de Stichting Amphia Ziekenhuis, Molengracht 21 te Breda, wordt vergunning verleend voor: - het verrichten van handelingen met radioactieve stoffen; - het verrichten van handelingen met ioniserende straling uitzendende toestellen. ## In deze ve [...]
A14: ANVS__PUC_1522_32_1.txt::Rechtshandeling | B14: ANVS__PUC_1522_32_1.txt | C14: ANVS | D14: Rechtshandeling | E14: gewijzigd | F14: verleend | G14: gewijzigd | H14: verleend | I14: gewijzigd [1035:1044] | J14: verleend [1193:1201] | L14: gewijzigd | M14: verleend | N14: Different value selected | O14: 0 | P14: 1 | Q14: 1 | R14: 0 | S14: gewijzigd | T14: verleend | X14: No | Y14: Needs review | AA14: =IF(X14="Yes","Excluded",IF(COUNTA(U14:W14)=0,"Auto",IF(COUNTA(U14:W14)=3,"Manual","INCOMPLETE"))) -> Auto | AB14: =IF(X14="Yes",0,IF(AA14="Manual",U14,O14)) -> 0 | AC14: =IF(X14="Yes",0,IF(AA14="Manual",V14,P14)) -> 1 | AD14: =IF(X14="Yes",0,IF(AA14="Manual",W14,Q14)) -> 1 | AE14: =IF(X14="Yes","",IF(AND(AC14=0,AD14=0),1,0)) -> 0 | AF14: [...] wachting van het behalen van het diploma, verbonden aan deze cursus, een tijdelijke vergunning wordt verleend. ## B E S L U I T : De d.d. 30 maart 2004, onder nr. 2004/11544, AI/IO/BES, verleende vergunning, wordt gewijzigd, zodat deze thans luidt als volgt: Aan Metaalhandel W. Ketting &amp; Zn. B.V., Bakkersoordsekade 16 te Pernis, wordt tot 1 april 2005 vergunning verleend voor het verrichten van handelingen met radioactieve stoffen. ## In deze vergunning wordt verstaan onder: - -bergplaats: - -besmettingscontrole: Ruimte, uitsluitend bedoeld voor de opslag van radioactieve stof [...]
A15: ANVS__PUC_5845_32_1.txt::Rechtshandeling | B15: ANVS__PUC_5845_32_1.txt | C15: ANVS | D15: Rechtshandeling | E15: ingetrokken | F15: intrekking | G15: ingetrokken | H15: intrekking | I15: ingetrokken [281:292] | J15: intrekking [3383:3393] | L15: ingetrokken | M15: intrekking | N15: Different value selected | O15: 0 | P15: 1 | Q15: 1 | R15: 0 | S15: ingetrokken | T15: intrekking | U15: 1 | V15: 0 | W15: 0 | X15: No | Y15: Needs review | AA15: =IF(X15="Yes","Excluded",IF(COUNTA(U15:W15)=0,"Auto",IF(COUNTA(U15:W15)=3,"Manual","INCOMPLETE"))) -> Manual | AB15: =IF(X15="Yes",0,IF(AA15="Manual",U15,O15)) -> 1 | AC15: =IF(X15="Yes",0,IF(AA15="Manual",V15,P15)) -> 0 | AD15: =IF(X15="Yes",0,IF(AA15="Manual",W15,Q15)) -> 0 | AE15: =IF(X15="Yes","",IF(AND(AC15=0,AD15=0),1,0)) -> 1 | AF15: [...] evestigd te Rotterdam verleende vergunning met nummer 2004/84197, Al/lO/BES, laatstelijk gewijzigd op 1 september 2005 met nummer 2005/63633 voor het verrichten van handelingen met radioactieve stoffen, wordt ambtshalve ingetrokken. ## II. Documenten Het op 31 maart 2016 ontvangen ambtsbericht van Inspectie SZW maakt deel uit van de intrekkingsbeschikking. ## III. Openbaarmaking en publicatie Deze intrekkingsbeschikking wordt ingevolge artikel 8 van de Wet openbaarheid van bestuur actief openbaar gemaakt door publicatie van deze beschikking op de internetsite www.anvs.nl. Van het intrekken van bovengenoemde vergunning wordt tevens mededeling gedaan in de Staatscourant. ## IV. Inwerkingtreding Dit besluit treedt conform artikel 20.5, eerste lid, Wet milieubeheer terstond in werking. <!-- image --> - &gt; Retouradres Postbus 16001 2500 BA Den Haag Datum 26 april 2016 Betreft Intrekking vergunning Kernenergiewet INTREKKING VAN EEN KERNENERGIEWETVERGUNNING VERLEEND AAN UNISCAN B.V. VOOR HET VERRICHTEN VAN HANDELINGEN MET RADIOACTIEVE STOFFEN Intrekking door: ## DE MINISTER VAN INFRASTRUCTUUR EN MILIEU. ## 1. Het besluit ## ANVS Stra Ii ngsbeschermi ng Aanvragen en r'lelden Bezuidenhoutseweg 67 Postbus 16001 2500 BA Den Haag www.anvs.nI - T 070-3487366 - E Postbus.Aanvragenenmelden @anvsnI Onze referentie 2016/0403-04 Bijlage(n) ## 2.1. De aanvraag Op 31 maart 2016 heb ik een brief met kenmerk A1207/82/02 ontvangen van de Inspectie SZW met betrekking op de op 17 december 2004 aan Uniscan B.V., gevestigd te Rotterdam verleende vergunning met nummer 2004/84197, Al/TO/BES, laatstelijk gewijzigd op 1 september 2005 met nummer 2005/63633. In de brief wordt gemeld dat bij een inspectie is gebleken dat de firma Uniscan B.V. niet meer bestaat. De activiteiten van Uniscan B.V. zijn in 2008 overgenomen door Teco Maritime Benelux te Spijkenisse. Hiervan is geen melding gedaan bij de overheid. Dit bedrijf heeft de betreffende bron in 2009 door de RTD af laten voeren. Ook toen heeft het betrokken bedrijf verzuimd hiervan melding te doen bij de overheid en de vergunning in te laten trekken. Bij de aanvraag zijn de volgende documenten toegevoegd: - -Mailcorrespondentie tussen Applus-RTD en Inspectie SZW. - -Overdrachtbewijs Cobalt-60 bron met referentienummer: BSH 106/04/RB/rb. - -Statusdocument Applus-RTD d.d.16 juni 2005 met opslagnummer 4039. - -Brief van Applus-RTD gericht aan Teco Maritime Benelux d.d. 26 februari 2009 met referentienummer CSH1815.09/BH/bh. - -Statusdocument Applus-RTD d.d. 18 oktober 2010 met opslagnummer 6669. ## 2.2. Gevolgde procedure De vergunning betreft handelingen met radioactieve stoffen op steeds wisselende plaatsen in geheel Nederland ten behoeve van meting van het CO 2 -niveau van gasflessen aan boord van zeeschepen. Het betreft één(1) ingekapselde bron cobalt-60 met een activiteit van maximaal 18,5 megabecquerel (MBq). De vergunde onderhavige radioactieve stoffen zijn definitief afgevoerd en van de vergunning zal geen gebruik meer worden gemaakt. Het ontdoen is geschied overeenkomstig het gestelde in artikel 37, vijfde, zevende en achtste lid, van het Besluit stralingsbescherming. ## 2.3. Besluit Op grond van bovenstaande heb ik besloten tot intrekking van de vergunning over te gaan. <!-- image --> ## 2. De aanvraag en de beoordeling Den Haag, De Minister van Infrastructuur en Milieu, namens deze: ir. M.J. Korse -Noordhoek MTD wnd. sectorhoofd directie [...]
A16: ANVS__PUC_5825_32_1.txt::Rechtshandeling | B16: ANVS__PUC_5825_32_1.txt | C16: ANVS | D16: Rechtshandeling | E16: verleend | F16: verleend | intrekking | G16: verleend | H16: intrekking | verleend | I16: verleend [1102:1111] | J16: verleend [1102:1110] || intrekking [606:616] || intrekking [774:784] | K16: verleend | M16: intrekking | N16: Partially overlapping value sets | O16: 1 | P16: 0 | Q16: 1 | R16: 0 | S16: verleend | T16: verleend | intrekking | U16: 1 | V16: 0 | W16: 0 | X16: No | Y16: Needs review | AA16: =IF(X16="Yes","Excluded",IF(COUNTA(U16:W16)=0,"Auto",IF(COUNTA(U16:W16)=3,"Manual","INCOMPLETE"))) -> Manual | AB16: =IF(X16="Yes",0,IF(AA16="Manual",U16,O16)) -> 1 | AC16: =IF(X16="Yes",0,IF(AA16="Manual",V16,P16)) -> 0 | AD16: =IF(X16="Yes",0,IF(AA16="Manual",W16,Q16)) -> 0 | AE16: =IF(X16="Yes","",IF(AND(AC16=0,AD16=0),1,0)) -> 1 | AF16: [...] ISERENDE STRALING UITZENDENDE TOESTELLEN ## Verleend door: DE MINISTER VAN INFRASTRUCTUUR EN MILIEU. ## 1. Het besluit ## 1. Vergunning Aan Stichting Alrijne Zorggroep gevestigd te Leiderdorp wordt, onder intrekking van de op 16 september 2003 verleende vergunning met nummer 2003/383383 AI/UJB/BES, laatstelijk gewijzigd op 1 april 2015, met nummer 2015/0036-07, en onder intrekking van de op 8 mei 2002 verleende vergunning met nummer 2002/11252 AI/CK/B/KEW, laatstelijk gewijzigd op 25 februari 2015, met nummer 2015/0112-04, krachtens de artikelen 29 en 34 van de Kernenergiewet en de artikelen 23, 24 en 25 van het Besluit stralingsbescherming voor onbepaalde tijd conform de aanvraag vergunning verleend voor: ## A. RADIOACTIEVE STOFFEN ## Locatie Leiderdorp Het verrichten van handelingen ten behoeve van medische diagnostiek en therapie, uk- en referentiedoeleinden en medisch wetenschappelijk onderzoek binnen de [...]
A17: Autoriteit_Persoonsgegevens__https___www.autoriteitpersoonsgegevens.nl_system_files_file=2025-10_Besluit%20bulkvergunningaanvraag%20CWV%20Centrum%20Hoensbroek.txt::Besluitvormend Orgaan | B17: Autoriteit_Persoonsgegevens__https___www.autoriteitpersoonsgegevens.nl_system_files_file=2025-10_Besluit%20bulkvergunningaanvraag%20CWV%20Centrum%20Hoensbroek.txt | C17: AP | D17: Besluitvormend Orgaan | F17: Autoriteit Persoonsgegevens | G17: <NONE> | H17: autoriteit persoonsgegevens | J17: Autoriteit Persoonsgegevens [15630:15657] | M17: autoriteit persoonsgegevens | N17: One annotator omitted feature | O17: 0 | P17: 0 | Q17: 1 | R17: 0 | T17: Autoriteit Persoonsgegevens | X17: No | Y17: Needs review | AA17: =IF(X17="Yes","Excluded",IF(COUNTA(U17:W17)=0,"Auto",IF(COUNTA(U17:W17)=3,"Manual","INCOMPLETE"))) -> Auto | AB17: =IF(X17="Yes",0,IF(AA17="Manual",U17,O17)) -> 0 | AC17: =IF(X17="Yes",0,IF(AA17="Manual",V17,P17)) -> 0 | AD17: =IF(X17="Yes",0,IF(AA17="Manual",W17,Q17)) -> 1 | AE17: =IF(X17="Yes","",IF(AND(AC17=0,AD17=0),1,0)) -> 0 | AF17: [...] chrift indienen, zie www.autoriteitpersoonsgegevens.nl. onder het kopje 'Bezwaar maken tegen een besluit'. Het indienen van een bezwaarschrift schort de werking van dit besluit niet op. Den Haag, 11 september 2025 Autoriteit Persoonsgegevens, Overeenkomstig het door de Autoriteit Persoonsgegevens genomen besluit, ir. N.G. de Jong Directeur Systeemtoezicht, Beveiliging en Technologie <!-- image --> ## Datum 11 september 2025 ## Ons kenme [...]
A18: Autoriteit_Persoonsgegevens__https___www.autoriteitpersoonsgegevens.nl_system_files_file=2025-01_Besluit%20vergunning%20collectief%20winkelverbod%20Rotterdam%20Zuidplein.txt::Ontvanger | B18: Autoriteit_Persoonsgegevens__https___www.autoriteitpersoonsgegevens.nl_system_files_file=2025-01_Besluit%20vergunning%20collectief%20winkelverbod%20Rotterdam%20Zuidplein.txt | C18: AP | D18: Ontvanger | E18: Centrum voor Criminaliteitspreventie en Veiligheid | F18: het Centrum voor Criminaliteitspreventie en Veiligheid | G18: centrum voor criminaliteitspreventie en veiligheid | H18: het centrum voor criminaliteitspreventie en veiligheid | I18: Centrum voor Criminaliteitspreventie en Veiligheid [419:469] | J18: het Centrum voor Criminaliteitspreventie en Veiligheid [415:469] | L18: centrum voor criminaliteitspreventie en veiligheid | M18: het centrum voor criminaliteitspreventie en veiligheid | N18: Minor boundary/extent difference | O18: 0 | P18: 1 | Q18: 1 | R18: 0 | S18: Centrum voor Criminaliteitspreventie en Veiligheid | T18: het Centrum voor Criminaliteitspreventie en Veiligheid | U18: 1 | V18: 0 | W18: 0 | X18: No | Y18: Needs review | AA18: =IF(X18="Yes","Excluded",IF(COUNTA(U18:W18)=0,"Auto",IF(COUNTA(U18:W18)=3,"Manual","INCOMPLETE"))) -> Manual | AB18: =IF(X18="Yes",0,IF(AA18="Manual",U18,O18)) -> 1 | AC18: =IF(X18="Yes",0,IF(AA18="Manual",V18,P18)) -> 0 | AD18: =IF(X18="Yes",0,IF(AA18="Manual",W18,Q18)) -> 0 | AE18: =IF(X18="Yes","",IF(AND(AC18=0,AD18=0),1,0)) -> 1 | AF18: [...] an de verwerking 'Collectief Winkelverbod' door de in de bijlage genoemde winkeliers van het winkelgebied Zuidplein Rotterdam - 2024-030739 ## 1 Inleiding: aanleiding vergunningaanvraag 1. Op 23 oktober 2024 heeft het Centrum voor Criminaliteitspreventie en Veiligheid (hierna: het CCV) ingevolge artikel 33, vierde lid, aanhef en onder c, van de Uitvoeringswet Algemene verordening gegevensbescherming (UAVG) - bij de Autoriteit Persoonsgegevens (AP) een bulkvergunningaanvraag ingediend [...]
A19: Autoriteit_Persoonsgegevens__https___www.autoriteitpersoonsgegevens.nl_system_files_file=2025-01_Besluit%20vergunning%20collectief%20winkelverbod%20Winterswijk.txt::Ontvanger | B19: Autoriteit_Persoonsgegevens__https___www.autoriteitpersoonsgegevens.nl_system_files_file=2025-01_Besluit%20vergunning%20collectief%20winkelverbod%20Winterswijk.txt | C19: AP | D19: Ontvanger | E19: Centrum voor Criminaliteitspreventie en Veiligheid | F19: het Centrum voor Criminaliteitspreventie en Veiligheid | G19: centrum voor criminaliteitspreventie en veiligheid | H19: het centrum voor criminaliteitspreventie en veiligheid | I19: Centrum voor Criminaliteitspreventie en Veiligheid [392:442] | J19: het Centrum voor Criminaliteitspreventie en Veiligheid [388:442] | L19: centrum voor criminaliteitspreventie en veiligheid | M19: het centrum voor criminaliteitspreventie en veiligheid | N19: Minor boundary/extent difference | O19: 0 | P19: 1 | Q19: 1 | R19: 0 | S19: Centrum voor Criminaliteitspreventie en Veiligheid | T19: het Centrum voor Criminaliteitspreventie en Veiligheid | U19: 1 | V19: 0 | W19: 0 | X19: No | Y19: Needs review | AA19: =IF(X19="Yes","Excluded",IF(COUNTA(U19:W19)=0,"Auto",IF(COUNTA(U19:W19)=3,"Manual","INCOMPLETE"))) -> Manual | AB19: =IF(X19="Yes",0,IF(AA19="Manual",U19,O19)) -> 1 | AC19: =IF(X19="Yes",0,IF(AA19="Manual",V19,P19)) -> 0 | AD19: =IF(X19="Yes",0,IF(AA19="Manual",W19,Q19)) -> 0 | AE19: =IF(X19="Yes","",IF(AND(AC19=0,AD19=0),1,0)) -> 1 | AF19: [...] n de verwerking 'Collectief Winkelverbod' door de in de bijlage genoemde winkeliers van het winkelgebied (Centrum Winterswijk) (2024-028600) ## 1 Inleiding: aanleiding vergunningaanvraag 1. Op 2 oktober 2024 heeft het Centrum voor Criminaliteitspreventie en Veiligheid (hierna: het CCV) ingevolge artikel 33, vierde lid, aanhef en onder c, van de Uitvoeringswet Algemene verordening gegevensbescherming (UAVG) - bij de Autoriteit Persoonsgegevens (AP) een bulkvergunningaanvraag ingediend [...]
A20: Autoriteit_Persoonsgegevens__https___www.autoriteitpersoonsgegevens.nl_system_files_file=2025-03_Besluit%20vergunning%20collectief%20winkelverbod%20Schijndel.txt::Ontvanger | B20: Autoriteit_Persoonsgegevens__https___www.autoriteitpersoonsgegevens.nl_system_files_file=2025-03_Besluit%20vergunning%20collectief%20winkelverbod%20Schijndel.txt | C20: AP | D20: Ontvanger | E20: Centrum voor Criminaliteitspreventie en Veiligheid | F20: het Centrum voor Criminaliteitspreventie en Veiligheid | G20: centrum voor criminaliteitspreventie en veiligheid | H20: het centrum voor criminaliteitspreventie en veiligheid | I20: Centrum voor Criminaliteitspreventie en Veiligheid [389:439] | J20: het Centrum voor Criminaliteitspreventie en Veiligheid [385:439] | L20: centrum voor criminaliteitspreventie en veiligheid | M20: het centrum voor criminaliteitspreventie en veiligheid | N20: Minor boundary/extent difference | O20: 0 | P20: 1 | Q20: 1 | R20: 0 | S20: Centrum voor Criminaliteitspreventie en Veiligheid | T20: het Centrum voor Criminaliteitspreventie en Veiligheid | U20: 1 | V20: 0 | W20: 0 | X20: No | Y20: Needs review | AA20: =IF(X20="Yes","Excluded",IF(COUNTA(U20:W20)=0,"Auto",IF(COUNTA(U20:W20)=3,"Manual","INCOMPLETE"))) -> Manual | AB20: =IF(X20="Yes",0,IF(AA20="Manual",U20,O20)) -> 1 | AC20: =IF(X20="Yes",0,IF(AA20="Manual",V20,P20)) -> 0 | AD20: =IF(X20="Yes",0,IF(AA20="Manual",W20,Q20)) -> 0 | AE20: =IF(X20="Yes","",IF(AND(AC20=0,AD20=0),1,0)) -> 1 | AF20: [...] n van de verwerking 'Collectief Winkelverbod' door de in de bijlage genoemde winkeliers van het winkelgebied Centrum Schijndel 2024-037030 ## 1 Inleiding: aanleiding vergunningaanvraag 1. Op 24 december 2024 heeft het Centrum voor Criminaliteitspreventie en Veiligheid (hierna: het CCV) - ingevolge artikel 33, vierde lid, aanhef en onder c, van de Uitvoeringswet Algemene verordening gegevensbescherming (UAVG) - bij de Autoriteit Persoonsgegevens (AP) een bulkvergunningaanvraag ingedie [...]
A21: Autoriteit_Persoonsgegevens__https___www.autoriteitpersoonsgegevens.nl_system_files_file=2025-10_Besluit%20bulkvergunningaanvraag%20Binnenstad%20Tilburg.txt::Ontvanger | B21: Autoriteit_Persoonsgegevens__https___www.autoriteitpersoonsgegevens.nl_system_files_file=2025-10_Besluit%20bulkvergunningaanvraag%20Binnenstad%20Tilburg.txt | C21: AP | D21: Ontvanger | E21: Centrum voor Criminaliteitspreventie en Veiligheid | F21: het Centrum voor Criminaliteitspreventie en Veiligheid | G21: centrum voor criminaliteitspreventie en veiligheid | H21: het centrum voor criminaliteitspreventie en veiligheid | I21: Centrum voor Criminaliteitspreventie en Veiligheid [462:512] | J21: het Centrum voor Criminaliteitspreventie en Veiligheid [458:512] | L21: centrum voor criminaliteitspreventie en veiligheid | M21: het centrum voor criminaliteitspreventie en veiligheid | N21: Minor boundary/extent difference | O21: 0 | P21: 1 | Q21: 1 | R21: 0 | S21: Centrum voor Criminaliteitspreventie en Veiligheid | T21: het Centrum voor Criminaliteitspreventie en Veiligheid | U21: 1 | V21: 0 | W21: 0 | X21: No | Y21: Needs review | AA21: =IF(X21="Yes","Excluded",IF(COUNTA(U21:W21)=0,"Auto",IF(COUNTA(U21:W21)=3,"Manual","INCOMPLETE"))) -> Manual | AB21: =IF(X21="Yes",0,IF(AA21="Manual",U21,O21)) -> 1 | AC21: =IF(X21="Yes",0,IF(AA21="Manual",V21,P21)) -> 0 | AD21: =IF(X21="Yes",0,IF(AA21="Manual",W21,Q21)) -> 0 | AE21: =IF(X21="Yes","",IF(AND(AC21=0,AD21=0),1,0)) -> 1 | AF21: [...] Collectief Winkelverbod' door de in de bijlage genoemde winkeliers van het winkelgebied Binnenstad Tilburg- 2024011591/2025-002437/2025-022203 ## 1 Inleiding: aanleiding vergunningaanvraag 1. Op 10 juli 2025 heeft het Centrum voor Criminaliteitspreventie en Veiligheid (hierna: het CCV) ingevolge artikel 33, vierde lid, aanhef en onder c, van de Uitvoeringswet Algemene verordening gegevensbescherming (UAVG) - bij de Autoriteit Persoonsgegevens (AP) een bulkvergunningaanvraag ingediend [...]
A22: Autoriteit_Persoonsgegevens__https___www.autoriteitpersoonsgegevens.nl_system_files_file=2025-10_Besluit%20bulkvergunningaanvraag%20CWV%20Centrum%20Hoensbroek.txt::Ontvanger | B22: Autoriteit_Persoonsgegevens__https___www.autoriteitpersoonsgegevens.nl_system_files_file=2025-10_Besluit%20bulkvergunningaanvraag%20CWV%20Centrum%20Hoensbroek.txt | C22: AP | D22: Ontvanger | E22: Centrum voor Criminaliteitspreventie en Veiligheid | Autoriteit Persoonsgegevens | F22: het Centrum voor Criminaliteitspreventie en Veiligheid | G22: autoriteit persoonsgegevens | centrum voor criminaliteitspreventie en veiligheid | H22: het centrum voor criminaliteitspreventie en veiligheid | I22: Centrum voor Criminaliteitspreventie en Veiligheid [414:464] || Autoriteit Persoonsgegevens [15630:15657] | J22: het Centrum voor Criminaliteitspreventie en Veiligheid [410:464] | L22: autoriteit persoonsgegevens | centrum voor criminaliteitspreventie en veiligheid | M22: het centrum voor criminaliteitspreventie en veiligheid | N22: Minor boundary/extent difference | O22: 0 | P22: 2 | Q22: 1 | R22: 0 | S22: Centrum voor Criminaliteitspreventie en Veiligheid | Autoriteit Persoonsgegevens | T22: het Centrum voor Criminaliteitspreventie en Veiligheid | U22: 1 | V22: 0 | W22: 0 | X22: No | Y22: Needs review | AA22: =IF(X22="Yes","Excluded",IF(COUNTA(U22:W22)=0,"Auto",IF(COUNTA(U22:W22)=3,"Manual","INCOMPLETE"))) -> Manual | AB22: =IF(X22="Yes",0,IF(AA22="Manual",U22,O22)) -> 1 | AC22: =IF(X22="Yes",0,IF(AA22="Manual",V22,P22)) -> 0 | AD22: =IF(X22="Yes",0,IF(AA22="Manual",W22,Q22)) -> 0 | AE22: =IF(X22="Yes","",IF(AND(AC22=0,AD22=0),1,0)) -> 1 | AF22: [...] rden van de verwerking 'Collectief Winkelverbod' door de in de bijlage genoemde winkeliers van het winkelgebied Centrum Hoensbroek- 2025-022232 ## 1 Inleiding: aanleiding vergunningaanvraag 1. Op 3 juli 2025 heeft het Centrum voor Criminaliteitspreventie en Veiligheid (hierna: het CCV) ingevolge artikel 33, vierde lid, aanhef en onder c, van de Uitvoeringswet Algemene verordening gegevensbescherming (UAVG) - bij de Autoriteit Persoonsgegevens (AP) een bulkvergunningaanvraag ingediend namens de in de bijlage van het besluit genoemde winkeliers in winkelgebied Centrum Hoensbroek. Ter onderbouwing van de aanvraag, heeft het CCV een protocol en een gegevensbeschermingseffectbeoordeling (ook wel data protection impact assessment/DPIA genoemd) bijgevoegd. Deze aanvraag is bij de AP bekend onder het zaaknummer 2025-022232 en onder de zaaknaam ' Bulkvergunningaanvraag winkelgebied Centrum Hoensbroek'. ## Procesverloop - -Op 3 juli 2025 heeft de AP de bulkvergunningaanvraag voor 17 winkeliers inzake een Collectief Winkelverbod in winkelgebied Centrum Hoensbroek van het CCV ontvangen. - -Op 19 augustus 2025 heeft de AP geconstateerd dat de vergunningaanvraag incompleet was en de AP heeft op 19 augustus 2025 verzocht om de vergunningaanvraag aan te vullen. - -Vervolgens heeft het CCV op 3 september 2025 de ontbrekende informatie en documenten aangeleverd. 2. Op grond van artikel 33, vierde lid, aanhef en onder c, UAVG mogen persoonsgegevens van strafrechtelijke aard ten behoeve van derden worden verwerkt indien de AP een vergunning voor de verwerking heeft verleend. Ingevolge artikel 33, vijfde lid, UAVG kan een vergunning slechts worden verleend, indien de verwerking noodzakelijk is met het oog op een zwaarwegend belang van derden en bij de uitvoering is voorzien in zodanige waarborgen dat de persoonlijke levenssfeer van de betrokkene niet onevenredig wordt geschaad. Aan de vergunning kunnen door de AP voorschriften worden verbonden. 3. In het navolgende concludeert de AP dat er een bulkvergunning voor de verwerking van gegevens van strafrechtelijke aard ten behoeve van derden kan worden verleend aan de individuele winkeliers, genoemd in de bijlage, omdat voldoende is aangetoond dat de verwerking noodzakelijk is met het oog op een zwaarwegend belang van derden en bij de uitvoering is voorzien in zodanige waarborgen dat de persoonlijke levenssfeer van de betrokkene niet onevenredig wordt geschaad. Het vorenstaande is uitgewerkt in het aangeleverde protocol en de DPIA. <!-- image --> ## Datum 11 september 2025 ## 2 Procedureverloop 4. De AP heeft het Protocol (collectief) winkelverbod, versie april 2020 (hierna: modelprotocol collectief winkelverbod) en d e Data Protection Impact Assessment - Registratie en gebruik winkelverboden, versie april 2020 (hierna: model-DPIA collectief winkelverbod) beoordeeld. De AP is op basis van de hiervoor genoemde documenten en de nadere toelichting die daarop is gegeven door het CCV, tot de conclusie gekomen dat de AP in genoemde documenten geen strijdigheden ziet met de AVG en de UAVG. De AP heeft dit bevestigd in haar brief van 18 mei 2020, waarbij is aangegeven dat aan de nog af te geven vergunningen in elk geval een aantal specifieke aanvullende voorschriften worden verbonden (zie onder overwegingen 12, 13, 14, 15 en 16 van dit besluit). Na afstemming met het CCV (landelijk) heeft de AP per brief van 14 april 2022 aangegeven dat de geldigheidstermijn van het modelprotocol, model-DPIA collectief winkelverbod en alle bulkvergunningen loopt tot 31 maart 2027. 5. De lokale ondernemers hebben schriftelijk verklaard dat zij het modelprotocol collectief winkelverbod (april 2020) en model-DPIA collectief winkelverbod (april 2020) onderschrijven en zich daaraan zullen conformeren. Dit is de basis voor de aanvraag van de bulkvergunning, die de ondernemers elk nodig hebben voor de verwerking van persoonsgegevens van strafrechtelijke aard ten behoeve van derden. ## 3 Feitelijke weergave van de voorgenomen verwerking 6. Het doel van het winkelverbod is om de criminele derving, agressie en geweld tegen te gaan binnen de detailhandel. 7. In eerste instantie krijgt iemand na een strafbaar feit een collectieve waarschuwing voor een jaar. Gedurende dit jaar kunnen de winkels nog steeds worden bezocht. Wanneer betrokkene in deze periode nogmaals in de fout gaat, wordt gedurende één of twee jaar de toegang ontzegd tot alle deelnemende ondernemingen in het betreffende winkelgebied, dan wel (wanneer sprake is van een winkelgebied met één eigenaar) tot het winkelcentrum zelf. Andere winkelgebieden en winkels van niet-deelnemende ondernemingen blijven dus toegankelijk. Uiteraard kan ook nog steeds gebruik worden gemaakt van bezorgdiensten, zodat niemand de mogelijkheid wordt ontzegd om aan de eerste levensbehoeften te komen. 8. Een individueel winkelverbod is bedoeld om een overlastgever uit een specifieke winkel te weren. Deze verboden worden (alleen zichtbaar voor de betreffende winkel en de beheerder) wel in het systeem opgenomen. Hiermee wordt het mogelijk om, wanneer blijkt dat het iemand betreft die in meerdere winkels overlast veroorzaakt, het individueel verbod te wijzigen in een collectief verbod. 9. Een collectief winkelverbod (waar eventueel een waarschuwing aan voorafgaat) levert een belangrijke bijdrage aan het tegengaan van criminele derving, agressie en geweld binnen de detailhandel. Om een collectief winkelverbod te handhaven is samenwerking tussen winkelondernemers, waarbij personen die zich schuldig maken aan overlast en/of strafbare feiten in een systeem worden geregistreerd, noodzakelijk. ## 4 Wettelijk kader van strafrechtelijke aard ten behoeve van derden Artikel 10 AVG bepaalt: ' Persoonsgegevens betreffende strafrechtelijke veroordelingen en strafbare feiten of daarmee verband houdende veiligheidsmaatregelen mogen op grond van artikel 6, lid 1, alleen worden verwerkt onder toezicht van de overheid of indien de verwerking is toegestaan bij Unierechtelijke of lidstaatrechtelijke bepalingen die passende waarborgen voor de rechten en vrijheden van de betrokkenen bieden. Omvattende registers van strafrechtelijke veroordelingen mogen alleen worden bijgehouden onder toezicht van de overheid .' ## Ons kenmerk 2025-022232 <!-- image --> ## Datum 11 september 2025 ## Ons kenmerk 2025-022232 Artikel 1 UAVG bepaalt: ' In deze wet en de daarop berustende bepalingen wordt verstaan onder: ## […] Persoonsgegevens van strafrechtelijke aard: persoonsgegevens betreffende strafrechtelijke veroordelingen en strafbare feiten of daarmee verband houdende veiligheidsmaatregelen als bedoeld in artikel 10 van de verordening, alsmede persoonsgegevens betreffende een door de rechter opgelegd verbod naar aanleiding van onrechtmatig of hinderlijk gedrag; […]' Artikel 31 UAVG bepaalt: 'Onverminderd artikel 10 van de verordening mogen persoonsgegevens van strafrechtelijke aard alleen worden verwerkt voor zover dit krachtens de artikelen 32 en 33 is toegestaan.' Artikel 33, vierde lid, aanhef en onder c, UAVG bepaalt: 'Persoonsgegevens van strafrechtelijke aard mogen ten behoeve van derden worden verwerkt: ## […] c. indien de Autoriteit persoonsgegevens met inachtneming van het vijfde lid een vergunning voor de verwerking heeft verleend .' Artikel 33, vijfde lid, UAVG bepaalt: ' Een vergunning als bedoeld in het vierde lid, onderdeel c, kan slechts worden verleend, indien de verwerking noodzakelijk is met het oog op een zwaarwegend belang van derden en bij de uitvoering is voorzien in zodanige waarborgen dat de persoonlijke levenssfeer van de betrokkene niet onevenredig wordt geschaad. Aan de vergunning kunnen voorschriften worden verbonden.' Artikel 6, eerste lid, aanhef en onder f, AVG bepaalt: ' De verwerking is alleen rechtmatig indien en voor zover aan ten minste een van de onderstaande voorwaarden is voldaan: ## […] f) de verwerking is noodzakelijk voor de behartiging van de gerechtvaardigde belangen van de verwerkingsverantwoordelijke of van een derde, behalve wanneer de belangen of de grondrechten en de fundamentele vrijheden van de betrokkene die tot bescherming van persoonsgegevens nopen, zwaarder wegen dan die belangen, met name wanneer de betrokkene een kind is.' Overweging 47 van de AVG stelt: ' De gerechtvaardigde belangen van een verwerkingsverantwoordelijke, waaronder die van een verwerkingsverantwoordelijke aan wie de persoonsgegevens kunnen worden verstrekt, of van een derde, kan een rechtsgrond bieden voor verwerking, mits de belangen of de grondrechten en de fundamentele vrijheden van de betrokkene niet zwaarder wegen, rekening houdend met de redelijke verwachtingen van de betrokkene op basis van zijn verhouding met de verwerkingsverantwoordelijke. […] In elk geval is een zorgvuldige beoordeling geboden om te bepalen of sprake is van een gerechtvaardigd belang, alsook om te bepalen of een betrokkene op het tijdstip en in het kader van de verzameling van de persoonsgegevens redelijkerwijs mag verwachten dat verwerking met dat doel kan plaatsvinden. De belangen en de grondrechten van de betrokkene kunnen met name zwaarder wegen dan het belang van de verwerkingsverantwoordelijke wanneer persoonsgegevens worden verwerkt in omstandigheden waarin de betrokkenen redelijkerwijs geen verdere verwerking verwachten. […] De verwerking van persoonsgegevens die strikt noodzakelijk is voor fraudevoorkoming is ook een gerechtvaardigd belang van de verwerkingsverantwoordelijke in kwestie. […]' Artikel 5, tweede lid, AVG bepaalt: ' De verwerkingsverantwoordelijke is verantwoordelijk voor de naleving van lid 1 en kan deze aantonen ('verantwoordingsplicht').' 10. Het wettelijk kader betekent dat de AP zich in het kader van de beoordeling van een vergunningaanvraag heeft beperkt tot de beoordeling van de verwerking van persoonsgegevens van strafrechtelijke aard ten behoeve van derden. <!-- image --> ## Ons kenmerk 2025-022232 ## 5 Beoordeling voorgenomen verwerking 11. Aan de hand van het wettelijk kader is de voorgenomen verwerking beoordeeld. De beoordeling is gebaseerd op de aan de verwerking ten grondslag liggende vergunningaanvraag, het protocol en de DPIA. Daarnaast zijn de overwegingen 12, 13, 14, 15 en 16 van dit besluit van belang bij de verrichtte beoordeling. 12. Het conformeren aan het modelprotocol collectief winkelverbod en model-DPIA collectief winkelverbod (versie april 2020) leidt tot het op een AVG-conforme wijze bijhouden van enerzijds de opgelegde individuele winkelverboden (voor intern/eigen gebruik) en anderzijds het delen met derden van strafrechtelijke persoonsgegevens ten aanzien van opgelegde collectieve winkelverboden. In het modelprotocol en de model-DPIA wordt het beroep op de grondslag gerechtvaardigd belang (artikel 6, eerste lid, onder f, van de AVG) conform de Normuitleg grondslag 'gerechtvaardigd belang' (november 2019) in voldoende mate uiteengezet om de in artikel 5 van het protocol genoemde categorieën van gegevens legitiem te verwerken. 13. Daarnaast is ook nog vereist dat tussen de beheerder (ofwel: verwerker) en de lokale ondernemers (ofwel: de gezamenlijke verwerkingsverantwoordelijken) een verwerkersovereenkomst opgesteld wordt om te komen tot een legitieme gegevensverwerking tussen deze partijen. 14. Het vorenstaande laat onverlet dat de (lokale) ondernemers mogen zorgen voor extra waarborgen om deze persoonsgegevens te beschermen. 15. Daarnaast dienen voor het verkrijgen van een vergunning voor het voeren van en/of deelname aan de hiervoor genoemde registratie van personen aan wie een collectief winkelverbod is opgelegd, ook de aanvullende vergunningsvoorschriften (zie hieronder) in acht genomen te worden. 16. Zoals ook onder overweging 4 van dit besluit is aangegeven, zijn er aanvullende voorschriften verbonden aan deze vergunningen. De aanvullende voorschriften, zoals ook benoemd in de brief van de AP van 18 mei 2020 aan het CCV, zijn, dat: - a. de lokale ondernemers (gezamenlijke verwerkingsverantwoordelijken) jaarlijks - gecoördineerd door het CCV 1 - een evaluatie van het modelprotocol en model-DPIA 2 van het collectief winkelverbod dienen uit te voeren. De AP ontvangt op aanvraag een afschrift van deze evaluatie. - b. in aansluiting op voorschrift b de verwerkingsverantwoordelijke bij deze jaarlijkse evaluatie in elk geval expliciet zal ingaan op: 3.  (de omvang van) de deelnemerslijst (ofwel: de lijst waarin de lokale ondernemers zijn opgesomd, die deelnemen aan het collectief winkelverbod in dat bepaalde winkelgebied). 3 4.  het aantal opgelegde individuele en collectieve winkelverboden en collectieve waarschuwingen. 1 Hierdoor kan een uniforme werkwijze voor alle bij het CCV aangesloten winkeliersverenigingen worden gerealiseerd. 2 Dit is feitelijk inherent aan de cyclus van een DPIA, omdat een DPIA uitvoeren geen eenmalige opdracht is, maar een continu proces. De verwerkingsverantwoordelijke moet altijd blijven monitoren of diens gegevensverwerking verandert. Bijvoorbeeld als er een nieuwe technologie gebruikt wordt. Of als persoonsgegevens voor een ander doel worden gebruikt. 3 Deze deelnemerslijst wordt door het CCV via een website actueel gehouden, zodat kenbaar is welke winkeliers deelnemen aan het collectief verbod in een bepaald gebied. <!-- image --> ## Datum 11 september 2025 <!-- image --> -  het aantal (wegens verlopen van de looptijd of om andere redenen) verwijderde individuele en collectieve verboden en collectieve waarschuwingen. -  de meldingen van eventuele bijzondere incidenten waarbij de aard en de omvang daarvan wordt beschreven, of van andere vermeldingswaardige bijzonderheden. - c. de vergunning is - behoudens ingrijpende wetswijzigingen of wijzigingen van de gegevensverwerking - geldig tot 31 maart 2027. - d. de verwerkingsverantwoordelijke (lokale ondernemer) diens gegevens volledig conform het modelprotocol en model-DPIA zal verwerken. Dat wil zeggen dat de lokale ondernemer het modelprotocol en model-DPIA ongewijzigd overneemt en de gegevens van de opgelegde collectieve winkelverboden precies, zoals in het modelprotocol en model-DPIA omschreven wordt, gaat verwerken. ## 6 Conclusie 17. De AP is van oordeel dat de in de bijlage genoemde winkeliers - door zich te conformeren aan de reeds door de AP beoordeelde modelprotocol en model-DPIA (versie april 2020) - de noodzaak en proportionaliteit van de voorgenomen verwerking voldoende hebben aangetoond. 18. De AP wijst de aanvraag ter verlening van een vergunning voor de verwerking van persoonsgegevens van strafrechtelijke aard ten behoeve van derden toe. Er mag met de voorgenomen verwerking worden gestart. ## 7 Afsluiting en rechtsmiddel Indien u het niet eens bent met dit besluit kunt u binnen zes weken na de datum van verzending van het besluit ingevolge de Awb een bezwaarschrift indienen bij de Autoriteit Persoonsgegevens. U kunt een bezwaarschrift indienen per post door deze te zenden naar Postbus 93374, 2509 AJ Den Haag, onder vermelding van 'Awb-bezwaar' op de envelop. U kunt ook een digitaal bezwaarschrift indienen, zie www.autoriteitpersoonsgegevens.nl. onder het kopje 'Bezwaar maken tegen een besluit'. Het indienen van een bezwaarschrift schort de werking van dit besluit niet op. Den Haag, 11 september 2025 Autoriteit Persoonsgegevens, Overeenkomstig het door de Autoriteit Persoonsgegevens genomen besluit, ir. N.G. de Jong Directeur Systeemtoezicht, Beveiliging en Technologie <!-- image --> ## Datum 11 september 2025 ## Ons kenme [...]
A23: Autoriteit_Persoonsgegevens__https___www.autoriteitpersoonsgegevens.nl_system_files_file=2025-10_Besluit%20bulkvergunningaanvraag%20CWV%20Winkelcentrum%20Donderberg.txt::Ontvanger | B23: Autoriteit_Persoonsgegevens__https___www.autoriteitpersoonsgegevens.nl_system_files_file=2025-10_Besluit%20bulkvergunningaanvraag%20CWV%20Winkelcentrum%20Donderberg.txt | C23: AP | D23: Ontvanger | E23: Centrum voor Criminaliteitspreventie en Veiligheid | F23: het Centrum voor Criminaliteitspreventie en Veiligheid | G23: centrum voor criminaliteitspreventie en veiligheid | H23: het centrum voor criminaliteitspreventie en veiligheid | I23: Centrum voor Criminaliteitspreventie en Veiligheid [420:470] | J23: het Centrum voor Criminaliteitspreventie en Veiligheid [416:470] | L23: centrum voor criminaliteitspreventie en veiligheid | M23: het centrum voor criminaliteitspreventie en veiligheid | N23: Minor boundary/extent difference | O23: 0 | P23: 1 | Q23: 1 | R23: 0 | S23: Centrum voor Criminaliteitspreventie en Veiligheid | T23: het Centrum voor Criminaliteitspreventie en Veiligheid | U23: 1 | V23: 0 | W23: 0 | X23: No | Y23: Needs review | AA23: =IF(X23="Yes","Excluded",IF(COUNTA(U23:W23)=0,"Auto",IF(COUNTA(U23:W23)=3,"Manual","INCOMPLETE"))) -> Manual | AB23: =IF(X23="Yes",0,IF(AA23="Manual",U23,O23)) -> 1 | AC23: =IF(X23="Yes",0,IF(AA23="Manual",V23,P23)) -> 0 | AD23: =IF(X23="Yes",0,IF(AA23="Manual",W23,Q23)) -> 0 | AE23: =IF(X23="Yes","",IF(AND(AC23=0,AD23=0),1,0)) -> 1 | AF23: [...] n de verwerking 'Collectief Winkelverbod' door de in de bijlage genoemde winkeliers van het winkelgebied Winkelcentrum Donderberg 2025-012716 ## 1 Inleiding: aanleiding vergunningaanvraag 1. Op 24 april 2025 heeft het Centrum voor Criminaliteitspreventie en Veiligheid (hierna: het CCV) ingevolge artikel 33, vierde lid, aanhef en onder c, van de Uitvoeringswet Algemene verordening gegevensbescherming (UAVG) - bij de Autoriteit Persoonsgegevens (AP) een bulkvergunningaanvraag ingediend [...]
A24: Autoriteit_Persoonsgegevens__https___www.autoriteitpersoonsgegevens.nl_uploads_2023-09_Besluit%20vergunning%20collectief%20winkelverbod%20Breda.txt::Ontvanger | B24: Autoriteit_Persoonsgegevens__https___www.autoriteitpersoonsgegevens.nl_uploads_2023-09_Besluit%20vergunning%20collectief%20winkelverbod%20Breda.txt | C24: AP | D24: Ontvanger | E24: Centrum voor Criminaliteitspreventie en Veiligheid | F24: het Centrum voor Criminaliteitspreventie en Veiligheid | G24: centrum voor criminaliteitspreventie en veiligheid | H24: het centrum voor criminaliteitspreventie en veiligheid | I24: Centrum voor Criminaliteitspreventie en Veiligheid [420:470] | J24: het Centrum voor Criminaliteitspreventie en Veiligheid [416:470] | L24: centrum voor criminaliteitspreventie en veiligheid | M24: het centrum voor criminaliteitspreventie en veiligheid | N24: Minor boundary/extent difference | O24: 0 | P24: 1 | Q24: 1 | R24: 0 | S24: Centrum voor Criminaliteitspreventie en Veiligheid | T24: het Centrum voor Criminaliteitspreventie en Veiligheid | U24: 1 | V24: 0 | W24: 0 | X24: No | Y24: Needs review | AA24: =IF(X24="Yes","Excluded",IF(COUNTA(U24:W24)=0,"Auto",IF(COUNTA(U24:W24)=3,"Manual","INCOMPLETE"))) -> Manual | AB24: =IF(X24="Yes",0,IF(AA24="Manual",U24,O24)) -> 1 | AC24: =IF(X24="Yes",0,IF(AA24="Manual",V24,P24)) -> 0 | AD24: =IF(X24="Yes",0,IF(AA24="Manual",W24,Q24)) -> 0 | AE24: =IF(X24="Yes","",IF(AND(AC24=0,AD24=0),1,0)) -> 1 | AF24: [...] van de verwerking 'Collectief Winkelverbod' door de in de bijlage genoemde winkeliers van het winkelgebied Breda Binnenstad - z2023-02774 ## 1 Inleiding: aanleiding vergunningaanvraag 1. Op 16 februari 2023 heeft het Centrum voor Criminaliteitspreventie en Veiligheid (hierna: het CCV) - ingevolge artikel 33, vierde lid, aanhef en onder c, van de Uitvoeringswet Algemene verordening gegevensbescherming (UAVG) - bij de Autoriteit Persoonsgegevens (AP) een bulkvergunningaanvraag ingedie [...]
A25: Autoriteit_Persoonsgegevens__https___www.autoriteitpersoonsgegevens.nl_uploads_imported_besluit_vergunning_collectief_winkelverbod_de_gaard_utrecht.txt::Ontvanger | B25: Autoriteit_Persoonsgegevens__https___www.autoriteitpersoonsgegevens.nl_uploads_imported_besluit_vergunning_collectief_winkelverbod_de_gaard_utrecht.txt | C25: AP | D25: Ontvanger | E25: Centrum voor Criminaliteitspreventie en Veiligheid | F25: het Centrum voor Criminaliteitspreventie en Veiligheid | G25: centrum voor criminaliteitspreventie en veiligheid | H25: het centrum voor criminaliteitspreventie en veiligheid | I25: Centrum voor Criminaliteitspreventie en Veiligheid [414:464] | J25: het Centrum voor Criminaliteitspreventie en Veiligheid [410:464] | L25: centrum voor criminaliteitspreventie en veiligheid | M25: het centrum voor criminaliteitspreventie en veiligheid | N25: Minor boundary/extent difference | O25: 0 | P25: 1 | Q25: 1 | R25: 0 | S25: Centrum voor Criminaliteitspreventie en Veiligheid | T25: het Centrum voor Criminaliteitspreventie en Veiligheid | U25: 1 | V25: 0 | W25: 0 | X25: No | Y25: Needs review | AA25: =IF(X25="Yes","Excluded",IF(COUNTA(U25:W25)=0,"Auto",IF(COUNTA(U25:W25)=3,"Manual","INCOMPLETE"))) -> Manual | AB25: =IF(X25="Yes",0,IF(AA25="Manual",U25,O25)) -> 1 | AC25: =IF(X25="Yes",0,IF(AA25="Manual",V25,P25)) -> 0 | AD25: =IF(X25="Yes",0,IF(AA25="Manual",W25,Q25)) -> 0 | AE25: =IF(X25="Yes","",IF(AND(AC25=0,AD25=0),1,0)) -> 1 | AF25: [...] en van de verwerking 'Collectief Winkelverbod' door de in de bijlage genoemde winkeliers van het winkelgebied De Gaard Utrecht z2021-17385 ## 1 Inleiding: aanleiding vergunningaanvraag 1. Op 29 november 2021 heeft het Centrum voor Criminaliteitspreventie en Veiligheid (hierna: het CCV) ingevolge artikel 33, vierde lid, aanhef en onder c, van de Uitvoeringswet Algemene verordening gegevensbescherming (UAVG) - bij de Autoriteit Persoonsgegevens (AP) een bulkvergunningaanvraag ingediend [...]
A26: Autoriteit_Persoonsgegevens__https___www.autoriteitpersoonsgegevens.nl_uploads_imported_besluit_vergunning_collectief_winkelverbod_elzas_passage.txt::Ontvanger | B26: Autoriteit_Persoonsgegevens__https___www.autoriteitpersoonsgegevens.nl_uploads_imported_besluit_vergunning_collectief_winkelverbod_elzas_passage.txt | C26: AP | D26: Ontvanger | E26: Centrum voor Criminaliteitspreventie en Veiligheid | F26: het Centrum voor Criminaliteitspreventie en Veiligheid | G26: centrum voor criminaliteitspreventie en veiligheid | H26: het centrum voor criminaliteitspreventie en veiligheid | I26: Centrum voor Criminaliteitspreventie en Veiligheid [405:455] | J26: het Centrum voor Criminaliteitspreventie en Veiligheid [401:455] | L26: centrum voor criminaliteitspreventie en veiligheid | M26: het centrum voor criminaliteitspreventie en veiligheid | N26: Minor boundary/extent difference | O26: 0 | P26: 1 | Q26: 1 | R26: 0 | S26: Centrum voor Criminaliteitspreventie en Veiligheid | T26: het Centrum voor Criminaliteitspreventie en Veiligheid | U26: 1 | V26: 0 | W26: 0 | X26: No | Y26: Needs review | AA26: =IF(X26="Yes","Excluded",IF(COUNTA(U26:W26)=0,"Auto",IF(COUNTA(U26:W26)=3,"Manual","INCOMPLETE"))) -> Manual | AB26: =IF(X26="Yes",0,IF(AA26="Manual",U26,O26)) -> 1 | AC26: =IF(X26="Yes",0,IF(AA26="Manual",V26,P26)) -> 0 | AD26: =IF(X26="Yes",0,IF(AA26="Manual",W26,Q26)) -> 0 | AE26: =IF(X26="Yes","",IF(AND(AC26=0,AD26=0),1,0)) -> 1 | AF26: [...] derden van de verwerking 'Collectief Winkelverbod' door de in de bijlage genoemde winkeliers van het winkelgebied Elzas Passage - z2022-03808 ## 1 Inleiding: aanleiding vergunningaanvraag 1. Op 20 juni 2022 heeft het Centrum voor Criminaliteitspreventie en Veiligheid (hierna: het CCV) ingevolge artikel 33, vierde lid, aanhef en onder c, van de Uitvoeringswet Algemene verordening gegevensbescherming (UAVG) - bij de Autoriteit Persoonsgegevens (AP) een bulkvergunningaanvraag ingediend [...]
A27: Autoriteit_Persoonsgegevens__https___www.autoriteitpersoonsgegevens.nl_uploads_imported_boete_transavia.txt::Rechtshandeling | B27: Autoriteit_Persoonsgegevens__https___www.autoriteitpersoonsgegevens.nl_uploads_imported_boete_transavia.txt | C27: AP | D27: Rechtshandeling | E27: legt | F27: op te leggen | G27: legt | H27: op te leggen | I27: legt [61244:61249] | J27: op te leggen [429:441] | L27: legt | M27: op te leggen | N27: Different value selected | O27: 0 | P27: 1 | Q27: 1 | R27: 0 | S27: legt | T27: op te leggen | U27: 1 | V27: 0 | W27: 0 | X27: No | Y27: Needs review | AA27: =IF(X27="Yes","Excluded",IF(COUNTA(U27:W27)=0,"Auto",IF(COUNTA(U27:W27)=3,"Manual","INCOMPLETE"))) -> Manual | AB27: =IF(X27="Yes",0,IF(AA27="Manual",U27,O27)) -> 1 | AC27: =IF(X27="Yes",0,IF(AA27="Manual",V27,P27)) -> 0 | AD27: =IF(X27="Yes",0,IF(AA27="Manual",W27,Q27)) -> 0 | AE27: =IF(X27="Yes","",IF(AND(AC27=0,AD27=0),1,0)) -> 1 | AF27: [...] ROUWELIJK] ## Onderwerp Besluit tot het opleggen van een boete ## Geachte heer, mevrouw, De Autoriteit Persoonsgegevens (AP) heeft besloten om aan Transavia Airlines C.V. een bestuurlijke boete van € 400.000 op te leggen. De AP komt is tot de conclusie gekomen dat Transavia geen passende maatregelen getroffen heeft om een op het risico afgestemd beveiligingsniveau te waarborgen. Hierdoor heeft Transavia in strijd gehandeld met artikel 32, eerste en tweede lid, van de Algemene verordening gegevensbescherming. De AP licht het besluit hierna nader toe. Hoofdstuk 1 betreft een inleiding en hoofdstuk 2 bevat de feiten. De AP beoordeelt in hoofdstuk 3 of er sprake is van verwerking van persoonsgegevens, de verwerkingsverantwoordelijkheid en de overtreding. In hoofdstuk 4 wordt de (hoogte van de) bestuurlijke boete uitgewerkt en hoofdstuk 5 bevat het dictum en de rechtsmiddelenclausule. ## Autoriteit Persoonsgegevens Postbus 93374, 2509 AJ Den Haag Bezuidenhoutseweg 30, 2594 AV Den Haag T 070 8888 500 - F 070 8888 501 autoriteitpersoonsgegevens.nl <!-- image --> ## Datum 23 september 2021 Ons kenmerk [VERTROUWELIJK] ## 1. Inleiding ## 1.1 Betrokken organisatie Dit besluit heeft betrekking op Transavia Airlines C.V. (hierna: Transavia), gevestigd aan de Piet Guilonardweg 15, 1117 EE te Schiphol. Het bedrijf staat ingeschreven in het handelsregister onder nummer: 34069081. 1 Als luchtvaarmaatschappij verzorgt Transavia vluchten voor zakelijke reizigers en consumenten binnen Europa. Op 24 oktober 2019 heeft de AP een melding ontvangen van Transavia over een inbreuk op de beveiliging van persoonsgegevens als bedoeld in artikel 33 van de AVG. In deze melding is door Transavia aangegeven dat een kwaadwillende derde partij ongeautoriseerd toegang heeft gehad tot systemen van Transavia. Naar aanleiding hiervan heeft de AP ambtshalve onderzocht of de technische maatregelen bij Transavia met betrekking tot de toegang tot persoonsgegevens passend waren als bedoeld in artikel 5, lid 1, sub f jo. artikel 32 van de AVG. Specifiek richtte dit onderzoek zich op de toegang tot bepaalde gebruikers-accounts bij Transavia, alsmede de rechten en mogelijkheden die deze gebruikers-accounts hadden binnen de systemen van Transavia. ## 1.2 Procesverloop Op 28 november 2019 heeft de AP telefonisch contact opgenomen met Transavia over de datalekmelding van 24 oktober 2019 en de daarop volgende meldingen. Toezichthouders van de AP hebben vervolgens meermaals informatie opgevraagd bij Transavia waarop Transavia deze informatie heeft geleverd. Bij brief van 12 mei 2021 heeft de AP aan Transavia een voornemen tot handhaving verzonden en het daaraan ten grondslag gelegde rapport met bevindingen. Transavia heeft op 28 juni 2021 hierop schriftelijk een zienswijze gegeven. 1 Zie Dossierstuk 26, Inschrijving Handelsregister Transavia Airlines C.V. <!-- image --> Datum 23 september 2021 Ons kenmerk [VERTROUWELIJK] ## 2. Feiten ## 2.1 De inbreuk bij Transavia In de datalekmelding van 24 oktober 2019 heeft Transavia aangegeven dat een kwaadwillende derde partij (hierna ook: 'aanvaller') ongeautoriseerd toegang heeft gehad tot systemen van Transavia. 2 Transavia is volgens de melding hier op 21 oktober 2019 achter gekomen. Transavia heeft vervolgens een externe dienstverlener ingeschakeld en samen met deze dienstverlener is de aanvaller van de systemen van Transavia geweerd. Verder heeft de externe dienstverlener geanalyseerd welke systemen getroffen waren en welke gegevens betrokken waren. In het rapport opgesteld door de externe dienstverlener (hierna ook: 'forensisch rapport') is beschreven dat een aanvaller gebruik heeft gemaakt van [VERTROUWELIJK] e-mailadressen. Deze adressen zijn mogelijk te vinden op het internet. 3 De aanvaller probeerde toegang te verkrijgen tot de [VERTROUWELIJK] 4 De aanvaller heeft gebruik gemaakt van een ' password spray ' of ' credential stuffing ' aanval. Met een " password spray ' aanval gebruikt een aanvaller veel gebruikte wachtwoorden om op een geautomatiseerde manier ongeautoriseerde toegang te krijgen. Bij ' credential stuffing' aanval gebruikt een aanvaller bekende gebruikersgegevens (afkomstig uit andere datalekken van derden) om te proberen toegang te krijgen tot een systeem. Op 12 september 2019 om 9:52 uur vond een succesvolle inlogpoging plaats door de aanvaller. De gebruikte gebruikersnaam was [VERTROUWELIJK] en het wachtwoord was [VERTROUWELIJK]. Met deze inlog kon de aanvaller gebruikmaken van de [VERTROUWELIJK] gebruiker. 5 Dit is een gebruiker die werd gebruikt voor [VERTROUWELIJK]. 6 Met de [VERTROUWELIJK] gebruiker was het mogelijk om toegang te krijgen tot een Citrix omgeving van Transavia. Citrix is software die het mogelijk maakt om te telewerken. Vervolgens was het mogelijk om mogelijke [VERTROUWELIJK]-gebruikers in het [VERTROUWELIJK] domein te achterhalen. 7 Het is de aanvaller vervolgens gelukt om de authenticatiegegevens te verkrijgen van de gebruiker [VERTROUWELIJK] door wederom het wachtwoord [VERTROUWELIJK] te gebruiken. Deze gebruiker 2 Transavia France S.A.S. (zustermaatschappij van Transavia) heeft afzonderlijk gemeld bij de Franse toezichthouder volgens de datalekmelding van 24 oktober 2019 omdat er ook persoonsgegevens zouden zijn betrokken waar Transavia France S.A.S verantwoordelijk voor is. Zie Dossierstuk 1, melding van 24 oktober 2019. 3 Zie Dossierstuk 11, rapport van 5 december 2019, pagina 21. 4 Active Directory Federation Services Webservice is software van Microsoft, die organisaties in staat stelt Single Sign On Services te bewerkstellingen in een organisatie. 5 Zie Dossierstuk 11, rapport van 5 december 2019, pagina 21. 6 Zie Dossierstuk 25, Antwoorden van Transavia, datum 26 mei 2020. 7 Zie Dossierstuk 11, rapport van 5 december 2019, pagina 21. Een netwerkdomein is een groep computers (systemen) binnen een computernetwerk met als doel de systemen gecentraliseerd te beheren. <!-- image --> Datum 23 september 2021 ## Ons kenmerk [VERTROUWELIJK] had volgens Transavia ' de hoogste privileges in het [VERTROUWELIJK]'. 8 In principe betekent dit dat de accounts [VERTROUWELIJK] en [VERTROUWELIJK] tezamen toegang verschaften tot een groot deel van het computernetwerk van Transavia. 9 De rol van het account was bedoeld om te dienen als koppeling tussen het HR systeem van Transavia en de Active Directory (om te bepalen welke medewerkers welke rechten tot systemen behoren te krijgen). 10 Active Directory is een dienst van Microsoft die (onder andere) wordt gebruikt om rechten van gebruikers te beheren. Vervolgens verkende de aanvaller de systemen van Transavia die onderdeel zijn van het domein. In deze verkenningsfase, is er (waarschijnlijk geautomatiseerd) ingelogd op [VERTROUWELIJK] systemen. 11 In totaal is er activiteit waargenomen betreffende [VERTROUWELIJK] systemen. De externe dienstverlener heeft op [VERTROUWELIJK] systemen vast kunnen stellen dat sprake is van gegevens die zijn gekopieerd. 12 De aanvaller had mogelijk interesse in toegang tot [VERTROUWELIJK]. Toegang hiertoe verkrijgen is echter niet gelukt. 13 Dit is ook bevestigd door Transavia. 14 De aanvaller heeft op tenminste [VERTROUWELIJK] systemen [VERTROUWELIJK] logbestanden verwijderd. 15 De aanvaller heeft verder gebruik gemaakt van [VERTROUWELIJK] software. Dit is penetratie test software die bedoeld is om kwetsbaarheden te vinden in een IT-landschap. De externe dienstverlener heeft op tenminste [VERTROUWELIJK] systemen hier aanwijzingen voor gevonden. Op 21 oktober 2019 is dit type aanval door de beheerder opgemerkt en heeft de beheerder onderzoek ingesteld. Na 21 oktober 2019 zijn ook geen activiteiten meer waargenomen van de aanvaller. 16 Op basis van deze signalering is door Transavia op 22 oktober 2019 een externe dienstverlener ingeschakeld (niet de beheerder). De externe dienstverlener heeft een forensische analyse uitgevoerd. Uit de analyse bleek dat het merendeel van de activiteiten van de aanvaller gericht waren op verkenningsactiviteiten. De volgende gegevens zijn echter wel gekopieerd: Netwerk documentatie, zakelijke en diverse andere documenten alsmede zes e-mailboxen. 17 Er zijn door Transavia [VERTROUWELIJK] systemen als kritiek bestempeld. Hier zat een systeem tussen voor de uitwisseling van gegevens met [VERTROUWELIJK]. Ook zaten hier [VERTROUWELIJK] bij en een [VERTROUWELIJK]. Op een van de kritieke systemen, het [VERTROUWELIJK], zijn bepaalde logbestanden verwijderd. Hierdoor was er op dit systeem minder bewijs over wat er gebeurd is met dit systeem. 18 8 Zie Dossierstuk 38, Antwoorden van Transavia datum 24 september 2020. 9 Zie Dossierstuk 11, rapport van 5 december 2019, pagina 21. 10 Zie Dossierstuk 25, Antwoorden van Transavia, datum 26 mei 2020. 11 Zie Dossierstuk 11, rapport van 5 december 2019, pagina 21. 12 Zie Dossierstuk 11, rapport van 5 december 2019, pagina 26. 13 Zie Dossierstuk 11, rapport van 5 december 2019, pagina 25. 14 Zie Dossierstuk 25, Antwoorden van Transavia, datum 26 mei 2020. 15 Zie Dossierstuk 11, rapport van 5 december 2019, pagina 23. 16 Zie Dossierstuk 11, rapport van 5 december 2019, pagina 25. 17 Zie Dossierstuk 11, rapport van 5 december 2019, pagina 4. 18 Zie Dossierstuk 11, rapport van 5 december 2019, pagina 17. <!-- image --> Datum 23 september 2021 ## Ons kenmerk [VERTROUWELIJK] Op 22 november 2019 heeft Transavia opdracht gegeven aan de externe dienstverlener om de mailboxen te onderzoeken die door de aanvaller in deze inbreuk zijn gekopieerd naar een externe locatie. Het doel van het onderzoek betrof de persoonsgegevens in zes mailboxen: vijf mailboxen van medewerkers en één van een oud-medewerker. In de mailboxen bleken 49 bestanden met persoonsgegevens aanwezig. 19 Deze mailboxen waren volgens Transavia (met name) in gebruik bij [VERTROUWELIJK] medewerkers. 20 Deze bestanden zijn vervolgens geanalyseerd en op basis hiervan is besloten een mededeling te doen aan 81.000 betrokkenen, zoals verplicht in artikel 34 van de AVG indien er mogelijk sprake is van een hoog risico. 21 Deze groep betrokkenen bestond uit werknemers van Transavia en klanten van Transavia. De medewerkers wiens mailboxen waren gekopieerd, waren reeds mondeling geïnformeerd volgens Transavia. 22 Transavia geeft aan dat sinds 25 november 2019 de aanvaller definitief geen toegang meer had tot het ITlandschap van Transavia. 23 Dit is ook bevestigd door de externe dienstverlener. 24 Samenvattend heeft een onbevoegde derde partij toegang gehad tot systemen van Transavia. Bij deze toegang was het mogelijk een gebruiker met veel rechten te gebruiken, waardoor de aanvaller veel mogelijkheden had binnen deze systemen. Hierdoor is er toegang geweest tot veel systemen en zijn er ook persoonsgegevens gekopieerd naar een externe locatie. ## 2.2 Soort persoonsgegevens Er zijn twee groepen te onderscheiden persoonsgegevens in deze inbreuk: (1) persoonsgegevens die de aanvaller heeft gekopieerd naar een externe locatie en (2) persoonsgegevens waar de aanvaller toegang tot had. ## 2.2.1 Persoonsgegevens die zijn gekopieerd naar een externe locatie De volgende persoonsgegevens die zich in de mailboxen bevonden zijn door de aanvaller gekopieerd (exclusief de bestandsnamen): 25 | [VERTROUWELIJK] | [VERTROUWELIJK] | [VERTROUWELIJK] | [VERTROUWELIJK] | |-------------------|-------------------|-------------------|-------------------| | [VERTROUWELIJK] | [VERTROUWELIJK] | [VERTROUWELIJK] | [VERTROUWELIJK] | <!-- image --> ## Datum 23 september 2021 ## Ons kenmerk [VERTROUWELIJK] | [VERTROUWELIJK] | [VERTROUWELIJK] | [VERTROUWELIJK] | [VERTROUWELIJK] | |-------------------|-------------------|-------------------|-------------------| | [VERTROUWELIJK] | [VERTROUWELIJK] | [VERTROUWELIJK] | [VERTROUWELIJK] | | [VERTROUWELIJK] | [VERTROUWELIJK] | [VERTROUWELIJK] | [VERTROUWELIJK] | | [VERTROUWELIJK] | [VERTROUWELIJK] | [VERTROUWELIJK] | [VERTROUWELIJK] | | [VERTROUWELIJK] | [VERTROUWELIJK] | [VERTROUWELIJK] | [VERTROUWELIJK] | | [VERTROUWELIJK] | [VERTROUWELIJK] | [VERTROUWELIJK] | [VERTROUWELIJK] | | [VERTROUWELIJK] | [VERTROUWELIJK] | [VERTROUWELIJK] | [VERTROUWELIJK] | | [VERTROUWELIJK] | [VERTROUWELIJK] | [VERTROUWELIJK] | [VERTROUWELIJK] | | [VERTROUWELIJK] | [VERTROUWELIJK] | [VERTROUWELIJK] | [VERTROUWELIJK] | | [VERTROUWELIJK] | [VERTROUWELIJK] | [VERTROUWELIJK] | [VERTROUWELIJK] | | [VERTROUWELIJK] | [VERTROUWELIJK] | [VERTROUWELIJK] | [VERTROUWELIJK] | | [VERTROUWELIJK] | [VERTROUWELIJK] | [VERTROUWELIJK] | [VERTROUWELIJK] | Uit de bovenstaande tabel blijkt dat zowel passagiers-, leveranciers- en (potentiele) werknemersgegevens zijn gekopieerd. Transavia heeft verklaard dat het hier circa 80.000 passagiers betreft. 26 Ook stonden in meerdere bestanden de persoonsgegevens van tot 3000 medewerkers en tot 200 leveranciers. 27 Van passagiers zijn betrokken: voor- en achternaam, geboortedatum, vluchtinformatie en SSR-code. Van één passagier is een adres en telefoonnummer betrokken. Van medewerkers gaat het om de volgende gegevens: voor- en achternaam, zakelijke e-mailadressen, adres, telefoonnummer. En van leveranciers zijn betrokken: zakelijke e-mailadressen, voor- en achternaam, adres, e-mailadres, telefoonnummer. 26 Zie Dossierstuk 25, Antwoorden van Transavia, datum 26 mei 2020. 27 Zie Dossierstuk 25, Antwoorden van Transavia, datum 26 mei 2020 - Bijlage 3: Toelichting bij bijlage 2. <!-- image --> Datum 23 september 2021 Ons kenmerk [VERTROUWELIJK] Ook blijken er tot 10 C.V.-bestanden van potentiele medewerkers betrokken. Hierin bevonden zich vooren achternaam, adres, e-mailadres, telefoonnummer en geboortedatum. In de melding aan de betrokken passagiers (80.000) die Transavia heeft verstuurd meldt Transavia de volgende betrokken gegevens: voornaam, achternaam, geboortedatum, vluchtgegevens, boekingsnummer en de bijgeboekte service zoals bagage, maar ook rolstoelgebruik. 28 Verder geeft Transavia aan dat de betrokken werknemers ook zijn geïnformeerd. 29 De bijgeboekte services werden beschreven als SSR-code. SSR-code staat voor ' Special Service Request ' code. Transavia gebruikt in hun boekingssysteem een reeks van 4 tekens voor additionele verzoeken, zoals een fiets als bagage. De SSR-code is dan ' BIKE '. 30 Deze codes zijn te vinden op het internet waardoor de betekenis bekend is, mocht dit niet al duidelijk zijn uit de code. 31 De AP heeft aan Transavia gevraagd welke SSR-codes Transavia gebruikt en in welke aantallen. De door Transavia gebruikte codes geven onder andere aan wanneer een rolstoel benodigd is, of dat een passagier bijvoorbeeld een elektrische rolstoel gebruikt. Codes voor dieetwensen gebruikt Transavia niet aangezien ze geen maaltijden verstrekken tijdens de vluchten. 32 In de bestanden die zijn gekopieerd naar een externe locatie kwamen codes die rolstoelgebruik indiceren 358 maal voor. Ook kwam een code die blindheid aangeeft vijfmaal voor. Doofheid kwam vier keer voor. 33 Volgens Transavia waren de passagiersgegevens verzameld in de periode van 21 tot en met 31 januari 2015. 34 De gegevens bevonden zich in een mailbox op ' managed devices van medewerkers '. 35 Dit zijn beheerde apparaten, veelal mobiele apparaten zoals telefoons of laptops. De medewerkers in kwestie waren [VERTROUWELIJK]. ## 2.2.2 Persoonsgegevens waar toegang toe mogelijk was Hieronder staat een overzicht van de systemen waar de gebruikers [VERTROUWELIJK] en [VERTROUWELIJK] tezamen toegang toe hadden. 36 De titel ' host ' betekent in dit geval de naam van het systeem. De kolom ' Gegevens vanaf ingezien /Geexfiltreerd ' geeft aan of er na het inloggen op het systeem nog andere acties zijn waargenomen. Indien er door Transavia ' nee' is weergegeven is er alleen ingelogd volgens Transavia. 37 28 Zie Dossierstuk 38, Antwoorden van Transavia datum 24 september 2020. 29 Zie Dossierstuk 12, Vervolgmelding van 18 februari 2020. 30 Zie Dossierstuk 38, Antwoorden van Transavia datum 24 september 2020. 31 Zie bijvoorbeeld: https://wheelchairtravel.org/air-travel/special-service-request-codes/, of https://guides.developer.iata.org/docs/en/list-of-service-ssrs. 32 Zie Dossierstuk 38, Antwoorden van Transavia datum 24 september 2020. 33 Dossierstuk 38, Antwoorden van Transavia datum 24 september 2020 - Bijlage 5: Overzicht aantallen SSR-codes. 34 Zie Dossierstuk 13, Persbericht Transavia. 35 Zie Dossierstuk 25, Antwoorden van Transavia, datum 26 mei 2020. 36 Dossierstuk 25, Antwoorden van Transavia, datum 26 mei 2020 - Bijlage 4: Host en Persoonsgegevens. 37 Zie Dossierstuk 25, Antwoorden van Transavia, datum 26 mei 2020. <!-- image --> ## Datum 23 september 2021 ## Ons kenmerk [VERTROUWELIJK] | [VERTROUWELIJK] | [VERTROUWELIJK] | [VERTROUWELIJK] | [VERTROUWELIJK] | [VERTROUWELIJK] | [VERTROUWELIJK] | |-------------------|-------------------|-------------------|-------------------|-------------------|-------------------| | [VERTROUWELIJK] | [VERTROUWELIJK] | [VERTROUWELIJK] | [VERTROUWELIJK] | [VERTROUWELIJK] | [VERTROUWELIJK] | | [VERTROUWELIJK] | [VERTROUWELIJK] | [VERTROUWELIJK] | [VERTROUWELIJK] | [VERTROUWELIJK] | [VERTROUWELIJK] | | [VERTROUWELIJK] | [VERTROUWELIJK] | [VERTROUWELIJK] . | [VERTROUWELIJK] | [VERTROUWELIJK] | [VERTROUWELIJK] | <!-- image --> ## Datum 23 september 2021 ## Ons kenmerk [VERTROUWELIJK] | [VERTROUWELIJK] | [VERTROUWELIJK] | [VERTROUWELIJK] | [VERTROUWELIJK] | [VERTROUWELIJK] | [VERTROUWELIJK] | |-------------------|-------------------|-------------------|-------------------|-------------------|-------------------| | [VERTROUWELIJK] | [VERTROUWELIJK] | [VERTROUWELIJK] | [VERTROUWELIJK] | [VERTROUWELIJK] | [VERTROUWELIJK] | | [VERTROUWELIJK] | [VERTROUWELIJK] | [VERTROUWELIJK] | [VERTROUWELIJK] | [VERTROUWELIJK] | [VERTROUWELIJK] | | [VERTROUWELIJK] | [VERTROUWELIJK] | [VERTROUWELIJK] | [VERTROUWELIJK] | [VERTROUWELIJK] | [VERTROUWELIJK] | |-------------------|-------------------|-------------------|-------------------|-------------------|-------------------| | [VERTROUWELIJK] | [VERTROUWELIJK] | [VERTROUWELIJK] | [VERTROUWELIJK] | [VERTROUWELIJK] | [VERTROUWELIJK] | | [VERTROUWELIJK] | [VERTROUWELIJK] | [VERTROUWELIJK] | [VERTROUWELIJK] | [VERTROUWELIJK] | [VERTROUWELIJK] | | [VERTROUWELIJK] | [VERTROUWELIJK] | [VERTROUWELIJK] | [VERTROUWELIJK] | [VERTROUWELIJK] | [VERTROUWELIJK] | <!-- image --> ## Datum 23 september 2021 ## Ons kenmerk [VERTROUWELIJK] Uit de bovenstaande tabellen blijkt dat van passagiers de volgende gegevens verwerkt worden: de voor- en achternaam, de geboortedatum, het geslacht, het e-mailadres en telefoonnummer, de vlucht- en boekingsgegevens en de (zakelijke) e-mailcorrespondentie. Van medewerkers zijn de voor- en achternaam, het geslacht, de geboortedatum, het werknemersnummer, het huisadres, het telefoonnummer, de kwalificaties/training, BSN, de aanwezigheidsadministratie en inloggegevens verwerkt. Verder staat genoemd in het overzicht dat op een systeem verslagen over veiligheidsincidenten aan boord bevonden. Hierin zijn ook mogelijk persoonsgegevens van medewerkers en passagiers betrokken. In totaal staan voor passagiers tot 25.000.000 betrokkenen genoemd in het aangeleverde overzicht. Voor medewerkers worden tot 3000 betrokkenen genoemd. Dit betekent dat de aanvaller persoonsgegevens heeft ingezien of had kunnen inzien van 25 miljoen mensen. De mate van activiteit van de aanvaller is door het de externe dienstverlener opgesplitst in de volgende categorieën: 38 -  [VERTROUWELIJK] -  [VERTROUWELIJK] -  [VERTROUWELIJK] -  [VERTROUWELIJK] -  [VERTROUWELIJK] -  [VERTROUWELIJK] Op alle genoemde systemen is er sprake van [VERTROUWELIJK]. 39 Op [VERTROUWELIJK] systemen is daadwerkelijk bewijs gevonden voor het kopiëren van persoonsgegevens. Systeem [VERTROUWELIJK] is als kritiek aangemerkt door Transavia vanwege de hoeveelheid persoonsgegevens. Op dit systeem was er zowel sprake van [VERTROUWELIJK]. Op het systeem [VERTROUWELIJK] was het bewijs voor de activiteiten van de aanvaller beperkter dan bij andere systemen, omdat er logbestanden ontbraken over de relevante periode van de inbreuk. 40 Verder is het systeem [VERTROUWELIJK] als kritiek aangemerkt vanwege de hoeveelheid persoonsgegevens op dit systeem. 41 Op dit systeem was er sprake van [VERTROUWELIJK]. In de melding aan de AP heeft Transavia aangegeven dat de betrokkenen afkomstig zijn uit meerdere landen, namelijk geheel Europa. De AP heeft Transavia verzocht een overzicht heeft uit welk land de betrokkenen komen. Hierop heeft Transavia geantwoord dat 90% van de klanten uit Nederland komt, gebaseerd op de Point of Sale. 42 Slechts een beperkt aantal persoonsgegevens van zustermaatschappij Transavia France S.A.S. waren op de systemen van Transavia Airlines C.V. aanwezig. 43 38 Zie Dossierstuk 11, rapport van 5 december 2019, pagina 19. 39 Zie Dossierstuk 11, rapport van 5 december 2019, pagina 32. 40 Zie Dossierstuk 11, rapport van 5 december 2019, pagina 17. 41 Zie Dossierstuk 11, rapport van 5 december 2019, pagina 4. 42 Zie Dossierstuk 25, Antwoorden van Transavia, datum 26 mei 2020. 43 Zie Dossierstuk 38, Antwoorden van Transavia datum 24 september 2020. <!-- image --> Datum 23 september 2021 Ons kenmerk [VERTROUWELIJK] De AP komt tot de conclusie dat Transavia ten tijde van de inbreuk persoonsgegevens verwerkte van ruim 25 miljoen personen. Hiervan zijn persoonsgegevens gelekt van tot 83.000 personen en gezondheidsgegevens van 367 personen. ## 2.3 Beveiliging ten tijde van de inbreuk ## 2.3.1 Toegang tot het [VERTROUWELIJK] domein In het wachtwoordbeleid van Transavia staat aangegeven welke eisen er gelden per gebruiker, per mogelijk risiconiveau. 44 In het wachtwoordbeleid van Transavia staan 3 niveaus vermeldt: -  ' Minimal baseline', het standaard niveau; -  'Medium Additions', additionele maatregelen voor gebruikers met meer bevoegdheden; -  'Medium and High additions', extra maatregelen voor bepaalde hoog risico gebruikers. De gebruikers die gebruikt zijn door de aanvaller hadden volgens Transavia de volgende niveaus: 45 -  [VERTROUWELIJK] had als niveau: minimal baseline -  [VERTROUWELIJK] had niveau: Medium and High security additions De externe dienstverlener heeft aangegeven dat de [VERTROUWELIJK] gebruikers ' contained the highest possible privileges '. Een gebruiker met minimal baseline heeft volgens het wachtwoordbeleid de volgende wachtwoordeisen: 46 -  [VERTROUWELIJK] -  [VERTROUWELIJK] -  [VERTROUWELIJK] -  [VERTROUWELIJK] -  [VERTROUWELIJK] Voor High security additions zijn de volgende aanvullende eisen van toepassing: 47 -  [VERTROUWELIJK] -  [VERTROUWELIJK] -  [VERTROUWELIJK] -  [VERTROUWELIJK] -  [VERTROUWELIJK] -  [VERTROUWELIJK] -  [VERTROUWELIJK] -  [VERTROUWELIJK] -  [VERTROUWELIJK] 44 Dossierstuk 25, Antwoorden van Transavia, datum 26 mei 2020 - Bijlage 1: Personnel &amp; Access Control Standard. 45 Zie Dossierstuk 25, Antwoorden van Transavia, datum 26 mei 2020. 46 Zie Dossierstuk 25, Antwoorden van Transavia, datum 26 mei 2020 - Bijlage 1: Personnel &amp; Access Control Standard. 47 Zie Dossierstuk 25, Antwoorden van Transavia, datum 26 mei 2020 - Bijlage 1: Personnel &amp; Access Control Standard. <!-- image --> Datum 23 september 2021 ## Ons kenmerk [VERTROUWELIJK] Transavia onderscheidt twee typen gebruiker accounts: ' user accounts ' en ' generieke accounts '. De ' user accounts ' betreffen individuele personen. De ' generieke accounts ' bestaan voor meerdere personen of systemen, onder andere voor koppelingen tussen systemen. Inloggen op deze gebruikers vindt veelal automatisch plaats volgens Transavia. 48 De AP heeft aan Transavia gevraagd waarom de accounts die betrokken waren bij de inbreuk niet voldeden aan de eigen standaarden van Transavia. Transavia geeft in haar antwoord aan dat de focus lag op ' user accounts ' als het gaat om naleving van het wachtwoordenbeleid. Dit zijn in verhouding meer accounts en er werd geacht dat hieruit de meeste risico's zouden voortvloeien. Ook heeft Transavia aangegeven dat deze aanpak de ' awareness ' zou verhogen binnen de organisatie. Vanwege deze focus zouden de tekortkomingen voor de generieke accounts betrokken in de inbreuk niet zijn opgemerkt. 49 In het wachtwoordbeleid staat verder dat er voor ' remote access ' meerfactorauthenticatie vereist is. 50 Uit het rapport blijkt dat dit niet het geval was voor de gebruikers waarmee de aanvaller toegang heeft kunnen verkrijgen. Zo is toegang geweest tot een Citrix omgeving zonder meerfactorauthenticatie. De externe dienstverlener geeft als een van de aanbevelingen aan Transavia het implementeren van meerfactorauthenticatie voor gebruikers wiens accounts toegankelijk zijn vanaf het internet of in ieder geval voor gebruikers met veel rechten. 51 Citrix zelf adviseert zelf ook om meerfactorauthenticatie voor het gebruik van hun applicatie in te voeren. 52 De AP heeft aan Transavia gevraagd waarom toegang mogelijk was tot een telewerkomgeving zonder gebruik te maken van meerfactorauthenticatie bij de accounts betrokken in de inbreuk. 53 Als antwoord heeft Transavia aangegeven dat eerst voor de ' user accounts ' is begonnen met de uitrol van deze maatregelen. De implementatie van deze maatregelen bij de ' user accounts ' duurde langer dan verwacht. Vliegend personeel maakt bij haar werkzaamheden gebruik van applicaties die nodig zijn voor een veilige vlucht. Indien een maatregel zoals meerdere factoren authenticatie vertraging zou veroorzaken, zou dit grote vertragingen bij vluchten kunnen veroorzaken. ' Generieke accounts ' hadden lagere prioriteit bij Transavia. Omdat de implementatie bij het vliegend personeel vertraagd was, was de implementatie bij de ' generieke accounts ' ook vertraagd. 54 48 Zie Dossierstuk 38, Antwoorden van Transavia datum 24 september 2020. 49 Zie Dossierstuk 38, Antwoorden van Transavia datum 24 september 2020. 50 Zie Dossierstuk 25, Antwoorden van Transavia, datum 26 mei 2020 - Bijlage 1: Personnel &amp; Access Control Standard. 51 Zie Dossierstuk 11, rapport van 5 december 2019, pagina 21. 52 Zie Dossierstuk 40, Citrix best practices, 9 april 2019. 53 Dossierstuk 30, Brief AP aan Transavia van 4 september 2020. 54 Zie Dossierstuk 38, Antwoorden van Transavia datum 24 september 2020. <!-- image --> Datum 23 september 2021 ## Ons kenmerk [VERTROUWELIJK] De AP heeft aan Transavia gevraagd of periodieke controles plaatsvonden van het beveiligingsbeleid en de feitelijke implementatie hiervan. Transavia heeft hierop aangegeven dat er meerdere periodieke controles plaatsvinden: 55 -  [VERTROUWELIJK] 56 -  [VERTROUWELIJK] -  [VERTROUWELIJK] Bij de [VERTROUWELIJK] controle is ook aangegeven dat voor geprivilegieerde accounts (accounts met veel toegangsrechten) er controle moet plaatsvinden of de wachtwoorden voldoen aan het beleid van Transavia. 57 Transavia heeft als voorbeeld hiervan de resultaten aangeleverd van een [VERTROUWELIJK] controle van 2019, kwartaal 3. De bevindingen gaan over de periode van 12 maanden vóór het onderzoek. Hierin staan positieve en negatieve resultaten aangegeven. Bij meerdere systemen is hier aangegeven dat de wachtwoorden niet voldeden aan het beleid van Transavia. 58 De AP stelt vast dat de gebruikte wachtwoorden in de aanval niet aan de eisen voldeden van het wachtwoordbeleid van Transavia. Ook was voor deze gebruikers geen meerfactorauthenticatie aanwezig, terwijl deze gebruikers wel toegankelijk waren via het internet of via telewerk software. ## 2.3.2 Toegang binnen het [VERTROUWELIJK] domein De aanvaller had tijdens de inbreuk toegang tot vrijwel het hele [VERTROUWELIJK] domein. Transavia heeft meer netwerksegmentatie als vervolgmaatregel doorgevoerd. 59 Volgens het Nationaal Cyber Security Centrum (NCSC) is netwerksegmentatie het ' netwerk opdelen in functionele segmenten '. Met netwerksegmentatie worden alleen de systemen die onderling moeten communiceren samen in aparte segmenten geplaatst. ' Gebruikers krijgen alleen toegang tot de segmenten die zij nodig hebben.' . 60 De AP heeft aan Transavia gevraagd of de aanvaller bij de systemen waar automatisch toegang toe is verkregen ook andere zaken had kunnen doen zoals gegevens kopiëren, inzien of anderzijds bewerken. 61 Transavia heeft aangegeven dat de aanvaller deze mogelijkheid had. In de schriftelijke reactie noemt Transavia een aantal beveiligingsmaatregelen die van kracht waren op het moment van de inbreuk: ' Op het moment van de inbreuk had Transavia verschillende maatregelen getroffen in het kader van haar beveiligingsbeleid om de gevolgen van een onbevoegde inlogpoging te voorkomen, waaronder monitoring. Zo werden met het voor Transavia door haar IT-leverancier ingerichte Security Operations Centre de computer- en netwerkactiviteiten van Transavia in de gaten gehouden en gecontroleerd op afwijkende activiteiten. Via dit systeem 55 Zie Dossierstuk 38, Antwoorden van Transavia datum 24 september 2020. 56 Dossierstuk 38, Antwoorden van Transavia datum 24 september 2020 - Bijlage 6: [VERTROUWELIJK]. 57 Dossierstuk 38, Antwoorden van Transavia datum 24 september 2020 - Bijlage 6: [VERTROUWELIJK]. 58 Dossierstuk 38, Antwoorden van Transavia datum 24 september 2020 - Bijlage 7: Resultaten [VERTROUWELIJK] 2019 - Q3. 59 Zie Dossierstuk 25, Antwoorden van Transavia, datum 26 mei 2020. 60 Zie Dossierstuk 41, NCSC, Ransomware, maatregelen voor het voorkomen, beperken en herstellen van een ransomware-aanval, juni 2020. 61 Dossierstuk 30, Brief AP aan Transavia van 4 september 2020. <!-- image --> Datum 23 september 2021 Ons kenmerk [VERTROUWELIJK] ontving Transavia op 21 oktober 2019 de beveiligingsmelding van haar IT-leverancier die duidde op ongeautoriseerde toegang tot het IT-landschap van Transavia.' 62 In het forensisch rapport is aangegeven dat de beheerder logging mogelijkheden had ingericht, waardoor de externe dienstverlener de gebeurtenissen voor een groot gedeelte heeft kunnen reconstrueren. De externe dienstverlener heeft gebruik kunnen maken van de [VERTROUWELIJK] 63 omgeving van Transavia. 64 Uit onderzoek bleek dat het mogelijk was om bepaalde logbestanden te verwijderen. Aangegeven is dat gedurende een week op tenminste [VERTROUWELIJK] systemen logbestanden zijn verwijderd. Ook is beschreven dat bepaalde logging niet bijgehouden werd in de gecentraliseerde omgeving, waaronder van Citrix en van bepaalde kritieke systemen. Een aanbeveling van de externe dienstverlener is dan ook de centrale logging uit te breiden om de integriteit hiervan te bewaken. Ook zou dit leiden tot betere respons op incidenten. 65 In het forensisch rapport staat verder dat op diverse systemen verouderde besturingssystemen geïnstalleerd waren. Ook staat er dat de geïmplementeerde meerfactorauthenticatie op bepaalde systemen dusdanig was ingeregeld dat een gebruiker zelf een telefoonnummer kon invullen om een tweede factor bericht op te ontvangen. Bepaalde systemen hadden ongecontroleerd toegang tot het internet. Hierdoor heeft de aanvaller kunnen communiceren met externe systemen vanuit het netwerk van Transavia. 66 Tot slot was er onvoldoende netwerk indringer detectie aanwezig was. Hierdoor was er sprake van een beperkt zicht op netwerkactiviteit van de aanvaller. 67 ## 2.4 Maatregelen na de inbreuk Nadat Transavia op 21 oktober 2019 erachter is gekomen dat een aanvaller ongeautoriseerde toegang heeft gehad tot haar systemen, heeft Transavia direct door een externe dienstverlener een forensische analyse laten uitvoeren. Na de vaststelling van de inbreuk heeft Transavia verschillende maatregelen genomen. Transavia heeft onder andere voor alle eindgebruikers en apparaten tweefactor-authenticatie ingevoerd. Daarnaast zijn de wachtwoorden van alle gebruikers- en generieke accounts gereset en zijn wachtwoordvereisten technisch doorgevoerd. Tot slot heeft Transavia haar netwerk opgedeeld in meerdere segmenten. 68 62 Zie Dossierstuk 25, Antwoorden van Transavia, datum 26 mei 2020. 63 [VERTROUWELIJK] maakt het mogelijk om gegevens uit een grote hoeveelheid verschillende bronnen (geautomatiseerd) te analyseren en signaleringen te ontvangen hierop. Een gecentraliseerde omgeving waarbij een systeem logging uit verschillende bronnen verzamelt, analyseert en rapporteert wordt ook wel een Security Information and Event Management (SIEM) genoemd. Zie ook: Dossierstuk 42, NCSC, Handreiking voor implementatie van detectie oplossingen, oktober 2015. 64 Zie Dossierstuk 11, rapport van 5 december 2019, pagina 4. 65 Zie Dossierstuk 11, rapport van 5 december 2019, pagina 23 en 29. 66 Zie Dossierstuk 11, rapport van 5 december 2019, pagina 27 en 28. 67 Zie Dossierstuk 11, rapport van 5 december 2019, pagina 29. 68 Schriftelijke zienswijze Transavia, 28 juni 2021, pagina 7 en 8. <!-- image --> Datum 23 september 2021 Ons kenmerk [VERTROUWELIJK] ## 2.5 Zienswijze Transavia op de vastgestelde feiten en reactie AP Transavia he
A28: Autoriteit_Persoonsgegevens__https___www.autoriteitpersoonsgegevens.nl_uploads_imported_boete_transavia.txt::Rechtsobject | B28: Autoriteit_Persoonsgegevens__https___www.autoriteitpersoonsgegevens.nl_uploads_imported_boete_transavia.txt | C28: AP | D28: Rechtsobject | E28: bestuurlijke boete | G28: bestuurlijke boete | H28: <NONE> | I28: bestuurlijke boete [61349:61367] | L28: bestuurlijke boete | N28: One annotator omitted feature | O28: 0 | P28: 1 | Q28: 0 | R28: 0 | S28: bestuurlijke boete | X28: No | Y28: Needs review | AA28: =IF(X28="Yes","Excluded",IF(COUNTA(U28:W28)=0,"Auto",IF(COUNTA(U28:W28)=3,"Manual","INCOMPLETE"))) -> Auto | AB28: =IF(X28="Yes",0,IF(AA28="Manual",U28,O28)) -> 0 | AC28: =IF(X28="Yes",0,IF(AA28="Manual",V28,P28)) -> 1 | AD28: =IF(X28="Yes",0,IF(AA28="Manual",W28,Q28)) -> 0 | AE28: =IF(X28="Yes","",IF(AND(AC28=0,AD28=0),1,0)) -> 0 | AF28: [...] r de motivering paragraaf 4.3.1 en 4.3.2. <!-- image --> Datum 23 september 2021 ## 5. Dictum De AP legt aan Transavia Airlines C.V. wegens overtreding van artikel 32, eerste en tweede lid, van de AVG een bestuurlijke boete op ten bedrage van: € 400.000 (zegge vierhonderdduizend euro). 84 Hoogachtend, Autoriteit Persoonsgegevens, w.g. drs. C.E. Mur Bestuurslid ## Rechtsmiddelenclausule Indien u het niet eens bent met dit [...]
